Workbook

Sheet GENERAL SUMMARY
B2: Account | C2: Value | F2: Station | G2: Benzine 1 | H2: Benzine 2 | I2: Mezout
B3: Opening Balance (DUE TO SUPPLIER) | C3: ='Daily Halba'!C2 -> 24612 | F3: Halba | G3: =Table_5[[#This Row],[Current]] -> 12390 | H3: ='BM Stock Halba'!E4 -> 9030 | I3: ='BM Stock Halba'!E6 -> 3690
B4: NET IN HALBA | C4: ='Daily Halba'!D2 -> 1132797 | F4: Tekrit | G4: ='BM Stock Tekrit'!E3 -> 1980 | H4: =Table_14[[#This Row],[Current]] -> 1191 | I4: ='BM Stock Tekrit'!E6 -> 309.466
B5: Cost of Stock HALBA | C5: ='BM Stock Halba'!N184 -> 1100428.9 | F5: Total | G5: =SUM(G3:G4) -> 14370 | H5: =SUM(H3:H4) -> 10221 | I5: =SUM(I3:I4) -> 3999.466
B6: NET IN TEKRIT | C6: ='Daily Tekrit'!D2 -> 169776.61 | F6: Oil stock Value | G6: =Table1[[#Totals],[28-Jun]] -> 5482.8155
B7: Cost of Stock TEKRIT | C7: ='Daily Tekrit'!E2 -> 157127.91 | F7: Fuel Stock value-Debts | G7: =(G5+H5)*1.228+I5*1.01+C8+G6 -> 60237.854
B8: GENERAL BALANCE to Supplier | C8: =C4+C6-C3-C5-C7+C9 -> 20517.83
B9: Rounding / Unexplained | C9: 113

Sheet Daily Halba
C1: Opening Balance | D1: IN - Net | E1: Total Purchases | F1: Balance
C2: =22221+1600+439+352 -> 24612 | D2: =AS5 -> 1132797 | E2: ='BM Stock Halba'!N184 -> 1100428.9 | F2: =114-(C2-D2+E2) -> 7870.1303
A4: TOTAL | C4: CASH IN | W4: OUT | AS4: NET
C5: =SUM('Daily Halba'!$C$8:$C$524) -> 494093 | E5: =SUM('Daily Halba'!$E$8:$E$524) -> 543418.18 | F5: =SUM('Daily Halba'!$F$8:$F$524) -> 396810 | H5: =SUM('Daily Halba'!$H$8:$H$524) -> 442506 | I5: =SUM('Daily Halba'!$I$8:$I$524) -> 890903 | J5: =SUM('Daily Halba'!$J$8:$J$524) -> 985924.19 | K5: =SUM('Daily Halba'!$K$8:$K$524) -> 314152 | M5: =SUM('Daily Halba'!$M$8:$M$524) -> 294511.26 | N5: =SUM('Daily Halba'!$N$8:$N$524) -> 5121.1739 | O5: =SUM('Daily Halba'!$O$8:$O$524) -> 4902.0257 | P5: =SUM('Daily Halba'!$P$8:$P$524) -> 12661.79 | Q5: =SUM(Q8:Q524) -> 265 | R5: =SUM($R$8:$R$524) -> 5781.32 | S5: =SUM($S$8:$S$524) -> 282267.95 | T5: =SUM($T$8:$T$524) -> 3153.137 | U5: =SUM('Daily Halba'!$U$8:$U$524) -> 1594587.8 | W5: =SUM('Daily Halba'!$W$8:$W$524) -> 265709.08 | Y5: =SUM('Daily Halba'!$Y$8:$Y$524) -> 69219.244 | Z5: =SUM('Daily Halba'!$Z$8:$Z$524) -> -825.5 | AA5: =SUM('Daily Halba'!$AA$8:$AA$524) -> 4347.29 | AB5: =SUM('Daily Halba'!$AB$8:$AB$524) -> 4020.7172 | AC5: =SUM('Daily Halba'!$AC$8:$AC$524) -> 13688.59 | AE5: =SUM('Daily Halba'!$AE$8:$AE$524) -> 25208.597 | AF5: =SUM('Daily Halba'!$AF$8:$AF$524) -> 6000 | AG5: =SUM('Daily Halba'!$AG$8:$AG$524) -> 14568 | AH5: =SUM('Daily Halba'!$AH$8:$AH$524) -> 1153.5741 | AI5: =SUM('Daily Halba'!$AI$8:$AI$524) -> 1891.7312 | AJ5: =SUM('Daily Halba'!$AJ$8:$AJ$524) -> 1943.4593 | AK5: =SUM('Daily Halba'!$AK$8:$AK$524) -> 592.86576 | AL5: =SUM('Daily Halba'!$AL$8:$AL$524) -> 1746 | AM5: =SUM('Daily Halba'!$AM$8:$AM$524) -> 212.22965 | AN5: =SUM('Daily Halba'!$AN$8:$AN$524) -> 28107.86 | AO5: =SUM('Daily Halba'!$AO$8:$AO$524) -> 43500 | AP5: =SUM('Daily Halba'!$AP$8:$AP$524) -> 461790.82 | AS5: =SUM(AS8:AS524) -> 1132797
C6: BENZINE | K6: MEZOUT | N6: OTHER | AA6: PURCHASES | AF6: EXPENSES
A7: Date | B7: Price Change | C7: Benzine 1 L | D7: Benzine 1 P | E7: Total Benzine 1 | F7: Benzine 2 L | G7: Benzine 2 P | H7: Total Benzine 2 | I7: Total Benzine L (1+2) | J7: Total Benzine $ | K7: Mezout L | L7: Mezout P | M7: Total Mezout | N7: Oil | O7: Wash | P7: Gaz | Q7: Fragrence | R7: Kiosk | S7: Payments | T7: Coupon | U7: Total IN | W7: Debts | X7: Internal Sale | Y7: Coupons | Z7: Difference | AA7: Purchase Oil | AB7: Purchase Kiosk | AC7: Purchase Gaz | AD7: Other Purchases | AE7: Total Purchases | AF7: PMNT - Rent | AG7: Salaries | AH7: R&M | AI7: Utilities | AJ7: Client Satisfaction | AK7: Tips | AL7: New Assets | AM7: Other | AN7: Total Expense | AO7: Profit Sharing | AP7: Total OUT | AQ7: Notes | AS7: Daily Total
A8: 45965 | C8: ='ODOMETERS Halba'!J4 -> 1434 | D8: 0.7793 | E8: ='Daily Halba'!$C8*'Daily Halba'!$D8 -> 1117.5162 | F8: ='ODOMETERS Halba'!K4 -> 1304 | G8: 0.7793 | H8: ='Daily Halba'!$F8*'Daily Halba'!$G8 -> 1016.2072 | I8: ='Daily Halba'!$C8+'Daily Halba'!$F8 -> 2738 | J8: ='Daily Halba'!$I8*'Daily Halba'!$G8 -> 2133.7234 | K8: ='ODOMETERS Halba'!L4 -> 587 | L8: 0.7402 | M8: ='Daily Halba'!$K8*'Daily Halba'!$L8 -> 434.4974 | N8: 3 | O8: 10 | S8: 55.57 | T8: 17.55 | U8: =SUM('Daily Halba'!$E8,'Daily Halba'!$H8,$M8:$T8) -> 2654.3408 | W8: 364.79 | Y8: 204.83 | AA8: 61 | AB8: 27.87 | AE8: =SUM(AA8:AD8) -> 88.87 | AG8: 1157 | AN8: =SUM(AF8:AM8) -> 1157 | AP8: =SUM(W8:Z8,AE8,AN8,AO8) -> 1815.49 | AS8: ='Daily Halba'!$U8-'Daily Halba'!$AP8 -> 838.8508
A9: 45966 | C9: ='ODOMETERS Halba'!J5 -> 1035 | D9: 0.7826 | E9: ='Daily Halba'!$C9*'Daily Halba'!$D9 -> 809.991 | F9: ='ODOMETERS Halba'!K5 -> 896 | G9: 0.7826 | H9: ='Daily Halba'!$F9*'Daily Halba'!$G9 -> 701.2096 | I9: ='Daily Halba'!$C9+'Daily Halba'!$F9 -> 1931 | J9: ='Daily Halba'!$I9*'Daily Halba'!$G9 -> 1511.2006 | K9: ='ODOMETERS Halba'!L5 -> 417 | L9: 0.7469 | M9: ='Daily Halba'!$K9*'Daily Halba'!$L9 -> 311.4573 | N9: 2.8 | O9: 8.9 | S9: 30.1 | T9: 12.5 | U9: =SUM('Daily Halba'!$E9,'Daily Halba'!$H9,$M9:$T9) -> 1876.9579 | W9: 177 | Y9: 172.2 | AE9: =SUM(AA9:AD9) -> 0 | AH9: 135 | AM9: 15 | AN9: =SUM(AF9:AM9) -> 150 | AP9: =SUM(W9:Z9,AE9,AN9,AO9) -> 499.2 | AQ9: Glass instalments (150) , Municipality (15) | AS9: ='Daily Halba'!$U9-'Daily Halba'!$AP9 -> 1377.7579
A10: 45967 | C10: ='ODOMETERS Halba'!J6 -> 1214 | D10: 0.7826 | E10: ='Daily Halba'!$C10*'Daily Halba'!$D10 -> 950.0764 | F10: ='ODOMETERS Halba'!K6 -> 974 | G10: 0.7826 | H10: ='Daily Halba'!$F10*'Daily Halba'!$G10 -> 762.2524 | I10: ='Daily Halba'!$C10+'Daily Halba'!$F10 -> 2188 | J10: ='Daily Halba'!$I10*'Daily Halba'!$G10 -> 1712.3288 | K10: ='ODOMETERS Halba'!L6 -> 441 | L10: 0.7469 | M10: ='Daily Halba'!$K10*'Daily Halba'!$L10 -> 329.3829 | N10: 11.57 | O10: 10 | S10: 70 | T10: 15.05 | U10: =SUM('Daily Halba'!$E10,'Daily Halba'!$H10,$M10:$T10) -> 2148.3317 | W10: 204.05 | Y10: 162 | AE10: =SUM(AA10:AD10) -> 0 | AN10: =SUM(AF10:AM10) -> 0 | AP10: =SUM(W10:Z10,AE10,AN10,AO10) -> 366.05 | AS10: ='Daily Halba'!$U10-'Daily Halba'!$AP10 -> 1782.2817
A11: 45968 | B11: Pre Price | C11: ='ODOMETERS Halba'!J7 -> 610 | D11: 0.7826 | E11: ='Daily Halba'!$C11*'Daily Halba'!$D11 -> 477.386 | F11: ='ODOMETERS Halba'!K7 -> 458 | G11: 0.7826 | H11: ='Daily Halba'!$F11*'Daily Halba'!$G11 -> 358.4308 | I11: ='Daily Halba'!$C11+'Daily Halba'!$F11 -> 1068 | J11: ='Daily Halba'!$I11*'Daily Halba'!$G11 -> 835.8168 | K11: ='ODOMETERS Halba'!L7 -> 312 | L11: 0.7469 | M11: ='Daily Halba'!$K11*'Daily Halba'!$L11 -> 233.0328 | N11: 0 | O11: 6.69 | S11: 0 | T11: 19.23 | U11: =SUM('Daily Halba'!$E11,'Daily Halba'!$H11,$M11:$T11) -> 1094.7696 | W11: 142.88 | Y11: 234.61 | AE11: =SUM(AA11:AD11) -> 0 | AN11: =SUM(AF11:AM11) -> 0 | AP11: =SUM(W11:Z11,AE11,AN11,AO11) -> 377.49 | AS11: ='Daily Halba'!$U11-'Daily Halba'!$AP11 -> 717.2796
A12: 45968 | B12: Post Price | C12: ='ODOMETERS Halba'!J8 -> 527 | D12: =(1416000/89700)/20 -> 0.78929766 | E12: ='Daily Halba'!$C12*'Daily Halba'!$D12 -> 415.95987 | F12: ='ODOMETERS Halba'!K8 -> 581 | G12: 0.7893 | H12: ='Daily Halba'!$F12*'Daily Halba'!$G12 -> 458.5833 | I12: ='Daily Halba'!$C12+'Daily Halba'!$F12 -> 1108 | J12: ='Daily Halba'!$I12*'Daily Halba'!$G12 -> 874.5444 | K12: ='ODOMETERS Halba'!L8 -> 169 | L12: =(1368000/89700)/20 -> 0.76254181 | M12: ='Daily Halba'!$K12*'Daily Halba'!$L12 -> 128.86957 | N12: 11.57 | O12: 15.6 | P12: 12.26 | S12: 0 | T12: 14.49 | U12: =SUM('Daily Halba'!$E12,'Daily Halba'!$H12,$M12:$T12) -> 1057.3327 | W12: 60 | Y12: 115.49 | AB12: 390 | AE12: =SUM(AA12:AD12) -> 390 | AN12: =SUM(AF12:AM12) -> 0 | AP12: =SUM(W12:Z12,AE12,AN12,AO12) -> 565.49 | AS12: ='Daily Halba'!$U12-'Daily Halba'!$AP12 -> 491.84273
A13: 45969 | C13: ='ODOMETERS Halba'!J9 -> 1895 | D13: =(1416000/89700)/20 -> 0.78929766 | E13: ='Daily Halba'!$C13*'Daily Halba'!$D13 -> 1495.7191 | F13: ='ODOMETERS Halba'!K9 -> 1059 | G13: 0.7893 | H13: ='Daily Halba'!$F13*'Daily Halba'!$G13 -> 835.8687 | I13: ='Daily Halba'!$C13+'Daily Halba'!$F13 -> 2954 | J13: ='Daily Halba'!$I13*'Daily Halba'!$G13 -> 2331.5922 | K13: ='ODOMETERS Halba'!L9 -> 434 | L13: =(1368000/89700)/20 -> 0.76254181 | M13: ='Daily Halba'!$K13*'Daily Halba'!$L13 -> 330.94314 | N13: 17.57 | O13: 28.72 | S13: 194 | T13: 42.64 | U13: =SUM('Daily Halba'!$E13,'Daily Halba'!$H13,$M13:$T13) -> 2945.4609 | W13: 130.92 | Y13: =273.49+61 -> 334.49 | AC13: 34 | AE13: =SUM(AA13:AD13) -> 34 | AN13: =SUM(AF13:AM13) -> 0 | AP13: =SUM(W13:Z13,AE13,AN13,AO13) -> 499.41 | AS13: ='Daily Halba'!$U13-'Daily Halba'!$AP13 -> 2446.0509
A14: 45970 | C14: ='ODOMETERS Halba'!J10 -> 2088 | D14: 0.7893 | E14: ='Daily Halba'!$C14*'Daily Halba'!$D14 -> 1648.0584 | F14: ='ODOMETERS Halba'!K10 -> 585 | G14: 0.7893 | H14: ='Daily Halba'!$F14*'Daily Halba'!$G14 -> 461.7405 | I14: ='Daily Halba'!$C14+'Daily Halba'!$F14 -> 2673 | J14: ='Daily Halba'!$I14*'Daily Halba'!$G14 -> 2109.7989 | K14: ='ODOMETERS Halba'!L10 -> 2517 | L14: =(1368000/89700)/20 -> 0.76254181 | M14: ='Daily Halba'!$K14*'Daily Halba'!$L14 -> 1919.3177 | N14: 22.57 | O14: 23.41 | P14: 12.26 | S14: 1619 | T14: 23.21 | U14: =SUM('Daily Halba'!$E14,'Daily Halba'!$H14,$M14:$T14) -> 5729.5666 | W14: 1748 | Y14: 236.79 | AE14: =SUM(AA14:AD14) -> 0 | AN14: =SUM(AF14:AM14) -> 0 | AP14: =SUM(W14:Z14,AE14,AN14,AO14) -> 1984.79 | AS14: ='Daily Halba'!$U14-'Daily Halba'!$AP14 -> 3744.7766
A15: 45971 | C15: ='ODOMETERS Halba'!J11 -> 2031 | D15: 0.7893 | E15: ='Daily Halba'!$C15*'Daily Halba'!$D15 -> 1603.0683 | F15: ='ODOMETERS Halba'!K11 -> 428 | G15: 0.7893 | H15: ='Daily Halba'!$F15*'Daily Halba'!$G15 -> 337.8204 | I15: ='Daily Halba'!$C15+'Daily Halba'!$F15 -> 2459 | J15: ='Daily Halba'!$I15*'Daily Halba'!$G15 -> 1940.8887 | K15: ='ODOMETERS Halba'!L11 -> 640 | L15: =(1368000/89700)/20 -> 0.76254181 | M15: ='Daily Halba'!$K15*'Daily Halba'!$L15 -> 488.02676 | N15: 6 | O15: 13 | P15: 24.52 | R15: 77 | S15: 484.5 | T15: 44 | U15: =SUM('Daily Halba'!$E15,'Daily Halba'!$H15,$M15:$T15) -> 3077.9355 | W15: 380.46 | Y15: 435.75 | Z15: 20 | AA15: 52 | AB15: 142.5 | AE15: =SUM(AA15:AD15) -> 194.5 | AN15: =SUM(AF15:AM15) -> 0 | AP15: =SUM(W15:Z15,AE15,AN15,AO15) -> 1030.71 | AS15: ='Daily Halba'!$U15-'Daily Halba'!$AP15 -> 2047.2255
A16: 45972 | B16: Pre Price | C16: ='ODOMETERS Halba'!J12 -> 934 | D16: 0.7893 | E16: ='Daily Halba'!$C16*'Daily Halba'!$D16 -> 737.2062 | F16: ='ODOMETERS Halba'!K12 -> 465 | G16: 0.7893 | H16: ='Daily Halba'!$F16*'Daily Halba'!$G16 -> 367.0245 | I16: ='Daily Halba'!$C16+'Daily Halba'!$F16 -> 1399 | J16: ='Daily Halba'!$I16*'Daily Halba'!$G16 -> 1104.2307 | K16: ='ODOMETERS Halba'!L12 -> 1326 | L16: =(1368000/89700)/20 -> 0.76254181 | M16: ='Daily Halba'!$K16*'Daily Halba'!$L16 -> 1011.1304 | O16: 3 | T16: 21.18 | U16: =SUM('Daily Halba'!$E16,'Daily Halba'!$H16,$M16:$T16) -> 2139.5411 | W16: 886.5 | Y16: 229.9 | Z16: 18 | AE16: =SUM(AA16:AD16) -> 0 | AN16: =SUM(AF16:AM16) -> 0 | AP16: =SUM(W16:Z16,AE16,AN16,AO16) -> 1134.4 | AS16: ='Daily Halba'!$U16-'Daily Halba'!$AP16 -> 1005.1411
A17: 45972 | B17: Post Price | C17: ='ODOMETERS Halba'!J13 -> 910 | D17: 0.7932 | E17: ='Daily Halba'!$C17*'Daily Halba'!$D17 -> 721.812 | F17: ='ODOMETERS Halba'!K13 -> 638 | G17: 0.7932 | H17: ='Daily Halba'!$F17*'Daily Halba'!$G17 -> 506.0616 | I17: ='Daily Halba'!$C17+'Daily Halba'!$F17 -> 1548 | J17: ='Daily Halba'!$I17*'Daily Halba'!$G17 -> 1227.8736 | K17: ='ODOMETERS Halba'!L13 -> 301 | L17: 0.7765 | M17: ='Daily Halba'!$K17*'Daily Halba'!$L17 -> 233.7265 | N17: 7.78 | P17: 24.52 | R17: 54.71 | S17: =2387+59.87+1455+2005 -> 5906.87 | T17: 20 | U17: =SUM('Daily Halba'!$E17,'Daily Halba'!$H17,$M17:$T17) -> 7475.4801 | W17: 138.06 | Y17: 324 | AA17: 29 | AE17: =SUM(AA17:AD17) -> 29 | AN17: =SUM(AF17:AM17) -> 0 | AP17: =SUM(W17:Z17,AE17,AN17,AO17) -> 491.06 | AS17: ='Daily Halba'!$U17-'Daily Halba'!$AP17 -> 6984.4201
A18: 45973 | C18: ='ODOMETERS Halba'!J14 -> 1259 | D18: 0.7932 | E18: ='Daily Halba'!$C18*'Daily Halba'!$D18 -> 998.6388 | F18: ='ODOMETERS Halba'!K14 -> 962 | G18: 0.7932 | H18: ='Daily Halba'!$F18*'Daily Halba'!$G18 -> 763.0584 | I18: ='Daily Halba'!$C18+'Daily Halba'!$F18 -> 2221 | J18: ='Daily Halba'!$I18*'Daily Halba'!$G18 -> 1761.6972 | K18: ='ODOMETERS Halba'!L14 -> 1116 | L18: 0.7765 | M18: ='Daily Halba'!$K18*'Daily Halba'!$L18 -> 866.574 | N18: 37.36 | O18: 23.5 | P18: 36.87 | R18: 81 | S18: 100 | T18: 31.77 | U18: =SUM('Daily Halba'!$E18,'Daily Halba'!$H18,$M18:$T18) -> 2938.7712 | W18: =832.84+20 -> 852.84 | Y18: =31.06+321.89 -> 352.95 | AE18: =SUM(AA18:AD18) -> 0 | AN18: =SUM(AF18:AM18) -> 0 | AP18: =SUM(W18:Z18,AE18,AN18,AO18) -> 1205.79 | AS18: ='Daily Halba'!$U18-'Daily Halba'!$AP18 -> 1732.9812
A19: 45974 | C19: ='ODOMETERS Halba'!J15 -> 1577 | D19: 0.7932 | E19: ='Daily Halba'!$C19*'Daily Halba'!$D19 -> 1250.8764 | F19: ='ODOMETERS Halba'!K15 -> 1044 | G19: 0.7932 | H19: ='Daily Halba'!$F19*'Daily Halba'!$G19 -> 828.1008 | I19: ='Daily Halba'!$C19+'Daily Halba'!$F19 -> 2621 | J19: ='Daily Halba'!$I19*'Daily Halba'!$G19 -> 2078.9772 | K19: ='ODOMETERS Halba'!L15 -> 325 | L19: 0.7765 | M19: ='Daily Halba'!$K19*'Daily Halba'!$L19 -> 252.3625 | O19: 7.8 | R19: 36 | S19: 728 | T19: 35.89 | U19: =SUM('Daily Halba'!$E19,'Daily Halba'!$H19,$M19:$T19) -> 3139.0297 | W19: =30+33.44 -> 63.44 | Y19: =54.35+354 -> 408.35 | AC19: 81.41 | AE19: =SUM(AA19:AD19) -> 81.41 | AI19: 5 | AN19: =SUM(AF19:AM19) -> 5 | AP19: =SUM(W19:Z19,AE19,AN19,AO19) -> 558.2 | AS19: ='Daily Halba'!$U19-'Daily Halba'!$AP19 -> 2580.8297
A20: 45975 | B20: Pre Price | C20: ='ODOMETERS Halba'!J16 -> 517 | D20: 0.7932 | E20: ='Daily Halba'!$C20*'Daily Halba'!$D20 -> 410.0844 | F20: ='ODOMETERS Halba'!K16 -> 471 | G20: 0.7932 | H20: ='Daily Halba'!$F20*'Daily Halba'!$G20 -> 373.5972 | I20: ='Daily Halba'!$C20+'Daily Halba'!$F20 -> 988 | J20: ='Daily Halba'!$I20*'Daily Halba'!$G20 -> 783.6816 | K20: ='ODOMETERS Halba'!L16 -> 287 | L20: 0.7765 | M20: ='Daily Halba'!$K20*'Daily Halba'!$L20 -> 222.8555 | N20: 8.36 | T20: 15.6 | U20: =SUM('Daily Halba'!$E20,'Daily Halba'!$H20,$M20:$T20) -> 1030.4971 | W20: =161.05+22.29 -> 183.34 | Y20: 126.91 | AE20: =SUM(AA20:AD20) -> 0 | AN20: =SUM(AF20:AM20) -> 0 | AP20: =SUM(W20:Z20,AE20,AN20,AO20) -> 310.25 | AS20: ='Daily Halba'!$U20-'Daily Halba'!$AP20 -> 720.2471
A21: 45975 | B21: Post Price | C21: ='ODOMETERS Halba'!J17 -> 651 | D21: 0.8043 | E21: ='Daily Halba'!$C21*'Daily Halba'!$D21 -> 523.5993 | F21: ='ODOMETERS Halba'!K17 -> 434 | G21: 0.8043 | H21: ='Daily Halba'!$F21*'Daily Halba'!$G21 -> 349.0662 | I21: ='Daily Halba'!$C21+'Daily Halba'!$F21 -> 1085 | J21: ='Daily Halba'!$I21*'Daily Halba'!$G21 -> 872.6655 | K21: ='ODOMETERS Halba'!L17 -> 652 | L21: 0.796 | M21: ='Daily Halba'!$K21*'Daily Halba'!$L21 -> 518.992 | N21: 17.14 | O21: 7.8 | P21: 24.52 | R21: 46.75 | S21: 10 | T21: 46.72 | U21: =SUM('Daily Halba'!$E21,'Daily Halba'!$H21,$M21:$T21) -> 1544.5875 | W21: =489+11.13 -> 500.13 | Y21: 187.8 | AB21: 86 | AE21: =SUM(AA21:AD21) -> 86 | AN21: =SUM(AF21:AM21) -> 0 | AP21: =SUM(W21:Z21,AE21,AN21,AO21) -> 773.93 | AS21: ='Daily Halba'!$U21-'Daily Halba'!$AP21 -> 770.6575
A22: 45976 | C22: ='ODOMETERS Halba'!J18 -> 1696 | D22: 0.8043 | E22: ='Daily Halba'!$C22*'Daily Halba'!$D22 -> 1364.0928 | F22: ='ODOMETERS Halba'!K18 -> 820 | G22: 0.8043 | H22: ='Daily Halba'!$F22*'Daily Halba'!$G22 -> 659.526 | I22: ='Daily Halba'!$C22+'Daily Halba'!$F22 -> 2516 | J22: ='Daily Halba'!$I22*'Daily Halba'!$G22 -> 2023.6188 | K22: ='ODOMETERS Halba'!L18 -> 734 | L22: 0.796 | M22: ='Daily Halba'!$K22*'Daily Halba'!$L22 -> 584.264 | N22: 5.57 | O22: 6.68 | P22: 24.5 | R22: 61 | S22: 52.2 | T22: 60.7 | U22: =SUM('Daily Halba'!$E22,'Daily Halba'!$H22,$M22:$T22) -> 2818.5328 | W22: =54.6+45+10.6+296.83 -> 407.03 | Y22: 660.1 | AE22: =SUM(AA22:AD22) -> 0 | AN22: =SUM(AF22:AM22) -> 0 | AP22: =SUM(W22:Z22,AE22,AN22,AO22) -> 1067.13 | AS22: ='Daily Halba'!$U22-'Daily Halba'!$AP22 -> 1751.4028
A23: 45977 | C23: ='ODOMETERS Halba'!J19 -> 1921 | D23: 0.8043 | E23: ='Daily Halba'!$C23*'Daily Halba'!$D23 -> 1545.0603 | F23: ='ODOMETERS Halba'!K19 -> 968 | G23: 0.8043 | H23: ='Daily Halba'!$F23*'Daily Halba'!$G23 -> 778.5624 | I23: ='Daily Halba'!$C23+'Daily Halba'!$F23 -> 2889 | J23: ='Daily Halba'!$I23*'Daily Halba'!$G23 -> 2323.6227 | K23: ='ODOMETERS Halba'!L19 -> 387 | L23: 0.796 | M23: ='Daily Halba'!$K23*'Daily Halba'!$L23 -> 308.052 | N23: 38.36 | O23: 25.64 | P23: 24.52 | R23: 74 | T23: 18.39 | U23: =SUM('Daily Halba'!$E23,'Daily Halba'!$H23,$M23:$T23) -> 2812.5847 | W23: =5.57+6.68+48.8+31.92+203.68 -> 296.65 | Y23: 198.66 | Z23: -34 | AE23: =SUM(AA23:AD23) -> 0 | AG23: 150 | AN23: =SUM(AF23:AM23) -> 150 | AP23: =SUM(W23:Z23,AE23,AN23,AO23) -> 611.31 | AS23: ='Daily Halba'!$U23-'Daily Halba'!$AP23 -> 2201.2747
A24: 45978 | C24: ='ODOMETERS Halba'!J20 -> 1821 | D24: 0.8043 | E24: ='Daily Halba'!$C24*'Daily Halba'!$D24 -> 1464.6303 | F24: ='ODOMETERS Halba'!K20 -> 882 | G24: 0.8043 | H24: ='Daily Halba'!$F24*'Daily Halba'!$G24 -> 709.3926 | I24: ='Daily Halba'!$C24+'Daily Halba'!$F24 -> 2703 | J24: ='Daily Halba'!$I24*'Daily Halba'!$G24 -> 2174.0229 | K24: ='ODOMETERS Halba'!L20 -> 3761 | L24: 0.796 | M24: ='Daily Halba'!$K24*'Daily Halba'!$L24 -> 2993.756 | N24: 25.78 | O24: 13.91 | P24: 12.26 | R24: 77 | S24: =28+112 -> 140 | T24: 52.61 | U24: =SUM('Daily Halba'!$E24,'Daily Halba'!$H24,$M24:$T24) -> 5489.3389 | W24: =155.64+2678 -> 2833.64 | Y24: 262 | AB24: 190 | AE24: =SUM(AA24:AD24) -> 190 | AN24: =SUM(AF24:AM24) -> 0 | AP24: =SUM(W24:Z24,AE24,AN24,AO24) -> 3285.64 | AS24: ='Daily Halba'!$U24-'Daily Halba'!$AP24 -> 2203.6989
A25: 45979 | B25: Pre Price | C25: ='ODOMETERS Halba'!J21 -> 800 | D25: 0.8043 | E25: ='Daily Halba'!$C25*'Daily Halba'!$D25 -> 643.44 | F25: ='ODOMETERS Halba'!K21 -> 445 | G25: 0.8043 | H25: ='Daily Halba'!$F25*'Daily Halba'!$G25 -> 357.9135 | I25: ='Daily Halba'!$C25+'Daily Halba'!$F25 -> 1245 | J25: ='Daily Halba'!$I25*'Daily Halba'!$G25 -> 1001.3535 | K25: ='ODOMETERS Halba'!L21 -> 71 | L25: 0.796 | M25: ='Daily Halba'!$K25*'Daily Halba'!$L25 -> 56.516 | N25: 6 | S25: 770 | T25: 15.82 | U25: =SUM('Daily Halba'!$E25,'Daily Halba'!$H25,$M25:$T25) -> 1849.6895 | Y25: 230.43 | Z25: 6 | AE25: =SUM(AA25:AD25) -> 0 | AN25: =SUM(AF25:AM25) -> 0 | AP25: =SUM(W25:Z25,AE25,AN25,AO25) -> 236.43 | AS25: ='Daily Halba'!$U25-'Daily Halba'!$AP25 -> 1613.2595
A26: 45979 | B26: Post Price | C26: ='ODOMETERS Halba'!J22 -> 773 | D26: 0.8082 | E26: ='Daily Halba'!$C26*'Daily Halba'!$D26 -> 624.7386 | F26: ='ODOMETERS Halba'!K22 -> 406 | G26: 0.8082 | H26: ='Daily Halba'!$F26*'Daily Halba'!$G26 -> 328.1292 | I26: ='Daily Halba'!$C26+'Daily Halba'!$F26 -> 1179 | J26: ='Daily Halba'!$I26*'Daily Halba'!$G26 -> 952.8678 | K26: ='ODOMETERS Halba'!L22 -> 643 | L26: 0.801 | M26: ='Daily Halba'!$K26*'Daily Halba'!$L26 -> 515.043 | N26: 6 | O26: 13.37 | R26: 36 | S26: 150 | T26: =8.5+23.69 -> 32.19 | U26: =SUM('Daily Halba'!$E26,'Daily Halba'!$H26,$M26:$T26) -> 1705.4708 | W26: =80+214+190 -> 484 | Z26: 47 | AA26: =64+80 -> 144 | AB26: =63.54 -> 63.54 | AC26: 70 | AE26: =SUM(AA26:AD26) -> 277.54 | AJ26: 80 | AN26: =SUM(AF26:AM26) -> 80 | AP26: =SUM(W26:Z26,AE26,AN26,AO26) -> 888.54 | AQ26: Klinex | AS26: ='Daily Halba'!$U26-'Daily Halba'!$AP26 -> 816.9308
A27: 45980 | C27: ='ODOMETERS Halba'!J23 -> 1436 | D27: 0.8082 | E27: ='Daily Halba'!$C27*'Daily Halba'!$D27 -> 1160.5752 | F27: ='ODOMETERS Halba'!K23 -> 1345 | G27: 0.8082 | H27: ='Daily Halba'!$F27*'Daily Halba'!$G27 -> 1087.029 | I27: ='Daily Halba'!$C27+'Daily Halba'!$F27 -> 2781 | J27: ='Daily Halba'!$I27*'Daily Halba'!$G27 -> 2247.6042 | K27: ='ODOMETERS Halba'!L23 -> 662 | L27: 0.801 | M27: ='Daily Halba'!$K27*'Daily Halba'!$L27 -> 530.262 | N27: 8.3 | O27: =15.6+2.2 -> 17.8 | P27: 36.7 | R27: 31 | S27: 158 | T27: 56 | U27: =SUM('Daily Halba'!$E27,'Daily Halba'!$H27,$M27:$T27) -> 3085.6662 | W27: =207-125-7 -> 75 | Y27: =350.75+344.4 -> 695.15 | AE27: =SUM(AA27:AD27) -> 0 | AH27: 125 | AI27: =7 -> 7 | AN27: =SUM(AF27:AM27) -> 132 | AP27: =SUM(W27:Z27,AE27,AN27,AO27) -> 902.15 | AQ27: Kiosk Paint | AS27: ='Daily Halba'!$U27-'Daily Halba'!$AP27 -> 2183.5162
A28: 45981 | C28: ='ODOMETERS Halba'!J24 -> 1442 | D28: 0.8082 | E28: ='Daily Halba'!$C28*'Daily Halba'!$D28 -> 1165.4244 | F28: ='ODOMETERS Halba'!K24 -> 898 | G28: 0.8082 | H28: ='Daily Halba'!$F28*'Daily Halba'!$G28 -> 725.7636 | I28: ='Daily Halba'!$C28+'Daily Halba'!$F28 -> 2340 | J28: ='Daily Halba'!$I28*'Daily Halba'!$G28 -> 1891.188 | K28: ='ODOMETERS Halba'!L24 -> 936 | L28: 0.801 | M28: ='Daily Halba'!$K28*'Daily Halba'!$L28 -> 749.736 | N28: 5.57 | O28: 21.18 | P28: 12.26 | Q28: 25 | R28: 57 | S28: 4300 | T28: 39.52 | U28: =SUM('Daily Halba'!$E28,'Daily Halba'!$H28,$M28:$T28) -> 7101.454 | W28: =20.6+395 -> 415.6 | Y28: =149+323.39+247 -> 719.39 | Z28: 47 | AA28: 133 | AB28: 220 | AC28: 81.96 | AE28: =SUM(AA28:AD28) -> 434.96 | AN28: =SUM(AF28:AM28) -> 0 | AP28: =SUM(W28:Z28,AE28,AN28,AO28) -> 1616.95 | AS28: ='Daily Halba'!$U28-'Daily Halba'!$AP28 -> 5484.504
A29: 45982 | B29: Pre Price | C29: ='ODOMETERS Halba'!J25 -> 632 | D29: 0.8082 | E29: ='Daily Halba'!$C29*'Daily Halba'!$D29 -> 510.7824 | F29: ='ODOMETERS Halba'!K25 -> 497 | G29: 0.8082 | H29: ='Daily Halba'!$F29*'Daily Halba'!$G29 -> 401.6754 | I29: ='Daily Halba'!$C29+'Daily Halba'!$F29 -> 1129 | J29: ='Daily Halba'!$I29*'Daily Halba'!$G29 -> 912.4578 | K29: ='ODOMETERS Halba'!L25 -> 188 | L29: 0.801 | M29: ='Daily Halba'!$K29*'Daily Halba'!$L29 -> 150.588 | T29: 5.79 | U29: =SUM('Daily Halba'!$E29,'Daily Halba'!$H29,$M29:$T29) -> 1068.8358 | W29: 41.18 | Y29: =68.69+1812 -> 1880.69 | AE29: =SUM(AA29:AD29) -> 0 | AH29: 290 | AN29: =SUM(AF29:AM29) -> 290 | AP29: =SUM(W29:Z29,AE29,AN29,AO29) -> 2211.87 | AQ29: Mezout tank hatch repair and hoover purchase | AS29: ='Daily Halba'!$U29-'Daily Halba'!$AP29 -> -1143.0342
A30: 45982 | B30: Post Price | C30: ='ODOMETERS Halba'!J26 -> 827 | D30: 0.8127 | E30: ='Daily Halba'!$C30*'Daily Halba'!$D30 -> 672.1029 | F30: ='ODOMETERS Halba'!K26 -> 835 | G30: 0.8127 | H30: ='Daily Halba'!$F30*'Daily Halba'!$G30 -> 678.6045 | I30: ='Daily Halba'!$C30+'Daily Halba'!$F30 -> 1662 | J30: ='Daily Halba'!$I30*'Daily Halba'!$G30 -> 1350.7074 | K30: ='ODOMETERS Halba'!L26 -> 1076 | L30: 0.811 | M30: ='Daily Halba'!$K30*'Daily Halba'!$L30 -> 872.636 | N30: 6 | O30: 17.91 | Q30: 5 | R30: 37 | T30: 8.58 | U30: =SUM('Daily Halba'!$E30,'Daily Halba'!$H30,$M30:$T30) -> 2297.8334 | W30: =766+554 -> 1320 | Y30: 83.7 | AA30: 104 | AE30: =SUM(AA30:AD30) -> 104 | AN30: =SUM(AF30:AM30) -> 0 | AP30: =SUM(W30:Z30,AE30,AN30,AO30) -> 1507.7 | AS30: ='Daily Halba'!$U30-'Daily Halba'!$AP30 -> 790.1334
A31: 45983 | C31: ='ODOMETERS Halba'!J27 -> 1892 | D31: 0.8127 | E31: ='Daily Halba'!$C31*'Daily Halba'!$D31 -> 1537.6284 | F31: ='ODOMETERS Halba'!K27 -> 1240 | G31: 0.8127 | H31: ='Daily Halba'!$F31*'Daily Halba'!$G31 -> 1007.748 | I31: ='Daily Halba'!$C31+'Daily Halba'!$F31 -> 3132 | J31: ='Daily Halba'!$I31*'Daily Halba'!$G31 -> 2545.3764 | K31: ='ODOMETERS Halba'!L27 -> 1531 | L31: 0.811 | M31: ='Daily Halba'!$K31*'Daily Halba'!$L31 -> 1241.641 | N31: 13.54 | O31: 20 | P31: 12.26 | R31: =17+87 -> 104 | S31: 611 | T31: 15.83 | U31: =SUM('Daily Halba'!$E31,'Daily Halba'!$H31,$M31:$T31) -> 4563.6474 | W31: =272.55+892 -> 1164.55 | Y31: 116 | AE31: =SUM(AA31:AD31) -> 0 | AN31: =SUM(AF31:AM31) -> 0 | AP31: =SUM(W31:Z31,AE31,AN31,AO31) -> 1280.55 | AS31: ='Daily Halba'!$U31-'Daily Halba'!$AP31 -> 3283.0974
A32: 45984 | C32: ='ODOMETERS Halba'!J28 -> 1682 | D32: 0.8127 | E32: ='Daily Halba'!$C32*'Daily Halba'!$D32 -> 1366.9614 | F32: ='ODOMETERS Halba'!K28 -> 771 | G32: 0.8127 | H32: ='Daily Halba'!$F32*'Daily Halba'!$G32 -> 626.5917 | I32: ='Daily Halba'!$C32+'Daily Halba'!$F32 -> 2453 | J32: ='Daily Halba'!$I32*'Daily Halba'!$G32 -> 1993.5531 | K32: ='ODOMETERS Halba'!L28 -> 246 | L32: 0.811 | M32: ='Daily Halba'!$K32*'Daily Halba'!$L32 -> 199.506 | N32: 15.57 | O32: 17.83 | R32: 64 | S32: 2.45 | U32: =SUM('Daily Halba'!$E32,'Daily Halba'!$H32,$M32:$T32) -> 2292.9091 | W32: 42.8 | Y32: 48 | AE32: =SUM(AA32:AD32) -> 0 | AN32: =SUM(AF32:AM32) -> 0 | AP32: =SUM(W32:Z32,AE32,AN32,AO32) -> 90.8 | AS32: ='Daily Halba'!$U32-'Daily Halba'!$AP32 -> 2202.1091
A33: 45985 | C33: ='ODOMETERS Halba'!J29 -> 1407 | D33: 0.8127 | E33: ='Daily Halba'!$C33*'Daily Halba'!$D33 -> 1143.4689 | F33: ='ODOMETERS Halba'!K29 -> 969 | G33: 0.8127 | H33: ='Daily Halba'!$F33*'Daily Halba'!$G33 -> 787.5063 | I33: ='Daily Halba'!$C33+'Daily Halba'!$F33 -> 2376 | J33: ='Daily Halba'!$I33*'Daily Halba'!$G33 -> 1930.9752 | K33: ='ODOMETERS Halba'!L29 -> 1205 | L33: 0.811 | M33: ='Daily Halba'!$K33*'Daily Halba'!$L33 -> 977.255 | N33: 8.36 | O33: 7.8 | R33: 216 | S33: =947+7741 -> 8688 | T33: 13.37 | U33: =SUM('Daily Halba'!$E33,'Daily Halba'!$H33,$M33:$T33) -> 11841.76 | W33: =33.44+159+616+50 -> 858.44 | Y33: =63.39+361 -> 424.39 | AB33: =59.75+40+118 -> 217.75 | AE33: =SUM(AA33:AD33) -> 217.75 | AN33: =SUM(AF33:AM33) -> 0 | AP33: =SUM(W33:Z33,AE33,AN33,AO33) -> 1500.58 | AS33: ='Daily Halba'!$U33-'Daily Halba'!$AP33 -> 10341.18
A34: 45986 | B34: Pre Price | C34: ='ODOMETERS Halba'!J30 -> 861 | D34: 0.8127 | E34: ='Daily Halba'!$C34*'Daily Halba'!$D34 -> 699.7347 | F34: ='ODOMETERS Halba'!K30 -> 329 | G34: 0.8127 | H34: ='Daily Halba'!$F34*'Daily Halba'!$G34 -> 267.3783 | I34: ='Daily Halba'!$C34+'Daily Halba'!$F34 -> 1190 | J34: ='Daily Halba'!$I34*'Daily Halba'!$G34 -> 967.113 | K34: ='ODOMETERS Halba'!L30 -> 117 | L34: 0.811 | M34: ='Daily Halba'!$K34*'Daily Halba'!$L34 -> 94.887 | P34: 12.26 | T34: 7.8 | U34: =SUM('Daily Halba'!$E34,'Daily Halba'!$H34,$M34:$T34) -> 1082.06 | W34: 10 | Y34: =65+36.5 -> 101.5 | AE34: =SUM(AA34:AD34) -> 0 | AN34: =SUM(AF34:AM34) -> 0 | AP34: =SUM(W34:Z34,AE34,AN34,AO34) -> 111.5 | AS34: ='Daily Halba'!$U34-'Daily Halba'!$AP34 -> 970.56
A35: 45986 | B35: Post Price | C35: ='ODOMETERS Halba'!J31 -> 774 | D35: 0.8138 | E35: ='Daily Halba'!$C35*'Daily Halba'!$D35 -> 629.8812 | F35: ='ODOMETERS Halba'!K31 -> 583 | G35: 0.8138 | H35: ='Daily Halba'!$F35*'Daily Halba'!$G35 -> 474.4454 | I35: ='Daily Halba'!$C35+'Daily Halba'!$F35 -> 1357 | J35: ='Daily Halba'!$I35*'Daily Halba'!$G35 -> 1104.3266 | K35: ='ODOMETERS Halba'!L31 -> 349 | L35: 0.8138 | M35: ='Daily Halba'!$K35*'Daily Halba'!$L35 -> 284.0162 | N35: 19.57 | O35: 3 | P35: 36.78 | R35: 43 | T35: 9.19 | U35: =SUM('Daily Halba'!$E35,'Daily Halba'!$H35,$M35:$T35) -> 1499.8828 | W35: =118.71+5+80 -> 203.71 | Y35: =70.8+81.38+170 -> 322.18 | AE35: =SUM(AA35:AD35) -> 0 | AN35: =SUM(AF35:AM35) -> 0 | AP35: =SUM(W35:Z35,AE35,AN35,AO35) -> 525.89 | AS35: ='Daily Halba'!$U35-'Daily Halba'!$AP35 -> 973.9928
A36: 45987 | C36: ='ODOMETERS Halba'!J32 -> 1141 | D36: 0.8138 | E36: ='Daily Halba'!$C36*'Daily Halba'!$D36 -> 928.5458 | F36: ='ODOMETERS Halba'!K32 -> 856 | G36: 0.8138 | H36: ='Daily Halba'!$F36*'Daily Halba'!$G36 -> 696.6128 | I36: ='Daily Halba'!$C36+'Daily Halba'!$F36 -> 1997 | J36: ='Daily Halba'!$I36*'Daily Halba'!$G36 -> 1625.1586 | K36: ='ODOMETERS Halba'!L32 -> 472 | L36: 0.8138 | M36: ='Daily Halba'!$K36*'Daily Halba'!$L36 -> 384.1136 | O36: 3 | P36: 49.13 | R36: 36 | U36: =SUM('Daily Halba'!$E36,'Daily Halba'!$H36,$M36:$T36) -> 2097.4022 | W36: =10.57+63.57+164.38 -> 238.52 | AB36: =254+17.83 -> 271.83 | AE36: =SUM(AA36:AD36) -> 271.83 | AI36: 10.57 | AK36: 16.72 | AN36: =SUM(AF36:AM36) -> 27.29 | AP36: =SUM(W36:Z36,AE36,AN36,AO36) -> 537.64 | AS36: ='Daily Halba'!$U36-'Daily Halba'!$AP36 -> 1559.7622
A37: 45988 | C37: ='ODOMETERS Halba'!J33 -> 1699 | D37: 0.8138 | E37: ='Daily Halba'!$C37*'Daily Halba'!$D37 -> 1382.6462 | F37: ='ODOMETERS Halba'!K33 -> 1015 | G37: 0.8138 | H37: ='Daily Halba'!$F37*'Daily Halba'!$G37 -> 826.007 | I37: ='Daily Halba'!$C37+'Daily Halba'!$F37 -> 2714 | J37: ='Daily Halba'!$I37*'Daily Halba'!$G37 -> 2208.6532 | K37: ='ODOMETERS Halba'!L33 -> 406 | L37: 0.8138 | M37: ='Daily Halba'!$K37*'Daily Halba'!$L37 -> 330.4028 | N37: 33.93 | O37: 17.83 | P37: 24.52 | Q37: 10 | R37: 54 | S37: 100 | T37: 26.68 | U37: =SUM('Daily Halba'!$E37,'Daily Halba'!$H37,$M37:$T37) -> 2806.016 | W37: 43.18 | Y37: =203.45+65.1 -> 268.55 | AB37: 209 | AC37: 165.5 | AE37: =SUM(AA37:AD37) -> 374.5 | AI37: 6.51 | AN37: =SUM(AF37:AM37) -> 6.51 | AP37: =SUM(W37:Z37,AE37,AN37,AO37) -> 692.74 | AS37: ='Daily Halba'!$U37-'Daily Halba'!$AP37 -> 2113.276
A38: 45989 | C38: ='ODOMETERS Halba'!J34 -> 1674 | D38: 0.8138 | E38: ='Daily Halba'!$C38*'Daily Halba'!$D38 -> 1362.3012 | F38: ='ODOMETERS Halba'!K34 -> 1419 | G38: 0.8138 | H38: ='Daily Halba'!$F38*'Daily Halba'!$G38 -> 1154.7822 | I38: ='Daily Halba'!$C38+'Daily Halba'!$F38 -> 3093 | J38: ='Daily Halba'!$I38*'Daily Halba'!$G38 -> 2517.0834 | K38: ='ODOMETERS Halba'!L34 -> 721 | L38: 0.8138 | M38: ='Daily Halba'!$K38*'Daily Halba'!$L38 -> 586.7498 | N38: 25.57 | O38: 8.7 | P38: 12.26 | R38: 125 | S38: =80+570*0.8138 -> 543.866 | T38: 18.29 | U38: =SUM('Daily Halba'!$E38,'Daily Halba'!$H38,$M38:$T38) -> 3837.5192 | X38: =570*0.8138 -> 463.866 | Y38: 69.98 | AA38: =217.57+309 -> 526.57 | AB38: 26.3 | AE38: =SUM(AA38:AD38) -> 552.87 | AN38: =SUM(AF38:AM38) -> 0 | AP38: =SUM(W38:Z38,AE38,AN38,AO38) -> 1086.716 | AS38: ='Daily Halba'!$U38-'Daily Halba'!$AP38 -> 2750.8032
A39: 45990 | C39: ='ODOMETERS Halba'!J35 -> 1688 | D39: 0.8138 | E39: ='Daily Halba'!$C39*'Daily Halba'!$D39 -> 1373.6944 | F39: ='ODOMETERS Halba'!K35 -> 1199 | G39: 0.8138 | H39: ='Daily Halba'!$F39*'Daily Halba'!$G39 -> 975.7462 | I39: ='Daily Halba'!$C39+'Daily Halba'!$F39 -> 2887 | J39: ='Daily Halba'!$I39*'Daily Halba'!$G39 -> 2349.4406 | K39: ='ODOMETERS Halba'!L35 -> 592 | L39: 0.8071 | M39: ='Daily Halba'!$K39*'Daily Halba'!$L39 -> 477.8032 | N39: 24.36 | O39: 12.26 | P39: 12.26 | R39: 57 | T39: 3.34 | U39: =SUM('Daily Halba'!$E39,'Daily Halba'!$H39,$M39:$T39) -> 2936.4638 | W39: 242 | Y39: 32.55 | AA39: 250 | AE39: =SUM(AA39:AD39) -> 250 | AI39: 7 | AJ39: 238 | AN39: =SUM(AF39:AM39) -> 245 | AP39: =SUM(W39:Z39,AE39,AN39,AO39) -> 769.55 | AS39: ='Daily Halba'!$U39-'Daily Halba'!$AP39 -> 2166.9138
A40: 45991 | C40: ='ODOMETERS Halba'!J36 -> 1440 | D40: 0.8138 | E40: ='Daily Halba'!$C40*'Daily Halba'!$D40 -> 1171.872 | F40: ='ODOMETERS Halba'!K36 -> 921 | G40: 0.8138 | H40: ='Daily Halba'!$F40*'Daily Halba'!$G40 -> 749.5098 | I40: ='Daily Halba'!$C40+'Daily Halba'!$F40 -> 2361 | J40: ='Daily Halba'!$I40*'Daily Halba'!$G40 -> 1921.3818 | K40: ='ODOMETERS Halba'!L36 -> 762 | L40: 0.8071 | M40: ='Daily Halba'!$K40*'Daily Halba'!$L40 -> 615.0102 | N40: 20 | O40: 17.8 | P40: 36.87 | R40: 58 | T40: 1.67 | U40: =SUM('Daily Halba'!$E40,'Daily Halba'!$H40,$M40:$T40) -> 2670.732 | W40: =30+30+20+242 -> 322 | Y40: 45.5 | AE40: =SUM(AA40:AD40) -> 0 | AI40: 6 | AN40: =SUM(AF40:AM40) -> 6 | AP40: =SUM(W40:Z40,AE40,AN40,AO40) -> 373.5 | AS40: ='Daily Halba'!$U40-'Daily Halba'!$AP40 -> 2297.232
A41: 45992 | C41: ='ODOMETERS Halba'!J37 -> 1557 | D41: 0.8138 | E41: ='Daily Halba'!$C41*'Daily Halba'!$D41 -> 1267.0866 | F41: ='ODOMETERS Halba'!K37 -> 929 | G41: 0.8138 | H41: ='Daily Halba'!$F41*'Daily Halba'!$G41 -> 756.0202 | I41: ='Daily Halba'!$C41+'Daily Halba'!$F41 -> 2486 | J41: ='Daily Halba'!$I41*'Daily Halba'!$G41 -> 2023.1068 | K41: ='ODOMETERS Halba'!L37 -> 5937 | L41: 0.8071 | M41: ='Daily Halba'!$K41*'Daily Halba'!$L41 -> 4791.7527 | N41: 10.87 | O41: 12.26 | P41: 49.05 | R41: 47 | S41: 930 | T41: 1.5 | U41: =SUM('Daily Halba'!$E41,'Daily Halba'!$H41,$M41:$T41) -> 7865.5395 | W41: =14.49+2825+15+50+20+717.5+957 -> 4598.99 | Y41: 16.27 | Z41: 9 | AB41: 10.5 | AE41: =SUM(AA41:AD41) -> 10.5 | AN41: =SUM(AF41:AM41) -> 0 | AP41: =SUM(W41:Z41,AE41,AN41,AO41) -> 4634.76 | AS41: ='Daily Halba'!$U41-'Daily Halba'!$AP41 -> 3230.7795
A42: 45993 | C42: ='ODOMETERS Halba'!J38 -> 1493 | D42: 0.8138 | E42: ='Daily Halba'!$C42*'Daily Halba'!$D42 -> 1215.0034 | F42: ='ODOMETERS Halba'!K38 -> 1128 | G42: 0.8138 | H42: ='Daily Halba'!$F42*'Daily Halba'!$G42 -> 917.9664 | I42: ='Daily Halba'!$C42+'Daily Halba'!$F42 -> 2621 | J42: ='Daily Halba'!$I42*'Daily Halba'!$G42 -> 2132.9698 | K42: ='ODOMETERS Halba'!L38 -> 1282 | L42: 0.8071 | M42: ='Daily Halba'!$K42*'Daily Halba'!$L42 -> 1034.7022 | N42: 14.36 | O42: 13.9 | R42: 79 | S42: =274+140 -> 414 | U42: =SUM('Daily Halba'!$E42,'Daily Halba'!$H42,$M42:$T42) -> 3688.932 | W42: =25.6+300+323+5.6 -> 654.2 | Y42: =108.2+46 -> 154.2 | AB42: 60 | AC42: 106.5 | AE42: =SUM(AA42:AD42) -> 166.5 | AN42: =SUM(AF42:AM42) -> 0 | AP42: =SUM(W42:Z42,AE42,AN42,AO42) -> 974.9 | AS42: ='Daily Halba'!$U42-'Daily Halba'!$AP42 -> 2714.032
A43: 45994 | B43: Pre Price | C43: ='ODOMETERS Halba'!J39 -> 436 | D43: 0.8138 | E43: ='Daily Halba'!$C43*'Daily Halba'!$D43 -> 354.8168 | F43: ='ODOMETERS Halba'!K39 -> 949 | G43: 0.8138 | H43: ='Daily Halba'!$F43*'Daily Halba'!$G43 -> 772.2962 | I43: ='Daily Halba'!$C43+'Daily Halba'!$F43 -> 1385 | J43: ='Daily Halba'!$I43*'Daily Halba'!$G43 -> 1127.113 | K43: ='ODOMETERS Halba'!L39 -> 1482 | L43: 0.8071 | M43: ='Daily Halba'!$K43*'Daily Halba'!$L43 -> 1196.1222 | N43: 8.36 | O43: 5 | P43: 0 | S43: 0 | T43: 6.58 | U43: =SUM('Daily Halba'!$E43,'Daily Halba'!$H43,$M43:$T43) -> 2343.1752 | W43: =10+1130 -> 1140 | Y43: 145.67 | AE43: =SUM(AA43:AD43) -> 0 | AN43: =SUM(AF43:AM43) -> 0 | AP43: =SUM(W43:Z43,AE43,AN43,AO43) -> 1285.67 | AS43: ='Daily Halba'!$U43-'Daily Halba'!$AP43 -> 1057.5052
A44: 45994 | B44: Post Price | C44: ='ODOMETERS Halba'!J40 -> 529 | D44: 0.8161 | E44: ='Daily Halba'!$C44*'Daily Halba'!$D44 -> 431.7169 | F44: ='ODOMETERS Halba'!K40 -> 738 | G44: 0.8161 | H44: ='Daily Halba'!$F44*'Daily Halba'!$G44 -> 602.2818 | I44: ='Daily Halba'!$C44+'Daily Halba'!$F44 -> 1267 | J44: ='Daily Halba'!$I44*'Daily Halba'!$G44 -> 1033.9987 | K44: ='ODOMETERS Halba'!L40 -> 730 | L44: 0.7988 | M44: ='Daily Halba'!$K44*'Daily Halba'!$L44 -> 583.124 | N44: 0 | O44: 7.8 | P44: 12.82 | Q44: 5 | R44: 52 | S44: 72.46 | T44: 21.67 | U44: =SUM('Daily Halba'!$E44,'Daily Halba'!$H44,$M44:$T44) -> 1788.8727 | W44: =172.3+20+79.88+198.3 -> 470.48 | Y44: =31+16 -> 47 | Z44: 20 | AE44: =SUM(AA44:AD44) -> 0 | AI44: 36 | AN44: =SUM(AF44:AM44) -> 36 | AP44: =SUM(W44:Z44,AE44,AN44,AO44) -> 573.48 | AQ44: Electricity ishtirak | AS44: ='Daily Halba'!$U44-'Daily Halba'!$AP44 -> 1215.3927
A45: 45995 | C45: ='ODOMETERS Halba'!J41 -> 1448 | D45: 0.8161 | E45: ='Daily Halba'!$C45*'Daily Halba'!$D45 -> 1181.7128 | F45: ='ODOMETERS Halba'!K41 -> 1487 | G45: 0.8161 | H45: ='Daily Halba'!$F45*'Daily Halba'!$G45 -> 1213.5407 | I45: ='Daily Halba'!$C45+'Daily Halba'!$F45 -> 2935 | J45: ='Daily Halba'!$I45*'Daily Halba'!$G45 -> 2395.2535 | K45: ='ODOMETERS Halba'!L41 -> 1364 | L45: 0.7988 | M45: ='Daily Halba'!$K45*'Daily Halba'!$L45 -> 1089.5632 | N45: 20.36 | O45: 11.14 | P45: 12.82 | Q45: 5 | R45: 82 | S45: 3103 | T45: 1.5 | U45: =SUM('Daily Halba'!$E45,'Daily Halba'!$H45,$M45:$T45) -> 6720.6367 | W45: =42.36+595.1+45+10+20 -> 712.46 | Y45: 97 | AB45: 176 | AC45: 36.79 | AE45: =SUM(AA45:AD45) -> 212.79 | AN45: =SUM(AF45:AM45) -> 0 | AP45: =SUM(W45:Z45,AE45,AN45,AO45) -> 1022.25 | AS45: ='Daily Halba'!$U45-'Daily Halba'!$AP45 -> 5698.3867
A46: 45996 | B46: Pre Price | C46: ='ODOMETERS Halba'!J42 -> 561 | D46: 0.8161 | E46: ='Daily Halba'!$C46*'Daily Halba'!$D46 -> 457.8321 | F46: ='ODOMETERS Halba'!K42 -> 493 | G46: 0.8161 | H46: ='Daily Halba'!$F46*'Daily Halba'!$G46 -> 402.3373 | I46: ='Daily Halba'!$C46+'Daily Halba'!$F46 -> 1054 | J46: ='Daily Halba'!$I46*'Daily Halba'!$G46 -> 860.1694 | K46: ='ODOMETERS Halba'!L42 -> 259 | L46: 0.7988 | M46: ='Daily Halba'!$K46*'Daily Halba'!$L46 -> 206.8892 | N46: 3 | P46: 12.82 | S46: 200 | U46: =SUM('Daily Halba'!$E46,'Daily Halba'!$H46,$M46:$T46) -> 1282.8786 | W46: 158 | Y46: 22.03 | Z46: -10 | AE46: =SUM(AA46:AD46) -> 0 | AN46: =SUM(AF46:AM46) -> 0 | AP46: =SUM(W46:Z46,AE46,AN46,AO46) -> 170.03 | AS46: ='Daily Halba'!$U46-'Daily Halba'!$AP46 -> 1112.8486
A47: 45996 | B47: Post Price | C47: ='ODOMETERS Halba'!J43 -> 1079 | D47: 0.8149 | E47: ='Daily Halba'!$C47*'Daily Halba'!$D47 -> 879.2771 | F47: ='ODOMETERS Halba'!K43 -> 436 | G47: 0.8149 | H47: ='Daily Halba'!$F47*'Daily Halba'!$G47 -> 355.2964 | I47: ='Daily Halba'!$C47+'Daily Halba'!$F47 -> 1515 | J47: ='Daily Halba'!$I47*'Daily Halba'!$G47 -> 1234.5735 | K47: ='ODOMETERS Halba'!L43 -> 1608 | L47: 0.7848 | M47: ='Daily Halba'!$K47*'Daily Halba'!$L47 -> 1261.9584 | N47: 4 | O47: 17.82 | R47: 49 | S47: =765+800+1504 -> 3069 | T47: 1 | U47: =SUM('Daily Halba'!$E47,'Daily Halba'!$H47,$M47:$T47) -> 5637.3519 | W47: =936.26+145+16.72 -> 1097.98 | Y47: 8.15 | AE47: =SUM(AA47:AD47) -> 0 | AG47: =80+300+265+300+50 -> 995 | AI47: 38 | AN47: =SUM(AF47:AM47) -> 1033 | AP47: =SUM(W47:Z47,AE47,AN47,AO47) -> 2139.13 | AQ47: Electricity Bill | AS47: ='Daily Halba'!$U47-'Daily Halba'!$AP47 -> 3498.2219
A48: 45997 | C48: ='ODOMETERS Halba'!J44 -> 1496 | D48: 0.8149 | E48: ='Daily Halba'!$C48*'Daily Halba'!$D48 -> 1219.0904 | F48: ='ODOMETERS Halba'!K44 -> 1229 | G48: 0.8149 | H48: ='Daily Halba'!$F48*'Daily Halba'!$G48 -> 1001.5121 | I48: ='Daily Halba'!$C48+'Daily Halba'!$F48 -> 2725 | J48: ='Daily Halba'!$I48*'Daily Halba'!$G48 -> 2220.6025 | K48: ='ODOMETERS Halba'!L44 -> 429 | L48: 0.7848 | M48: ='Daily Halba'!$K48*'Daily Halba'!$L48 -> 336.6792 | N48: 55.03 | O48: 10.57 | P48: 12.82 | Q48: 10 | R48: 57 | S48: 95.42 | T48: 1.67 | U48: =SUM('Daily Halba'!$E48,'Daily Halba'!$H48,$M48:$T48) -> 2799.7917 | W48: =239+7 -> 246 | Y48: 16.29 | AA48: 75 | AB48: 35 | AE48: =SUM(AA48:AD48) -> 110 | AH48: 350 | AI48: 15 | AN48: =SUM(AF48:AM48) -> 365 | AP48: =SUM(W48:Z48,AE48,AN48,AO48) -> 737.29 | AQ48: Delivery pick up Paint + municipality | AS48: ='Daily Halba'!$U48-'Daily Halba'!$AP48 -> 2062.5017
A49: 45998 | C49: ='ODOMETERS Halba'!J45 -> 1543 | D49: 0.8149 | E49: ='Daily Halba'!$C49*'Daily Halba'!$D49 -> 1257.3907 | F49: ='ODOMETERS Halba'!K45 -> 1156 | G49: 0.8149 | H49: ='Daily Halba'!$F49*'Daily Halba'!$G49 -> 942.0244 | I49: ='Daily Halba'!$C49+'Daily Halba'!$F49 -> 2699 | J49: ='Daily Halba'!$I49*'Daily Halba'!$G49 -> 2199.4151 | K49: ='ODOMETERS Halba'!L45 -> 2844 | L49: 0.7848 | M49: ='Daily Halba'!$K49*'Daily Halba'!$L49 -> 2231.9712 | N49: 11.57 | O49: 11.14 | P49: 12.82 | R49: 91 | S49: =50+788+2174 -> 3012 | T49: 5 | U49: =SUM('Daily Halba'!$E49,'Daily Halba'!$H49,$M49:$T49) -> 7574.9163 | W49: =13.37+2002 -> 2015.37 | Y49: 49 | Z49: 5 | AE49: =SUM(AA49:AD49) -> 0 | AN49: =SUM(AF49:AM49) -> 0 | AP49: =SUM(W49:Z49,AE49,AN49,AO49) -> 2069.37 | AS49: ='Daily Halba'!$U49-'Daily Halba'!$AP49 -> 5505.5463
A50: 45999 | C50: ='ODOMETERS Halba'!J46 -> 1242 | D50: 0.8149 | E50: ='Daily Halba'!$C50*'Daily Halba'!$D50 -> 1012.1058 | F50: ='ODOMETERS Halba'!K46 -> 754 | G50: 0.8149 | H50: ='Daily Halba'!$F50*'Daily Halba'!$G50 -> 614.4346 | I50: ='Daily Halba'!$C50+'Daily Halba'!$F50 -> 1996 | J50: ='Daily Halba'!$I50*'Daily Halba'!$G50 -> 1626.5404 | K50: ='ODOMETERS Halba'!L46 -> 243 | L50: 0.7848 | M50: ='Daily Halba'!$K50*'Daily Halba'!$L50 -> 190.7064 | N50: 21.14 | O50: 14.49 | R50: 56 | S50: 1900 | U50: =SUM('Daily Halba'!$E50,'Daily Halba'!$H50,$M50:$T50) -> 3808.8768 | W50: =46.72+3 -> 49.72 | Z50: 10 | AB50: =25.5+37.68 -> 63.18 | AC50: 48.5 | AE50: =SUM(AA50:AD50) -> 111.68 | AN50: =SUM(AF50:AM50) -> 0 | AP50: =SUM(W50:Z50,AE50,AN50,AO50) -> 171.4 | AS50: ='Daily Halba'!$U50-'Daily Halba'!$AP50 -> 3637.4768
A51: 46000 | B51: Pre Price | C51: ='ODOMETERS Halba'!J47 -> 767 | D51: 0.8149 | E51: ='Daily Halba'!$C51*'Daily Halba'!$D51 -> 625.0283 | F51: ='ODOMETERS Halba'!K47 -> 395 | G51: 0.8149 | H51: ='Daily Halba'!$F51*'Daily Halba'!$G51 -> 321.8855 | I51: ='Daily Halba'!$C51+'Daily Halba'!$F51 -> 1162 | J51: ='Daily Halba'!$I51*'Daily Halba'!$G51 -> 946.9138 | K51: ='ODOMETERS Halba'!L47 -> 134 | L51: 0.7848 | M51: ='Daily Halba'!$K51*'Daily Halba'!$L51 -> 105.1632 | N51: 14.36 | S51: 100 | U51: =SUM('Daily Halba'!$E51,'Daily Halba'!$H51,$M51:$T51) -> 1166.437 | W51: 45.57 | AB51: 380 | AE51: =SUM(AA51:AD51) -> 380 | AN51: =SUM(AF51:AM51) -> 0 | AP51: =SUM(W51:Z51,AE51,AN51,AO51) -> 425.57 | AS51: ='Daily Halba'!$U51-'Daily Halba'!$AP51 -> 740.867
A52: 46000 | B52: Post Price | C52: ='ODOMETERS Halba'!J48 -> 867 | D52: 0.8116 | E52: ='Daily Halba'!$C52*'Daily Halba'!$D52 -> 703.6572 | F52: ='ODOMETERS Halba'!K48 -> 585 | G52: 0.8116 | H52: ='Daily Halba'!$F52*'Daily Halba'!$G52 -> 474.786 | I52: ='Daily Halba'!$C52+'Daily Halba'!$F52 -> 1452 | J52: ='Daily Halba'!$I52*'Daily Halba'!$G52 -> 1178.4432 | K52: ='ODOMETERS Halba'!L48 -> 249 | L52: 0.7748 | M52: ='Daily Halba'!$K52*'Daily Halba'!$L52 -> 192.9252 | O52: 10 | P52: 64 | R52: 31 | S52: 100 | T52: 7.52 | U52: =SUM('Daily Halba'!$E52,'Daily Halba'!$H52,$M52:$T52) -> 1583.8884 | W52: 43.95 | Y52: 109.56 | Z52: -7 | AA52: 54 | AB52: 201 | AE52: =SUM(AA52:AD52) -> 255 | AG52: 83 | AI52: 10 | AN52: =SUM(AF52:AM52) -> 93 | AP52: =SUM(W52:Z52,AE52,AN52,AO52) -> 494.51 | AS52: ='Daily Halba'!$U52-'Daily Halba'!$AP52 -> 1089.3784
A53: 46001 | C53: ='ODOMETERS Halba'!J49 -> 1603 | D53: 0.8116 | E53: ='Daily Halba'!$C53*'Daily Halba'!$D53 -> 1300.9948 | F53: ='ODOMETERS Halba'!K49 -> 1885 | G53: 0.8116 | H53: ='Daily Halba'!$F53*'Daily Halba'!$G53 -> 1529.866 | I53: ='Daily Halba'!$C53+'Daily Halba'!$F53 -> 3488 | J53: ='Daily Halba'!$I53*'Daily Halba'!$G53 -> 2830.8608 | K53: ='ODOMETERS Halba'!L49 -> 2023 | L53: 0.7748 | M53: ='Daily Halba'!$K53*'Daily Halba'!$L53 -> 1567.4204 | N53: 14.86 | O53: 16.72 | P53: 64.1 | R53: 50 | S53: =894+748 -> 1642 | T53: 2.5 | U53: =SUM('Daily Halba'!$E53,'Daily Halba'!$H53,$M53:$T53) -> 6188.4612 | W53: =26.14+1272+811.6 -> 2109.74 | Y53: 46.26 | AB53: 28 | AE53: =SUM(AA53:AD53) -> 28 | AN53: =SUM(AF53:AM53) -> 0 | AP53: =SUM(W53:Z53,AE53,AN53,AO53) -> 2184 | AS53: ='Daily Halba'!$U53-'Daily Halba'!$AP53 -> 4004.4612
A54: 46002 | C54: ='ODOMETERS Halba'!J50 -> 1530 | D54: 0.8116 | E54: ='Daily Halba'!$C54*'Daily Halba'!$D54 -> 1241.748 | F54: ='ODOMETERS Halba'!K50 -> 755 | G54: 0.8116 | H54: ='Daily Halba'!$F54*'Daily Halba'!$G54 -> 612.758 | I54: ='Daily Halba'!$C54+'Daily Halba'!$F54 -> 2285 | J54: ='Daily Halba'!$I54*'Daily Halba'!$G54 -> 1854.506 | K54: ='ODOMETERS Halba'!L50 -> 824 | L54: 0.7748 | M54: ='Daily Halba'!$K54*'Daily Halba'!$L54 -> 638.4352 | N54: 12.82 | O54: 7.8 | P54: 89.74 | R54: 47 | S54: 1665.82 | T54: 18.39 | U54: =SUM('Daily Halba'!$E54,'Daily Halba'!$H54,$M54:$T54) -> 4334.5112 | W54: =35+375 -> 410 | Y54: 30.8 | AB54: 17 | AC54: 161 | AD54: 3152 | AE54: =SUM(AA54:AD54) -> 3330 | AN54: =SUM(AF54:AM54) -> 0 | AP54: =SUM(W54:Z54,AE54,AN54,AO54) -> 3770.8 | AQ54: Mezout purch from abou Charbel (sold on the sopt / paid thru debt) | AS54: ='Daily Halba'!$U54-'Daily Halba'!$AP54 -> 563.7112
A55: 46003 | B55: Pre Price | C55: ='ODOMETERS Halba'!J51 -> 679 | D55: 0.8116 | E55: ='Daily Halba'!$C55*'Daily Halba'!$D55 -> 551.0764 | F55: ='ODOMETERS Halba'!K51 -> 356 | G55: 0.8116 | H55: ='Daily Halba'!$F55*'Daily Halba'!$G55 -> 288.9296 | I55: ='Daily Halba'!$C55+'Daily Halba'!$F55 -> 1035 | J55: ='Daily Halba'!$I55*'Daily Halba'!$G55 -> 840.006 | K55: ='ODOMETERS Halba'!L51 -> 199 | L55: 0.7748 | M55: ='Daily Halba'!$K55*'Daily Halba'!$L55 -> 154.1852 | O55: 5.57 | U55: =SUM('Daily Halba'!$E55,'Daily Halba'!$H55,$M55:$T55) -> 999.7612 | W55: 44 | Z55: 1 | AE55: =SUM(AA55:AD55) -> 0 | AG55: 150 | AI55: 5 | AN55: =SUM(AF55:AM55) -> 155 | AP55: =SUM(W55:Z55,AE55,AN55,AO55) -> 200 | AS55: ='Daily Halba'!$U55-'Daily Halba'!$AP55 -> 799.7612
A56: 46003 | B56: Post Price | C56: ='ODOMETERS Halba'!J52 -> 2314 | D56: 0.8038 | E56: ='Daily Halba'!$C56*'Daily Halba'!$D56 -> 1859.9932 | F56: ='ODOMETERS Halba'!K52 -> 573 | G56: 0.8038 | H56: ='Daily Halba'!$F56*'Daily Halba'!$G56 -> 460.5774 | I56: ='Daily Halba'!$C56+'Daily Halba'!$F56 -> 2887 | J56: ='Daily Halba'!$I56*'Daily Halba'!$G56 -> 2320.5706 | K56: ='ODOMETERS Halba'!L52 -> 187 | L56: 0.752 | M56: ='Daily Halba'!$K56*'Daily Halba'!$L56 -> 140.624 | N56: 11.15 | O56: 21.18 | P56: =25.64*2 -> 51.28 | S56: 1115 | T56: 3.34 | U56: =SUM('Daily Halba'!$E56,'Daily Halba'!$H56,$M56:$T56) -> 3663.1446 | W56: =15+1205.7 -> 1220.7 | Y56: 32.15 | AB56: 82.38 | AE56: =SUM(AA56:AD56) -> 82.38 | AI56: 5 | AK56: 13.38 | AN56: =SUM(AF56:AM56) -> 18.38 | AP56: =SUM(W56:Z56,AE56,AN56,AO56) -> 1353.61 | AS56: ='Daily Halba'!$U56-'Daily Halba'!$AP56 -> 2309.5346
A57: 46004 | C57: ='ODOMETERS Halba'!J53 -> 1722 | D57: 0.8038 | E57: ='Daily Halba'!$C57*'Daily Halba'!$D57 -> 1384.1436 | F57: ='ODOMETERS Halba'!K53 -> 1083 | G57: 0.8038 | H57: ='Daily Halba'!$F57*'Daily Halba'!$G57 -> 870.5154 | I57: ='Daily Halba'!$C57+'Daily Halba'!$F57 -> 2805 | J57: ='Daily Halba'!$I57*'Daily Halba'!$G57 -> 2254.659 | K57: ='ODOMETERS Halba'!L53 -> 1445 | L57: 0.752 | M57: ='Daily Halba'!$K57*'Daily Halba'!$L57 -> 1086.64 | N57: 4.45 | O57: 20 | P57: 12.82 | R57: 133 | S57: 687 | T57: 6.35 | U57: =SUM('Daily Halba'!$E57,'Daily Halba'!$H57,$M57:$T57) -> 4204.919 | W57: =67+143.25+752 -> 962.25 | Y57: =60.6+37.6 -> 98.2 | AB57: 49.7 | AE57: =SUM(AA57:AD57) -> 49.7 | AG57: 190 | AI57: 4 | AN57: =SUM(AF57:AM57) -> 194 | AP57: =SUM(W57:Z57,AE57,AN57,AO57) -> 1304.15 | AS57: ='Daily Halba'!$U57-'Daily Halba'!$AP57 -> 2900.769
A58: 46005 | C58: ='ODOMETERS Halba'!J54 -> 1420 | D58: 0.8038 | E58: ='Daily Halba'!$C58*'Daily Halba'!$D58 -> 1141.396 | F58: ='ODOMETERS Halba'!K54 -> 1568 | G58: 0.8038 | H58: ='Daily Halba'!$F58*'Daily Halba'!$G58 -> 1260.3584 | I58: ='Daily Halba'!$C58+'Daily Halba'!$F58 -> 2988 | J58: ='Daily Halba'!$I58*'Daily Halba'!$G58 -> 2401.7544 | K58: ='ODOMETERS Halba'!L54 -> 657 | L58: 0.752 | M58: ='Daily Halba'!$K58*'Daily Halba'!$L58 -> 494.064 | N58: 27.21 | O58: 24.52 | P58: 25.64 | Q58: 9 | S58: 5 | T58: 45 | U58: =SUM('Daily Halba'!$E58,'Daily Halba'!$H58,$M58:$T58) -> 3032.1884 | W58: =37+30+63+5.57 -> 135.57 | Y58: =150.4+43.4+48.88 -> 242.68 | AE58: =SUM(AA58:AD58) -> 0 | AI58: 10 | AL58: 1150 | AN58: =SUM(AF58:AM58) -> 1160 | AP58: =SUM(W58:Z58,AE58,AN58,AO58) -> 1538.25 | AQ58: Electricity Generator | AS58: ='Daily Halba'!$U58-'Daily Halba'!$AP58 -> 1493.9384
A59: 46006 | C59: ='ODOMETERS Halba'!J55 -> 869 | D59: 0.8038 | E59: ='Daily Halba'!$C59*'Daily Halba'!$D59 -> 698.5022 | F59: ='ODOMETERS Halba'!K55 -> 2001 | G59: 0.8038 | H59: ='Daily Halba'!$F59*'Daily Halba'!$G59 -> 1608.4038 | I59: ='Daily Halba'!$C59+'Daily Halba'!$F59 -> 2870 | J59: ='Daily Halba'!$I59*'Daily Halba'!$G59 -> 2306.906 | K59: ='ODOMETERS Halba'!L55 -> 1162 | L59: 0.752 | M59: ='Daily Halba'!$K59*'Daily Halba'!$L59 -> 873.824 | N59: 6 | O59: 6.67 | P59: 25.64 | R59: 124 | S59: 1320 | T59: 37.9 | U59: =SUM('Daily Halba'!$E59,'Daily Halba'!$H59,$M59:$T59) -> 4700.94 | W59: =10+376 -> 386 | Y59: =178.44+225.6 -> 404.04 | AB59: 118.17 | AC59: 285 | AE59: =SUM(AA59:AD59) -> 403.17 | AI59: 23 | AL59: 31 | AN59: =SUM(AF59:AM59) -> 54 | AP59: =SUM(W59:Z59,AE59,AN59,AO59) -> 1247.21 | AQ59: Utilities: Mezout - Asset: Deffeye and water | AS59: ='Daily Halba'!$U59-'Daily Halba'!$AP59 -> 3453.73
A60: 46007 | B60: Pre Price | C60: ='ODOMETERS Halba'!J56 -> 404 | D60: 0.8038 | E60: ='Daily Halba'!$C60*'Daily Halba'!$D60 -> 324.7352 | F60: ='ODOMETERS Halba'!K56 -> 548 | G60: 0.8038 | H60: ='Daily Halba'!$F60*'Daily Halba'!$G60 -> 440.4824 | I60: ='Daily Halba'!$C60+'Daily Halba'!$F60 -> 952 | J60: ='Daily Halba'!$I60*'Daily Halba'!$G60 -> 765.2176 | K60: ='ODOMETERS Halba'!L56 -> 3183 | L60: 0.752 | M60: ='Daily Halba'!$K60*'Daily Halba'!$L60 -> 2393.616 | N60: 5.57 | P60: 51.8 | T60: 5.8 | U60: =SUM('Daily Halba'!$E60,'Daily Halba'!$H60,$M60:$T60) -> 3222.0036 | W60: =30+2256 -> 2286 | Y60: 76.4 | Z60: 1 | AC60: 87 | AE60: =SUM(AA60:AD60) -> 87 | AI60: 10 | AN60: =SUM(AF60:AM60) -> 10 | AP60: =SUM(W60:Z60,AE60,AN60,AO60) -> 2460.4 | AQ60: Diesel for Pickup | AS60: ='Daily Halba'!$U60-'Daily Halba'!$AP60 -> 761.6036
A61: 46007 | B61: Post Price | C61: ='ODOMETERS Halba'!J57 -> 551 | D61: 0.7988 | E61: ='Daily Halba'!$C61*'Daily Halba'!$D61 -> 440.1388 | F61: ='ODOMETERS Halba'!K57 -> 754 | G61: 0.7988 | H61: ='Daily Halba'!$F61*'Daily Halba'!$G61 -> 602.2952 | I61: ='Daily Halba'!$C61+'Daily Halba'!$F61 -> 1305 | J61: ='Daily Halba'!$I61*'Daily Halba'!$G61 -> 1042.434 | K61: ='ODOMETERS Halba'!L57 -> 658 | L61: 0.738 | M61: ='Daily Halba'!$K61*'Daily Halba'!$L61 -> 485.604 | N61: 27.78 | O61: 6.68 | P61: =27+13.5 -> 40.5 | R61: 79 | S61: =299+30 -> 329 | T61: 3.34 | U61: =SUM('Daily Halba'!$E61,'Daily Halba'!$H61,$M61:$T61) -> 2014.338 | W61: =15+295.5 -> 310.5 | Y61: =39.14+33.21 -> 72.35 | AE61: =SUM(AA61:AD61) -> 0 | AK61: 13.37 | AN61: =SUM(AF61:AM61) -> 13.37 | AO61: 1000 | AP61: =SUM(W61:Z61,AE61,AN61,AO61) -> 1396.22 | AS61: ='Daily Halba'!$U61-'Daily Halba'!$AP61 -> 618.118
A62: 46008 | C62: ='ODOMETERS Halba'!J58 -> 1273 | D62: 0.7988 | E62: ='Daily Halba'!$C62*'Daily Halba'!$D62 -> 1016.8724 | F62: ='ODOMETERS Halba'!K58 -> 2276 | G62: 0.7988 | H62: ='Daily Halba'!$F62*'Daily Halba'!$G62 -> 1818.0688 | I62: ='Daily Halba'!$C62+'Daily Halba'!$F62 -> 3549 | J62: ='Daily Halba'!$I62*'Daily Halba'!$G62 -> 2834.9412 | K62: ='ODOMETERS Halba'!L58 -> 586 | L62: 0.738 | M62: ='Daily Halba'!$K62*'Daily Halba'!$L62 -> 432.468 | N62: 6.13 | O62: 14.49 | P62: 67.5 | R62: 51.86 | S62: =0.738*800+480*0.7988 -> 973.824 | T62: 2.78 | U62: =SUM('Daily Halba'!$E62,'Daily Halba'!$H62,$M62:$T62) -> 4383.9932 | W62: 12.26 | X62: =798.8+973.824 -> 1772.624 | Y62: 23.97 | AE62: =SUM(AA62:AD62) -> 0 | AN62: =SUM(AF62:AM62) -> 0 | AO62: 1000 | AP62: =SUM(W62:Z62,AE62,AN62,AO62) -> 2808.854 | AS62: ='Daily Halba'!$U62-'Daily Halba'!$AP62 -> 1575.1392
A63: 46009 | C63: ='ODOMETERS Halba'!J59 -> 1408 | D63: 0.7988 | E63: ='Daily Halba'!$C63*'Daily Halba'!$D63 -> 1124.7104 | F63: ='ODOMETERS Halba'!K59 -> 1059 | G63: 0.7988 | H63: ='Daily Halba'!$F63*'Daily Halba'!$G63 -> 845.9292 | I63: ='Daily Halba'!$C63+'Daily Halba'!$F63 -> 2467 | J63: ='Daily Halba'!$I63*'Daily Halba'!$G63 -> 1970.6396 | K63: ='ODOMETERS Halba'!L59 -> 327 | L63: 0.738 | M63: ='Daily Halba'!$K63*'Daily Halba'!$L63 -> 241.326 | N63: =34.7+5+6.5 -> 46.2 | O63: 9 | P63: 66.88 | R63: 70 | T63: 6.68 | U63: =SUM('Daily Halba'!$E63,'Daily Halba'!$H63,$M63:$T63) -> 2410.7256 | W63: 23.34 | Y63: 99.85 | Z63: 15 | AB63: =85+313 -> 398 | AC63: 127.5 | AE63: =SUM(AA63:AD63) -> 525.5 | AI63: 5.57 | AN63: =SUM(AF63:AM63) -> 5.57 | AO63: 1000 | AP63: =SUM(W63:Z63,AE63,AN63,AO63) -> 1669.26 | AS63: ='Daily Halba'!$U63-'Daily Halba'!$AP63 -> 741.4656
A64: 46010 | B64: Pre Price | C64: ='ODOMETERS Halba'!J60 -> 1182 | D64: 0.7988 | E64: ='Daily Halba'!$C64*'Daily Halba'!$D64 -> 944.1816 | F64: ='ODOMETERS Halba'!K60 -> 211 | G64: 0.7988 | H64: ='Daily Halba'!$F64*'Daily Halba'!$G64 -> 168.5468 | I64: ='Daily Halba'!$C64+'Daily Halba'!$F64 -> 1393 | J64: ='Daily Halba'!$I64*'Daily Halba'!$G64 -> 1112.7284 | K64: ='ODOMETERS Halba'!L60 -> 152 | L64: 0.738 | M64: ='Daily Halba'!$K64*'Daily Halba'!$L64 -> 112.176 | O64: 3 | U64: =SUM('Daily Halba'!$E64,'Daily Halba'!$H64,$M64:$T64) -> 1227.9044 | W64: 40 | Y64: 28.75 | AC64: 25.5 | AE64: =SUM(AA64:AD64) -> 25.5 | AN64: =SUM(AF64:AM64) -> 0 | AP64: =SUM(W64:Z64,AE64,AN64,AO64) -> 94.25 | AS64: ='Daily Halba'!$U64-'Daily Halba'!$AP64 -> 1133.6544
A65: 46010 | B65: Post Price | C65: ='ODOMETERS Halba'!J61 -> 1068 | D65: 0.7848 | E65: ='Daily Halba'!$C65*'Daily Halba'!$D65 -> 838.1664 | F65: ='ODOMETERS Halba'!K61 -> 228 | G65: 0.7848 | H65: ='Daily Halba'!$F65*'Daily Halba'!$G65 -> 178.9344 | I65: ='Daily Halba'!$C65+'Daily Halba'!$F65 -> 1296 | J65: ='Daily Halba'!$I65*'Daily Halba'!$G65 -> 1017.1008 | K65: ='ODOMETERS Halba'!L61 -> 635 | L65: 0.723 | M65: ='Daily Halba'!$K65*'Daily Halba'!$L65 -> 459.105 | O65: 10 | P65: =1200000/89700 -> 13.377926 | T65: 13.82 | U65: =SUM('Daily Halba'!$E65,'Daily Halba'!$H65,$M65:$T65) -> 1513.4037 | W65: =56.29+135-117 -> 74.29 | Y65: =47.08+292.8 -> 339.88 | AE65: =SUM(AA65:AD65) -> 0 | AG65: 100 | AI65: 7 | AK65: 10 | AN65: =SUM(AF65:AM65) -> 117 | AP65: =SUM(W65:Z65,AE65,AN65,AO65) -> 531.17 | AS65: ='Daily Halba'!$U65-'Daily Halba'!$AP65 -> 982.23373
A66: 46011 | C66: ='ODOMETERS Halba'!J62 -> 2158 | D66: 0.7848 | E66: ='Daily Halba'!$C66*'Daily Halba'!$D66 -> 1693.5984 | F66: ='ODOMETERS Halba'!K62 -> 1045 | G66: 0.7848 | H66: ='Daily Halba'!$F66*'Daily Halba'!$G66 -> 820.116 | I66: ='Daily Halba'!$C66+'Daily Halba'!$F66 -> 3203 | J66: ='Daily Halba'!$I66*'Daily Halba'!$G66 -> 2513.7144 | K66: ='ODOMETERS Halba'!L62 -> 2956 | L66: 0.723 | M66: ='Daily Halba'!$K66*'Daily Halba'!$L66 -> 2137.188 | N66: 18.26 | O66: 24.52 | P66: 26.75 | R66: 114 | S66: =1000+250*0.723 -> 1180.75 | T66: 4.18 | U66: =SUM('Daily Halba'!$E66,'Daily Halba'!$H66,$M66:$T66) -> 6019.3624 | W66: =13.37+94+1780*0.723 -> 1394.31 | X66: =250*0.723+900*0.723 -> 831.45 | Y66: 54.93 | Z66: 15 | AB66: 130 | AE66: =SUM(AA66:AD66) -> 130 | AJ66: =130+300 -> 430 | AN66: =SUM(AF66:AM66) -> 430 | AP66: =SUM(W66:Z66,AE66,AN66,AO66) -> 2855.69 | AQ66: Christmas Chocolate and Decoration | AS66: ='Daily Halba'!$U66-'Daily Halba'!$AP66 -> 3163.6724
A67: 46012 | C67: ='ODOMETERS Halba'!J63 -> 875 | D67: 0.7848 | E67: ='Daily Halba'!$C67*'Daily Halba'!$D67 -> 686.7 | F67: ='ODOMETERS Halba'!K63 -> 2166 | G67: 0.7848 | H67: ='Daily Halba'!$F67*'Daily Halba'!$G67 -> 1699.8768 | I67: ='Daily Halba'!$C67+'Daily Halba'!$F67 -> 3041 | J67: ='Daily Halba'!$I67*'Daily Halba'!$G67 -> 2386.5768 | K67: ='ODOMETERS Halba'!L63 -> 298 | L67: 0.723 | M67: ='Daily Halba'!$K67*'Daily Halba'!$L67 -> 215.454 | N67: 5.57 | O67: 25.64 | P67: 40 | R67: 88 | T67: 7.52 | U67: =SUM('Daily Halba'!$E67,'Daily Halba'!$H67,$M67:$T67) -> 2768.7608 | W67: 21.14 | Y67: 91.82 | Z67: -5 | AE67: =SUM(AA67:AD67) -> 0 | AN67: =SUM(AF67:AM67) -> 0 | AP67: =SUM(W67:Z67,AE67,AN67,AO67) -> 107.96 | AS67: ='Daily Halba'!$U67-'Daily Halba'!$AP67 -> 2660.8008
A68: 46013 | C68: ='ODOMETERS Halba'!J64 -> 2371 | D68: 0.7848 | E68: ='Daily Halba'!$C68*'Daily Halba'!$D68 -> 1860.7608 | F68: ='ODOMETERS Halba'!K64 -> 901 | G68: 0.7848 | H68: ='Daily Halba'!$F68*'Daily Halba'!$G68 -> 707.1048 | I68: ='Daily Halba'!$C68+'Daily Halba'!$F68 -> 3272 | J68: ='Daily Halba'!$I68*'Daily Halba'!$G68 -> 2567.8656 | K68: ='ODOMETERS Halba'!L64 -> 3104 | L68: 0.723 | M68: ='Daily Halba'!$K68*'Daily Halba'!$L68 -> 2244.192 | N68: =5+12+5.57+5.57 -> 28.14 | O68: 8.9 | P68: =6*1200/89.7 -> 80.267559 | S68: =67+490 -> 557 | T68: 5.85 | U68: =SUM('Daily Halba'!$E68,'Daily Halba'!$H68,$M68:$T68) -> 5492.2152 | W68: =677.83+200+50+30+1700*0.723+800/89700 -> 2186.9389 | Y68: =15.696+36.15 -> 51.846 | Z68: 10 | AB68: =51.5+7400/89.7 -> 133.99721 | AC68: 153 | AE68: =SUM(AA68:AD68) -> 286.99721 | AI68: 14.5 | AN68: =SUM(AF68:AM68) -> 14.5 | AP68: =SUM(W68:Z68,AE68,AN68,AO68) -> 2550.2821 | AS68: ='Daily Halba'!$U68-'Daily Halba'!$AP68 -> 2941.933
A69: 46014 | B69: Pre Price | C69: ='ODOMETERS Halba'!J65 -> 1445 | D69: 0.7848 | E69: ='Daily Halba'!$C69*'Daily Halba'!$D69 -> 1134.036 | F69: ='ODOMETERS Halba'!K65 -> 61 | G69: 0.7848 | H69: ='Daily Halba'!$F69*'Daily Halba'!$G69 -> 47.8728 | I69: ='Daily Halba'!$C69+'Daily Halba'!$F69 -> 1506 | J69: ='Daily Halba'!$I69*'Daily Halba'!$G69 -> 1181.9088 | K69: ='ODOMETERS Halba'!L65 -> 315 | L69: 0.723 | M69: ='Daily Halba'!$K69*'Daily Halba'!$L69 -> 227.745 | N69: 6.5 | O69: 7.8 | P69: 13.37 | Q69: 5 | S69: 192 | U69: =SUM('Daily Halba'!$E69,'Daily Halba'!$H69,$M69:$T69) -> 1634.3238 | Z69: 5 | AC69: 25.5 | AE69: =SUM(AA69:AD69) -> 25.5 | AN69: =SUM(AF69:AM69) -> 0 | AP69: =SUM(W69:Z69,AE69,AN69,AO69) -> 30.5 | AS69: ='Daily Halba'!$U69-'Daily Halba'!$AP69 -> 1603.8238
A70: 46014 | B70: Post Price | C70: ='ODOMETERS Halba'!J66 -> 557 | D70: 0.7715 | E70: ='Daily Halba'!$C70*'Daily Halba'!$D70 -> 429.7255 | F70: ='ODOMETERS Halba'!K66 -> 965 | G70: 0.7715 | H70: ='Daily Halba'!$F70*'Daily Halba'!$G70 -> 744.4975 | I70: ='Daily Halba'!$C70+'Daily Halba'!$F70 -> 1522 | J70: ='Daily Halba'!$I70*'Daily Halba'!$G70 -> 1174.223 | K70: ='ODOMETERS Halba'!L66 -> 1003 | L70: 0.7135 | M70: ='Daily Halba'!$K70*'Daily Halba'!$L70 -> 715.6405 | N70: 5.67 | R70: 78 | S70: =781+450 -> 1231 | U70: =SUM('Daily Halba'!$E70,'Daily Halba'!$H70,$M70:$T70) -> 3204.5335 | W70: =21.68+428 -> 449.68 | Z70: -14 | AA70: 32 | AE70: =SUM(AA70:AD70) -> 32 | AN70: =SUM(AF70:AM70) -> 0 | AP70: =SUM(W70:Z70,AE70,AN70,AO70) -> 467.68 | AS70: ='Daily Halba'!$U70-'Daily Halba'!$AP70 -> 2736.8535
A71: 46015 | C71: ='ODOMETERS Halba'!J67 -> 868 | D71: 0.7715 | E71: ='Daily Halba'!$C71*'Daily Halba'!$D71 -> 669.662 | F71: ='ODOMETERS Halba'!K67 -> 2547 | G71: 0.7715 | H71: ='Daily Halba'!$F71*'Daily Halba'!$G71 -> 1965.0105 | I71: ='Daily Halba'!$C71+'Daily Halba'!$F71 -> 3415 | J71: ='Daily Halba'!$I71*'Daily Halba'!$G71 -> 2634.6725 | K71: ='ODOMETERS Halba'!L67 -> 1127 | L71: 0.7135 | M71: ='Daily Halba'!$K71*'Daily Halba'!$L71 -> 804.1145 | N71: 9.34 | O71: 20.5 | R71: 36 | T71: 28.34 | U71: =SUM('Daily Halba'!$E71,'Daily Halba'!$H71,$M71:$T71) -> 3532.967 | W71: 101.6 | Y71: =61.72+338.91 -> 400.63 | AE71: =SUM(AA71:AD71) -> 0 | AG71: 100 | AJ71: =10+36 -> 46 | AN71: =SUM(AF71:AM71) -> 146 | AP71: =SUM(W71:Z71,AE71,AN71,AO71) -> 648.23 | AQ71: Prinitng Sationary for Christmas | AS71: ='Daily Halba'!$U71-'Daily Halba'!$AP71 -> 2884.737
A72: 46016 | C72: ='ODOMETERS Halba'!J68 -> 2828 | D72: 0.7715 | E72: ='Daily Halba'!$C72*'Daily Halba'!$D72 -> 2181.802 | F72: ='ODOMETERS Halba'!K68 -> 379 | G72: 0.7715 | H72: ='Daily Halba'!$F72*'Daily Halba'!$G72 -> 292.3985 | I72: ='Daily Halba'!$C72+'Daily Halba'!$F72 -> 3207 | J72: ='Daily Halba'!$I72*'Daily Halba'!$G72 -> 2474.2005 | K72: ='ODOMETERS Halba'!L68 -> 255 | L72: 0.7135 | M72: ='Daily Halba'!$K72*'Daily Halba'!$L72 -> 181.9425 | N72: 0 | O72: 14 | P72: 40 | R72: 66 | S72: =850*0.7135 -> 606.475 | T72: 1.7 | U72: =SUM('Daily Halba'!$E72,'Daily Halba'!$H72,$M72:$T72) -> 3384.318 | W72: 140 | X72: =850*0.7135 -> 606.475 | Y72: 43.2 | Z72: -15 | AC72: 38.7 | AE72: =SUM(AA72:AD72) -> 38.7 | AI72: 5.5 | AK72: 20 | AN72: =SUM(AF72:AM72) -> 25.5 | AP72: =SUM(W72:Z72,AE72,AN72,AO72) -> 838.875 | AS72: ='Daily Halba'!$U72-'Daily Halba'!$AP72 -> 2545.443
A73: 46017 | B73: Pre Price | C73: ='ODOMETERS Halba'!J69 -> 1765 | D73: 0.7715 | E73: ='Daily Halba'!$C73*'Daily Halba'!$D73 -> 1361.6975 | F73: ='ODOMETERS Halba'!K69 -> 26 | G73: 0.7715 | H73: ='Daily Halba'!$F73*'Daily Halba'!$G73 -> 20.059 | I73: ='Daily Halba'!$C73+'Daily Halba'!$F73 -> 1791 | J73: ='Daily Halba'!$I73*'Daily Halba'!$G73 -> 1381.7565 | K73: ='ODOMETERS Halba'!L69 -> 525 | L73: 0.7135 | M73: ='Daily Halba'!$K73*'Daily Halba'!$L73 -> 374.5875 | N73: 9.47 | P73: 66.88 | S73: =750+342 -> 1092 | U73: =SUM('Daily Halba'!$E73,'Daily Halba'!$H73,$M73:$T73) -> 2924.694 | X73: 342 | Y73: =29.31+157+14 -> 200.31 | Z73: 21 | AC73: 64 | AE73: =SUM(AA73:AD73) -> 64 | AI73: 10 | AN73: =SUM(AF73:AM73) -> 10 | AP73: =SUM(W73:Z73,AE73,AN73,AO73) -> 637.31 | AS73: ='Daily Halba'!$U73-'Daily Halba'!$AP73 -> 2287.384
A74: 46017 | B74: Post Price | C74: ='ODOMETERS Halba'!J70 -> 953 | D74: 0.7559 | E74: ='Daily Halba'!$C74*'Daily Halba'!$D74 -> 720.3727 | F74: ='ODOMETERS Halba'!K70 -> 315 | G74: 0.7559 | H74: ='Daily Halba'!$F74*'Daily Halba'!$G74 -> 238.1085 | I74: ='Daily Halba'!$C74+'Daily Halba'!$F74 -> 1268 | J74: ='Daily Halba'!$I74*'Daily Halba'!$G74 -> 958.4812 | K74: ='ODOMETERS Halba'!L70 -> 1757 | L74: 0.7028 | M74: ='Daily Halba'!$K74*'Daily Halba'!$L74 -> 1234.8196 | N74: 2.87 | O74: 3 | R74: 75 | T74: 1.67 | U74: =SUM('Daily Halba'!$E74,'Daily Halba'!$H74,$M74:$T74) -> 2275.8408 | W74: =913.64+24+98.39 -> 1036.03 | Y74: 15 | AE74: =SUM(AA74:AD74) -> 0 | AN74: =SUM(AF74:AM74) -> 0 | AP74: =SUM(W74:Z74,AE74,AN74,AO74) -> 1051.03 | AS74: ='Daily Halba'!$U74-'Daily Halba'!$AP74 -> 1224.8108
A75: 46018 | C75: ='ODOMETERS Halba'!J71 -> 1540 | D75: 0.7559 | E75: ='Daily Halba'!$C75*'Daily Halba'!$D75 -> 1164.086 | F75: ='ODOMETERS Halba'!K71 -> 772 | G75: 0.7559 | H75: ='Daily Halba'!$F75*'Daily Halba'!$G75 -> 583.5548 | I75: ='Daily Halba'!$C75+'Daily Halba'!$F75 -> 2312 | J75: ='Daily Halba'!$I75*'Daily Halba'!$G75 -> 1747.6408 | K75: ='ODOMETERS Halba'!L71 -> 1094 | L75: 0.7028 | M75: ='Daily Halba'!$K75*'Daily Halba'!$L75 -> 768.8632 | N75: 15 | P75: 26.75 | R75: 50 | S75: 1235 | U75: =SUM('Daily Halba'!$E75,'Daily Halba'!$H75,$M75:$T75) -> 3843.254 | W75: =20.06+316+492 -> 828.06 | Z75: 20 | AB75: 293 | AE75: =SUM(AA75:AD75) -> 293 | AN75: =SUM(AF75:AM75) -> 0 | AP75: =SUM(W75:Z75,AE75,AN75,AO75) -> 1141.06 | AS75: ='Daily Halba'!$U75-'Daily Halba'!$AP75 -> 2702.194
A76: 46019 | C76: ='ODOMETERS Halba'!J72 -> 2234 | D76: 0.7559 | E76: ='Daily Halba'!$C76*'Daily Halba'!$D76 -> 1688.6806 | F76: ='ODOMETERS Halba'!K72 -> 789 | G76: 0.7559 | H76: ='Daily Halba'!$F76*'Daily Halba'!$G76 -> 596.4051 | I76: ='Daily Halba'!$C76+'Daily Halba'!$F76 -> 3023 | J76: ='Daily Halba'!$I76*'Daily Halba'!$G76 -> 2285.0857 | K76: ='ODOMETERS Halba'!L72 -> 588 | L76: 0.7028 | M76: ='Daily Halba'!$K76*'Daily Halba'!$L76 -> 413.2464 | N76: =6.5+6+8 -> 20.5 | O76: =1300/89.7 -> 14.492754 | P76: =7*1200000/89700 -> 93.645485 | S76: =80 -> 80 | T76: =75/89.7 -> 0.8361204 | U76: =SUM('Daily Halba'!$E76,'Daily Halba'!$H76,$M76:$T76) -> 2907.8065 | W76: 30 | Y76: =(10+27+18)*0.7559 -> 41.5745 | AE76: =SUM(AA76:AD76) -> 0 | AI76: =500/89.7 -> 5.574136 | AN76: =SUM(AF76:AM76) -> 5.574136 | AP76: =SUM(W76:Z76,AE76,AN76,AO76) -> 77.148636 | AS76: ='Daily Halba'!$U76-'Daily Halba'!$AP76 -> 2830.6578
A77: 46020 | C77: ='ODOMETERS Halba'!J73 -> 1283 | D77: 0.7559 | E77: ='Daily Halba'!$C77*'Daily Halba'!$D77 -> 969.8197 | F77: ='ODOMETERS Halba'!K73 -> 1977 | G77: 0.7559 | H77: ='Daily Halba'!$F77*'Daily Halba'!$G77 -> 1494.4143 | I77: ='Daily Halba'!$C77+'Daily Halba'!$F77 -> 3260 | J77: ='Daily Halba'!$I77*'Daily Halba'!$G77 -> 2464.234 | K77: ='ODOMETERS Halba'!L73 -> 519 | L77: 0.7028 | M77: ='Daily Halba'!$K77*'Daily Halba'!$L77 -> 364.7532 | N77: 26.92 | O77: 20 | P77: 26.75 | S77: 20 | T77: 4.23 | U77: =SUM('Daily Halba'!$E77,'Daily Halba'!$H77,$M77:$T77) -> 2926.8872 | W77: 53.9 | Y77: 37.8 | Z77: 7 | AC77: 129 | AE77: =SUM(AA77:AD77) -> 129 | AI77: 6.67 | AN77: =SUM(AF77:AM77) -> 6.67 | AP77: =SUM(W77:Z77,AE77,AN77,AO77) -> 234.37 | AS77: ='Daily Halba'!$U77-'Daily Halba'!$AP77 -> 2692.5172
A78: 46021 | B78: Pre Price | C78: ='ODOMETERS Halba'!J74 -> 742 | D78: 0.7559 | E78: ='Daily Halba'!$C78*'Daily Halba'!$D78 -> 560.8778 | F78: ='ODOMETERS Halba'!K74 -> 631 | G78: 0.7559 | H78: ='Daily Halba'!$F78*'Daily Halba'!$G78 -> 476.9729 | I78: ='Daily Halba'!$C78+'Daily Halba'!$F78 -> 1373 | J78: ='Daily Halba'!$I78*'Daily Halba'!$G78 -> 1037.8507 | K78: ='ODOMETERS Halba'!L74 -> 153 | L78: 0.7028 | M78: ='Daily Halba'!$K78*'Daily Halba'!$L78 -> 107.5284 | P78: 71.8 | Q78: 5 | S78: 2000 | T78: 1.57 | U78: =SUM('Daily Halba'!$E78,'Daily Halba'!$H78,$M78:$T78) -> 3223.7491 | W78: 20 | Y78: 28.7 | Z78: -5 | AE78: =SUM(AA78:AD78) -> 0 | AG78: 500 | AN78: =SUM(AF78:AM78) -> 500 | AP78: =SUM(W78:Z78,AE78,AN78,AO78) -> 543.7 | AQ78: Tony's Salary | AS78: ='Daily Halba'!$U78-'Daily Halba'!$AP78 -> 2680.0491
A79: 46021 | B79: Post Price | C79: ='ODOMETERS Halba'!J75 -> 750 | D79: 0.7486 | E79: ='Daily Halba'!$C79*'Daily Halba'!$D79 -> 561.45 | F79: ='ODOMETERS Halba'!K75 -> 1014 | G79: 0.7486 | H79: ='Daily Halba'!$F79*'Daily Halba'!$G79 -> 759.0804 | I79: ='Daily Halba'!$C79+'Daily Halba'!$F79 -> 1764 | J79: ='Daily Halba'!$I79*'Daily Halba'!$G79 -> 1320.5304 | K79: ='ODOMETERS Halba'!L75 -> 2549 | L79: 0.6973 | M79: ='Daily Halba'!$K79*'Daily Halba'!$L79 -> 1777.4177 | N79: 15 | O79: 6.67 | P79: 26.75 | T79: 10 | U79: =SUM('Daily Halba'!$E79,'Daily Halba'!$H79,$M79:$T79) -> 3156.3681 | W79: =5+1556+7 -> 1568 | Y79: =14.97+69.73 -> 84.7 | AE79: =SUM(AA79:AD79) -> 0 | AG79: 50 | AK79: 10 | AN79: =SUM(AF79:AM79) -> 60 | AP79: =SUM(W79:Z79,AE79,AN79,AO79) -> 1712.7 | AS79: ='Daily Halba'!$U79-'Daily Halba'!$AP79 -> 1443.6681
A80: 46022 | C80: ='ODOMETERS Halba'!J76 -> 1488 | D80: 0.7486 | E80: ='Daily Halba'!$C80*'Daily Halba'!$D80 -> 1113.9168 | F80: ='ODOMETERS Halba'!K76 -> 1338 | G80: 0.7486 | H80: ='Daily Halba'!$F80*'Daily Halba'!$G80 -> 1001.6268 | I80: ='Daily Halba'!$C80+'Daily Halba'!$F80 -> 2826 | J80: ='Daily Halba'!$I80*'Daily Halba'!$G80 -> 2115.5436 | K80: ='ODOMETERS Halba'!L76 -> 1931 | L80: 0.6973 | M80: ='Daily Halba'!$K80*'Daily Halba'!$L80 -> 1346.4863 | N80: =250/89.7 -> 2.787068 | O80: =700/89.7 -> 7.8037904 | P80: =1200/89.7 -> 13.377926 | S80: =623+20 -> 643 | T80: =450/89.7 -> 5.0167224 | U80: =SUM('Daily Halba'!$E80,'Daily Halba'!$H80,$M80:$T80) -> 4134.0154 | W80: =20+(1327*0.6973) -> 945.3171 | Y80: =(18+30+18+30)*0.6973 -> 66.9408 | Z80: -5 | AE80: =SUM(AA80:AD80) -> 0 | AI80: 19 | AK80: =600/89.7 -> 6.6889632 | AN80: =SUM(AF80:AM80) -> 25.688963 | AP80: =SUM(W80:Z80,AE80,AN80,AO80) -> 1032.9469 | AS80: ='Daily Halba'!$U80-'Daily Halba'!$AP80 -> 3101.0685
A81: 46023 | C81: ='ODOMETERS Halba'!J77 -> 1607 | D81: 0.7486 | E81: ='Daily Halba'!$C81*'Daily Halba'!$D81 -> 1203.0002 | F81: ='ODOMETERS Halba'!K77 -> 657 | G81: 0.7486 | H81: ='Daily Halba'!$F81*'Daily Halba'!$G81 -> 491.8302 | I81: ='Daily Halba'!$C81+'Daily Halba'!$F81 -> 2264 | J81: ='Daily Halba'!$I81*'Daily Halba'!$G81 -> 1694.8304 | K81: ='ODOMETERS Halba'!L77 -> 2716 | L81: 0.6973 | M81: ='Daily Halba'!$K81*'Daily Halba'!$L81 -> 1893.8668 | N81: =1000/89.7+300/89.7+6 -> 20.492754 | P81: =(1200/89.7)*9 -> 120.40134 | S81: =20+2600 -> 2620 | T81: =225/89.7+150/89.7 -> 4.180602 | U81: =SUM('Daily Halba'!$E81,'Daily Halba'!$H81,$M81:$T81) -> 6353.7719 | W81: =2000*0.6973+10 -> 1404.6 | Y81: =(30+20)*0.7486+180*0.6973 -> 162.944 | AC81: 103 | AE81: =SUM(AA81:AD81) -> 103 | AN81: =SUM(AF81:AM81) -> 0 | AP81: =SUM(W81:Z81,AE81,AN81,AO81) -> 1670.544 | AS81: ='Daily Halba'!$U81-'Daily Halba'!$AP81 -> 4683.2279
A82: 46024 | C82: ='ODOMETERS Halba'!J78 -> 2417 | D82: 0.7486 | E82: ='Daily Halba'!$C82*'Daily Halba'!$D82 -> 1809.3662 | F82: ='ODOMETERS Halba'!K78 -> 143 | G82: 0.7486 | H82: ='Daily Halba'!$F82*'Daily Halba'!$G82 -> 107.0498 | I82: ='Daily Halba'!$C82+'Daily Halba'!$F82 -> 2560 | J82: ='Daily Halba'!$I82*'Daily Halba'!$G82 -> 1916.416 | K82: ='ODOMETERS Halba'!L78 -> 1431 | L82: 0.6973 | M82: ='Daily Halba'!$K82*'Daily Halba'!$L82 -> 997.8363 | N82: =42+4 -> 46 | O82: =700/89.7 -> 7.8037904 | P82: =1200*4/89.7 -> 53.511706 | Q82: 5 | S82: 38 | T82: =(150+225+150+75)/89.7 -> 6.6889632 | U82: =SUM('Daily Halba'!$E82,'Daily Halba'!$H82,$M82:$T82) -> 3071.2568 | W82: =30+35+0.6973*1000 -> 762.3 | Y82: =0.7486*(20+36+10+20+9+30) -> 93.575 | Z82: 3 | AE82: =SUM(AA82:AD82) -> 0 | AI82: =10*0.6973 -> 6.973 | AK82: =300/89.7 -> 3.3444816 | AM82: =200/89.7 -> 2.2296544 | AN82: =SUM(AF82:AM82) -> 12.547136 | AP82: =SUM(W82:Z82,AE82,AN82,AO82) -> 871.42214 | AS82: ='Daily Halba'!$U82-'Daily Halba'!$AP82 -> 2199.8346
A83: 46025 | B83: Pre Price | C83: ='ODOMETERS Halba'!J79 -> 889 | D83: 0.7486 | E83: ='Daily Halba'!$C83*'Daily Halba'!$D83 -> 665.5054 | F83: ='ODOMETERS Halba'!K79 -> 309 | G83: 0.7486 | H83: ='Daily Halba'!$F83*'Daily Halba'!$G83 -> 231.3174 | I83: ='Daily Halba'!$C83+'Daily Halba'!$F83 -> 1198 | J83: ='Daily Halba'!$I83*'Daily Halba'!$G83 -> 896.8228 | K83: ='ODOMETERS Halba'!L79 -> 151 | L83: 0.6973 | M83: ='Daily Halba'!$K83*'Daily Halba'!$L83 -> 105.2923 | N83: =150/89.7+300/89.7+13 -> 18.016722 | P83: =3600/89.7 -> 40.133779 | T83: =150/89.7 -> 1.6722408 | U83: =SUM('Daily Halba'!$E83,'Daily Halba'!$H83,$M83:$T83) -> 1061.9378 | Y83: =38*0.7486 -> 28.4468 | AE83: =SUM(AA83:AD83) -> 0 | AN83: =SUM(AF83:AM83) -> 0 | AP83: =SUM(W83:Z83,AE83,AN83,AO83) -> 28.4468 | AS83: ='Daily Halba'!$U83-'Daily Halba'!$AP83 -> 1033.491
A84: 46025 | B84: Post Price | C84: ='ODOMETERS Halba'!J80 -> 1175 | D84: 0.7358 | E84: ='Daily Halba'!$C84*'Daily Halba'!$D84 -> 864.565 | F84: ='ODOMETERS Halba'!K80 -> 779 | G84: 0.7358 | H84: ='Daily Halba'!$F84*'Daily Halba'!$G84 -> 573.1882 | I84: ='Daily Halba'!$C84+'Daily Halba'!$F84 -> 1954 | J84: ='Daily Halba'!$I84*'Daily Halba'!$G84 -> 1437.7532 | K84: ='ODOMETERS Halba'!L80 -> 612 | L84: 0.6895 | M84: ='Daily Halba'!$K84*'Daily Halba'!$L84 -> 421.974 | N84: =24+48+1000/89.7+5 -> 88.148272 | O84: 20 | P84: =4*1200/89.7 -> 53.511706 | S84: =25+210+327 -> 562 | T84: =(225+150)/89.7 -> 4.180602 | U84: =SUM('Daily Halba'!$E84,'Daily Halba'!$H84,$M84:$T84) -> 2587.5678 | W84: =1700/89.7+200+300*0.6895 -> 425.80206 | X84: 15 | Y84: =(30+20+27)*0.7358 -> 56.6566 | AC84: 220 | AE84: =SUM(AA84:AD84) -> 220 | AG84: =30+1155 -> 1185 | AN84: =SUM(AF84:AM84) -> 1185 | AP84: =SUM(W84:Z84,AE84,AN84,AO84) -> 1902.4587 | AQ84: air pressure gauge for tekrit, 2 Bateries to tekrit (from oil stock sheet) | AS84: ='Daily Halba'!$U84-'Daily Halba'!$AP84 -> 685.10912
A85: 46026 | C85: ='ODOMETERS Halba'!J81 -> 2367 | D85: 0.7358 | E85: ='Daily Halba'!$C85*'Daily Halba'!$D85 -> 1741.6386 | F85: ='ODOMETERS Halba'!K81 -> 1166 | G85: 0.7358 | H85: ='Daily Halba'!$F85*'Daily Halba'!$G85 -> 857.9428 | I85: ='Daily Halba'!$C85+'Daily Halba'!$F85 -> 3533 | J85: ='Daily Halba'!$I85*'Daily Halba'!$G85 -> 2599.5814 | K85: ='ODOMETERS Halba'!L81 -> 551 | L85: 0.6895 | M85: ='Daily Halba'!$K85*'Daily Halba'!$L85 -> 379.9145 | N85: 8.34 | O85: 28.98 | P85: 120 | S85: =27.87+150 -> 177.87 | T85: 7.52 | U85: =SUM('Daily Halba'!$E85,'Daily Halba'!$H85,$M85:$T85) -> 3322.2059 | W85: 44.57 | Y85: 127.87 | Z85: 5 | AE85: =SUM(AA85:AD85) -> 0 | AN85: =SUM(AF85:AM85) -> 0 | AP85: =SUM(W85:Z85,AE85,AN85,AO85) -> 177.44 | AS85: ='Daily Halba'!$U85-'Daily Halba'!$AP85 -> 3144.7659
A86: 46027 | C86: ='ODOMETERS Halba'!J82 -> 1044 | D86: 0.7358 | E86: ='Daily Halba'!$C86*'Daily Halba'!$D86 -> 768.1752 | F86: ='ODOMETERS Halba'!K82 -> 2068 | G86: 0.7358 | H86: ='Daily Halba'!$F86*'Daily Halba'!$G86 -> 1521.6344 | I86: ='Daily Halba'!$C86+'Daily Halba'!$F86 -> 3112 | J86: ='Daily Halba'!$I86*'Daily Halba'!$G86 -> 2289.8096 | K86: ='ODOMETERS Halba'!L82 -> 1676 | L86: 0.6895 | M86: ='Daily Halba'!$K86*'Daily Halba'!$L86 -> 1155.602 | N86: =22.78-10 -> 12.78 | O86: 18.95 | P86: =80.26 -> 80.26 | Q86: 10 | S86: 1800 | T86: 6.68 | U86: =SUM('Daily Halba'!$E86,'Daily Halba'!$H86,$M86:$T86) -> 5374.0816 | W86: =87+662 -> 749 | Y86: 22.07 | Z86: 10 | AC86: 557 | AE86: =SUM(AA86:AD86) -> 557 | AN86: =SUM(AF86:AM86) -> 0 | AP86: =SUM(W86:Z86,AE86,AN86,AO86) -> 1338.07 | AS86: ='Daily Halba'!$U86-'Daily Halba'!$AP86 -> 4036.0116
A87: 46028 | C87: ='ODOMETERS Halba'!J83 -> 1693 | D87: 0.7358 | E87: ='Daily Halba'!$C87*'Daily Halba'!$D87 -> 1245.7094 | F87: ='ODOMETERS Halba'!K83 -> 931 | G87: 0.7358 | H87: ='Daily Halba'!$F87*'Daily Halba'!$G87 -> 685.0298 | I87: ='Daily Halba'!$C87+'Daily Halba'!$F87 -> 2624 | J87: ='Daily Halba'!$I87*'Daily Halba'!$G87 -> 1930.7392 | K87: ='ODOMETERS Halba'!L83 -> 1627 | L87: 0.6895 | M87: ='Daily Halba'!$K87*'Daily Halba'!$L87 -> 1121.8165 | N87: =250/89.7+6.5+24 -> 33.287068 | O87: =11 -> 11 | P87: =8*13 -> 104 | T87: =(75+150+225+450+450)/89.7 -> 15.050167 | U87: =SUM('Daily Halba'!$E87,'Daily Halba'!$H87,$M87:$T87) -> 3215.8929 | W87: =1000*0.6895 -> 689.5 | Y87: =(27+54+10+20+30+40+20+18)*0.7358+64*0.6895 -> 205.2682 | Z87: 2 | AA87: 102 | AC87: 78 | AE87: =SUM(AA87:AD87) -> 180 | AI87: =5+20+10 -> 35 | AN87: =SUM(AF87:AM87) -> 35 | AO87: 1500 | AP87: =SUM(W87:Z87,AE87,AN87,AO87) -> 2611.7682 | AQ87: Utilities: mezout for generator + municipality | AS87: ='Daily Halba'!$U87-'Daily Halba'!$AP87 -> 604.12474
A88: 46029 | B88: Pre Price | C88: ='ODOMETERS Halba'!J84 -> 1029 | D88: 0.7358 | E88: ='Daily Halba'!$C88*'Daily Halba'!$D88 -> 757.1382 | F88: ='ODOMETERS Halba'!K84 -> 770 | G88: 0.7358 | H88: ='Daily Halba'!$F88*'Daily Halba'!$G88 -> 566.566 | I88: ='Daily Halba'!$C88+'Daily Halba'!$F88 -> 1799 | J88: ='Daily Halba'!$I88*'Daily Halba'!$G88 -> 1323.7042 | K88: ='ODOMETERS Halba'!L84 -> 2013 | L88: 0.6895 | M88: ='Daily Halba'!$K88*'Daily Halba'!$L88 -> 1387.9635 | N88: =750/89.47 -> 8.3826981 | O88: =800/89.7 -> 8.9186176 | P88: =3*13 -> 39 | T88: =150/89.7 -> 1.6722408 | U88: =SUM('Daily Halba'!$E88,'Daily Halba'!$H88,$M88:$T88) -> 2769.6413 | W88: =20+1500*0.6895 -> 1054.25 | Y88: =20*0.7358 -> 14.716 | Z88: 6 | AE88: =SUM(AA88:AD88) -> 0 | AK88: =600/89.7 -> 6.6889632 | AN88: =SUM(AF88:AM88) -> 6.6889632 | AO88: 1000 | AP88: =SUM(W88:Z88,AE88,AN88,AO88) -> 2081.655 | AS88: ='Daily Halba'!$U88-'Daily Halba'!$AP88 -> 687.98629
A89: 46029 | B89: Post Price | C89: ='ODOMETERS Halba'!J85 -> 626 | D89: 0.7291 | E89: ='Daily Halba'!$C89*'Daily Halba'!$D89 -> 456.4166 | F89: ='ODOMETERS Halba'!K85 -> 348 | G89: 0.7291 | H89: ='Daily Halba'!$F89*'Daily Halba'!$G89 -> 253.7268 | I89: ='Daily Halba'!$C89+'Daily Halba'!$F89 -> 974 | J89: ='Daily Halba'!$I89*'Daily Halba'!$G89 -> 710.1434 | K89: ='ODOMETERS Halba'!L85 -> 155 | L89: 0.6867 | M89: ='Daily Halba'!$K89*'Daily Halba'!$L89 -> 106.4385 | O89: =1000/89.7 -> 11.148272 | P89: 13 | S89: =686+20+1100+70 -> 1876 | U89: =SUM('Daily Halba'!$E89,'Daily Halba'!$H89,$M89:$T89) -> 2716.7302 | W89: =180 -> 180 | Y89: =9*0.7291 -> 6.5619 | Z89: -2 | AE89: =SUM(AA89:AD89) -> 0 | AG89: 30 | AI89: 16 | AK89: =300/89.7 -> 3.3444816 | AN89: =SUM(AF89:AM89) -> 49.344482 | AO89: 500 | AP89: =SUM(W89:Z89,AE89,AN89,AO89) -> 733.90638 | AS89: ='Daily Halba'!$U89-'Daily Halba'!$AP89 -> 1982.8238
A90: 46030 | C90: ='ODOMETERS Halba'!J86 -> 1642 | D90: 0.7291 | E90: ='Daily Halba'!$C90*'Daily Halba'!$D90 -> 1197.1822 | F90: ='ODOMETERS Halba'!K86 -> 1095 | G90: 0.7291 | H90: ='Daily Halba'!$F90*'Daily Halba'!$G90 -> 798.3645 | I90: ='Daily Halba'!$C90+'Daily Halba'!$F90 -> 2737 | J90: ='Daily Halba'!$I90*'Daily Halba'!$G90 -> 1995.5467 | K90: ='ODOMETERS Halba'!L86 -> 2760 | L90: 0.6867 | M90: ='Daily Halba'!$K90*'Daily Halba'!$L90 -> 1895.292 | N90: =250/89.7+8+500/89.7 -> 16.361204 | O90: =(300+300+800+300)/89.7 -> 18.952062 | P90: =13*5 -> 65 | Q90: 5 | S90: =580+10 -> 590 | T90: =(150+75+150+150+150)/89.7 -> 7.5250836 | U90: =SUM('Daily Halba'!$E90,'Daily Halba'!$H90,$M90:$T90) -> 4593.6771 | W90: =202*0.6867+700/89.7+16+20+30+260*0.6867+10+10+1500*0.6867 -> 1441.1092 | Y90: =(9+20+10+20+20+18+20+9)*0.7291+0.6867*350 -> 332.2116 | Z90: 24 | AC90: 91 | AE90: =SUM(AA90:AD90) -> 91 | AI90: =1200/89.7 -> 13.377926 | AN90: =SUM(AF90:AM90) -> 13.377926 | AP90: =SUM(W90:Z90,AE90,AN90,AO90) -> 1901.6987 | AS90: ='Daily Halba'!$U90-'Daily Halba'!$AP90 -> 2691.9783
A91: 46031 | B91: Pre Price | C91: ='ODOMETERS Halba'!J87 -> 1008 | D91: 0.7291 | E91: ='Daily Halba'!$C91*'Daily Halba'!$D91 -> 734.9328 | F91: ='ODOMETERS Halba'!K87 -> 706 | G91: 0.7291 | H91: ='Daily Halba'!$F91*'Daily Halba'!$G91 -> 514.7446 | I91: ='Daily Halba'!$C91+'Daily Halba'!$F91 -> 1714 | J91: ='Daily Halba'!$I91*'Daily Halba'!$G91 -> 1249.6774 | K91: ='ODOMETERS Halba'!L87 -> 370 | L91: 0.6867 | M91: ='Daily Halba'!$K91*'Daily Halba'!$L91 -> 254.079 | N91: 2.78 | P91: 26.75 | S91: =150+173+1442 -> 1765 | U91: =SUM('Daily Halba'!$E91,'Daily Halba'!$H91,$M91:$T91) -> 3298.2864 | W91: =120*0.6867+20 -> 102.404 | Z91: -5 | AE91: =SUM(AA91:AD91) -> 0 | AI91: 5 | AN91: =SUM(AF91:AM91) -> 5 | AP91: =SUM(W91:Z91,AE91,AN91,AO91) -> 102.404 | AS91: ='Daily Halba'!$U91-'Daily Halba'!$AP91 -> 3195.8824
A92: 46031 | B92: Post Price | C92: ='ODOMETERS Halba'!J88 -> 721 | D92: 0.728 | E92: ='Daily Halba'!$C92*'Daily Halba'!$D92 -> 524.888 | F92: ='ODOMETERS Halba'!K88 -> 462 | G92: 0.728 | H92: ='Daily Halba'!$F92*'Daily Halba'!$G92 -> 336.336 | I92: ='Daily Halba'!$C92+'Daily Halba'!$F92 -> 1183 | J92: ='Daily Halba'!$I92*'Daily Halba'!$G92 -> 861.224 | K92: ='ODOMETERS Halba'!L88 -> 455 | L92: 0.6851 | M92: ='Daily Halba'!$K92*'Daily Halba'!$L92 -> 311.7205 | P92: 26.75 | S92: 10 | U92: =SUM('Daily Halba'!$E92,'Daily Halba'!$H92,$M92:$T92) -> 1209.6945 | W92: 115.5 | Y92: 150.72 | AE92: =SUM(AA92:AD92) -> 0 | AN92: =SUM(AF92:AM92) -> 0 | AP92: =SUM(W92:Z92,AE92,AN92,AO92) -> 266.22 | AS92: ='Daily Halba'!$U92-'Daily Halba'!$AP92 -> 943.4745
A93: 46032 | C93: ='ODOMETERS Halba'!J89 -> 2677 | D93: 0.728 | E93: ='Daily Halba'!$C93*'Daily Halba'!$D93 -> 1948.856 | F93: ='ODOMETERS Halba'!K89 -> 524 | G93: 0.728 | H93: ='Daily Halba'!$F93*'Daily Halba'!$G93 -> 381.472 | I93: ='Daily Halba'!$C93+'Daily Halba'!$F93 -> 3201 | J93: ='Daily Halba'!$I93*'Daily Halba'!$G93 -> 2330.328 | K93: ='ODOMETERS Halba'!L89 -> 1458 | L93: 0.6851 | M93: ='Daily Halba'!$K93*'Daily Halba'!$L93 -> 998.8758 | N93: 17.36 | O93: 31.68 | P93: 132 | S93: =480*0.6851+1712 -> 2040.848 | T93: 9.19 | U93: =SUM('Daily Halba'!$E93,'Daily Halba'!$H93,$M93:$T93) -> 5560.2818 | W93: =89.15+685 -> 774.15 | X93: =480*0.6851 -> 328.848 | Y93: 93.18 | AA93: 19 | AC93: 91 | AE93: =SUM(AA93:AD93) -> 110 | AN93: =SUM(AF93:AM93) -> 0 | AP93: =SUM(W93:Z93,AE93,AN93,AO93) -> 1306.178 | AS93: ='Daily Halba'!$U93-'Daily Halba'!$AP93 -> 4254.1038
A94: 46033 | C94: ='ODOMETERS Halba'!J90 -> 1960 | D94: 0.728 | E94: ='Daily Halba'!$C94*'Daily Halba'!$D94 -> 1426.88 | F94: ='ODOMETERS Halba'!K90 -> 925 | G94: 0.728 | H94: ='Daily Halba'!$F94*'Daily Halba'!$G94 -> 673.4 | I94: ='Daily Halba'!$C94+'Daily Halba'!$F94 -> 2885 | J94: ='Daily Halba'!$I94*'Daily Halba'!$G94 -> 2100.28 | K94: ='ODOMETERS Halba'!L90 -> 2140 | L94: 0.6851 | M94: ='Daily Halba'!$K94*'Daily Halba'!$L94 -> 1466.114 | N94: =250/89.7+15+6 -> 23.787068 | O94: 10 | P94: =13*2 -> 26 | S94: =220+496 -> 716 | T94: =300/89.7 -> 3.3444816 | U94: =SUM('Daily Halba'!$E94,'Daily Halba'!$H94,$M94:$T94) -> 4345.5255 | W94: =1500*0.6851+35+100 -> 1162.65 | Y94: =40*0.728+50*0.6851 -> 63.375 | Z94: -1 | AE94: =SUM(AA94:AD94) -> 0 | AN94: =SUM(AF94:AM94) -> 0 | AP94: =SUM(W94:Z94,AE94,AN94,AO94) -> 1225.025 | AS94: ='Daily Halba'!$U94-'Daily Halba'!$AP94 -> 3120.5005
A95: 46034 | C95: ='ODOMETERS Halba'!J91 -> 1247 | D95: 0.728 | E95: ='Daily Halba'!$C95*'Daily Halba'!$D95 -> 907.816 | F95: ='ODOMETERS Halba'!K91 -> 1792 | G95: 0.728 | H95: ='Daily Halba'!$F95*'Daily Halba'!$G95 -> 1304.576 | I95: ='Daily Halba'!$C95+'Daily Halba'!$F95 -> 3039 | J95: ='Daily Halba'!$I95*'Daily Halba'!$G95 -> 2212.392 | K95: ='ODOMETERS Halba'!L91 -> 696 | L95: 0.6851 | M95: ='Daily Halba'!$K95*'Daily Halba'!$L95 -> 476.8296 | N95: =250/89.7+250/89.7+5 -> 10.574136 | O95: =600/89.7+5+400/89.7 -> 16.148272 | P95: =6*1200/89.7 -> 80.267559 | Q95: 5 | R95: 1800 | T95: =300/89.7 -> 3.3444816 | U95: =SUM('Daily Halba'!$E95,'Daily Halba'!$H95,$M95:$T95) -> 4604.556 | W95: =5+26+3000/89.7+115*0.6851+3900000/89700+10+500/89.7 -> 202.28371 | Y95: =(27+40)*0.728+96 -> 144.776 | AC95: 195 | AE95: =SUM(AA95:AD95) -> 195 | AI95: =1000/89.7 -> 11.148272 | AJ95: 182 | AN95: =SUM(AF95:AM95) -> 193.14827 | AP95: =SUM(W95:Z95,AE95,AN95,AO95) -> 735.20798 | AS95: ='Daily Halba'!$U95-'Daily Halba'!$AP95 -> 3869.3481
A96: 46035 | B96: Pre Price | C96: ='ODOMETERS Halba'!J92 -> 761 | D96: 0.728 | E96: ='Daily Halba'!$C96*'Daily Halba'!$D96 -> 554.008 | F96: ='ODOMETERS Halba'!K92 -> 450 | G96: 0.728 | H96: ='Daily Halba'!$F96*'Daily Halba'!$G96 -> 327.6 | I96: ='Daily Halba'!$C96+'Daily Halba'!$F96 -> 1211 | J96: ='Daily Halba'!$I96*'Daily Halba'!$G96 -> 881.608 | K96: ='ODOMETERS Halba'!L92 -> 1924 | L96: 0.6851 | M96: ='Daily Halba'!$K96*'Daily Halba'!$L96 -> 1318.1324 | N96: 5 | P96: 13.37 | S96: 725 | U96: =SUM('Daily Halba'!$E96,'Daily Halba'!$H96,$M96:$T96) -> 2943.1104 | W96: =60+1165 -> 1225 | Z96: 8 | AC96: 78 | AE96: =SUM(AA96:AD96) -> 78 | AH96: 70 | AL96: 81 | AN96: =SUM(AF96:AM96) -> 151 | AP96: =SUM(W96:Z96,AE96,AN96,AO96) -> 1462 | AQ96: R&M: Preparing oil Change Joura, New Assets: Rfouf | AS96: ='Daily Halba'!$U96-'Daily Halba'!$AP96 -> 1481.1104
A97: 46035 | B97: Post Price | C97: ='ODOMETERS Halba'!J93 -> 499 | D97: 0.7313 | E97: ='Daily Halba'!$C97*'Daily Halba'!$D97 -> 364.9187 | F97: ='ODOMETERS Halba'!K93 -> 614 | G97: 0.7313 | H97: ='Daily Halba'!$F97*'Daily Halba'!$G97 -> 449.0182 | I97: ='Daily Halba'!$C97+'Daily Halba'!$F97 -> 1113 | J97: ='Daily Halba'!$I97*'Daily Halba'!$G97 -> 813.9369 | K97: ='ODOMETERS Halba'!L93 -> 508 | L97: 0.6867 | M97: ='Daily Halba'!$K97*'Daily Halba'!$L97 -> 348.8436 | N97: 5 | P97: 68.93 | S97: 49 | U97: =SUM('Daily Halba'!$E97,'Daily Halba'!$H97,$M97:$T97) -> 1285.7105 | W97: =12+32+156 -> 200 | AE97: =SUM(AA97:AD97) -> 0 | AN97: =SUM(AF97:AM97) -> 0 | AP97: =SUM(W97:Z97,AE97,AN97,AO97) -> 200 | AS97: ='Daily Halba'!$U97-'Daily Halba'!$AP97 -> 1085.7105
A98: 46036 | C98: ='ODOMETERS Halba'!J94 -> 1707 | D98: 0.7313 | E98: ='Daily Halba'!$C98*'Daily Halba'!$D98 -> 1248.3291 | F98: ='ODOMETERS Halba'!K94 -> 776 | G98: 0.7313 | H98: ='Daily Halba'!$F98*'Daily Halba'!$G98 -> 567.4888 | I98: ='Daily Halba'!$C98+'Daily Halba'!$F98 -> 2483 | J98: ='Daily Halba'!$I98*'Daily Halba'!$G98 -> 1815.8179 | K98: ='ODOMETERS Halba'!L94 -> 4591 | L98: 0.6867 | M98: ='Daily Halba'!$K98*'Daily Halba'!$L98 -> 3152.6397 | N98: 2.78 | P98: 111.48 | S98: =1141+400 -> 1541 | T98: 27.52 | U98: =SUM('Daily Halba'!$E98,'Daily Halba'!$H98,$M98:$T98) -> 6651.2376 | W98: =124+2826 -> 2950 | Y98: 66 | Z98: -23 | AC98: 105 | AE98: =SUM(AA98:AD98) -> 105 | AN98: =SUM(AF98:AM98) -> 0 | AP98: =SUM(W98:Z98,AE98,AN98,AO98) -> 3098 | AS98: ='Daily Halba'!$U98-'Daily Halba'!$AP98 -> 3553.2376
A99: 46037 | C99: ='ODOMETERS Halba'!J95 -> 1689 | D99: 0.7313 | E99: ='Daily Halba'!$C99*'Daily Halba'!$D99 -> 1235.1657 | F99: ='ODOMETERS Halba'!K95 -> 1153 | G99: 0.7313 | H99: ='Daily Halba'!$F99*'Daily Halba'!$G99 -> 843.1889 | I99: ='Daily Halba'!$C99+'Daily Halba'!$F99 -> 2842 | J99: ='Daily Halba'!$I99*'Daily Halba'!$G99 -> 2078.3546 | K99: ='ODOMETERS Halba'!L95 -> 2032 | L99: 0.6867 | M99: ='Daily Halba'!$K99*'Daily Halba'!$L99 -> 1395.3744 | N99: 3 | O99: 3 | P99: 55.8 | Q99: 5 | S99: 1074 | T99: 4.18 | U99: =SUM('Daily Halba'!$E99,'Daily Halba'!$H99,$M99:$T99) -> 4618.709 | W99: =454.52+958 -> 1412.52 | Y99: =50*0.7313 -> 36.565 | AC99: 117.63 | AE99: =SUM(AA99:AD99) -> 117.63 | AI99: 10 | AN99: =SUM(AF99:AM99) -> 10 | AP99: =SUM(W99:Z99,AE99,AN99,AO99) -> 1576.715 | AS99: ='Daily Halba'!$U99-'Daily Halba'!$AP99 -> 3041.994
A100: 46038 | B100: Pre Price | C100: ='ODOMETERS Halba'!J96 -> 901 | D100: 0.7313 | E100: ='Daily Halba'!$C100*'Daily Halba'!$D100 -> 658.9013 | F100: ='ODOMETERS Halba'!K96 -> 520 | G100: 0.7313 | H100: ='Daily Halba'!$F100*'Daily Halba'!$G100 -> 380.276 | I100: ='Daily Halba'!$C100+'Daily Halba'!$F100 -> 1421 | J100: ='Daily Halba'!$I100*'Daily Halba'!$G100 -> 1039.1773 | K100: ='ODOMETERS Halba'!L96 -> 418 | L100: 0.6867 | M100: ='Daily Halba'!$K100*'Daily Halba'!$L100 -> 287.0406 | N100: 11.7 | O100: 3 | P100: 27.87 | T100: 1.67 | U100: =SUM('Daily Halba'!$E100,'Daily Halba'!$H100,$M100:$T100) -> 1370.4579 | W100: 210.57 | Y100: 14.62 | AE100: =SUM(AA100:AD100) -> 0 | AN100: =SUM(AF100:AM100) -> 0 | AP100: =SUM(W100:Z100,AE100,AN100,AO100) -> 225.19 | AS100: ='Daily Halba'!$U100-'Daily Halba'!$AP100 -> 1145.2679
A101: 46038 | B101: Post Price | C101: ='ODOMETERS Halba'!J97 -> 739 | D101: 0.738 | E101: ='Daily Halba'!$C101*'Daily Halba'!$D101 -> 545.382 | F101: ='ODOMETERS Halba'!K97 -> 682 | G101: 0.738 | H101: ='Daily Halba'!$F101*'Daily Halba'!$G101 -> 503.316 | I101: ='Daily Halba'!$C101+'Daily Halba'!$F101 -> 1421 | J101: ='Daily Halba'!$I101*'Daily Halba'!$G101 -> 1048.698 | K101: ='ODOMETERS Halba'!L97 -> 541 | L101: 0.6923 | M101: ='Daily Halba'!$K101*'Daily Halba'!$L101 -> 374.5343 | N101: =8+6.5 -> 14.5 | O101: 3 | P101: =1250/89.7 -> 13.93534 | S101: =10+850+2000/89.7 -> 882.29654 | T101: =375/89.7 -> 4.180602 | U101: =SUM('Daily Halba'!$E101,'Daily Halba'!$H101,$M101:$T101) -> 2341.1448 | W101: =20+23+29 -> 72 | Y101: =(20+18+10+9+20)*0.738 -> 56.826 | AE101: =SUM(AA101:AD101) -> 0 | AN101: =SUM(AF101:AM101) -> 0 | AP101: =SUM(W101:Z101,AE101,AN101,AO101) -> 128.826 | AS101: ='Daily Halba'!$U101-'Daily Halba'!$AP101 -> 2212.3188
...

Sheet BM Stock Halba
A1: OUT | H1: IN
A2: Type | B2: Initial | C2: Out | D2: In | E2: Current | H2: Date | I2: Benzine 1 | J2: Benzine 2 | K2: Benzine Backup | L2: Mezout | M2: Price | N2: Total
A3: Benzine 1 | B3: =8567-189+224+551+2463-41+88 -> 11663 | C3: ='ODOMETERS Halba'!J1 -> 494093 | D3: =I184 -> 494820 | E3: =B3-C3+D3 -> 12390 | H3: 45967 | L3: 2987 | M3: =14.25/20 -> 0.7125 | N3: =SUM('BM Stock Halba'!$I3:$L3)*'BM Stock Halba'!$M3 -> 2128.2375
A4: Benzine 2 | B4: =6041-96-1947-142+16 -> 3872 | C4: ='ODOMETERS Halba'!K1 -> 396810 | D4: =J184 -> 401968 | E4: =B4-C4+D4 -> 9030 | H4: 45967 | I4: 4849 | M4: =14.4/20 -> 0.72 | N4: =SUM('BM Stock Halba'!$I4:$L4)*'BM Stock Halba'!$M4 -> 3491.28
A5: Total Benzine | B5: =B3+B4 -> 15535 | C5: =C3+C4 -> 890903 | D5: =D3+D4 -> 896788 | E5: =E3+E4 -> 21420 | H5: 45971 | I5: 3025 | J5: =2950+3095 -> 6045 | M5: =14.55/20 -> 0.7275 | N5: =SUM('BM Stock Halba'!$I5:$L5)*'BM Stock Halba'!$M5 -> 6598.425
A6: Mezout | B6: =16143-24-636+256 -> 15739 | C6: ='ODOMETERS Halba'!L1 -> 315152 | D6: =L184 -> 303103 | E6: =B6-C6+D6 -> 3690 | H6: 45972 | L6: 4078 | M6: =14.55/20 -> 0.7275 | N6: =SUM('BM Stock Halba'!$I6:$L6)*'BM Stock Halba'!$M6 -> 2966.745
A7: GRAND TOTAL | B7: =SUM(B5:B6) -> 31274 | C7: =SUM(C5:C6) -> 1206055 | D7: =SUM(D5:D6) -> 1199891 | E7: =SUM(E5:E6) -> 25110 | H7: 45972 | I7: 4625 | M7: =14.55/20 -> 0.7275 | N7: =SUM('BM Stock Halba'!$I7:$L7)*'BM Stock Halba'!$M7 -> 3364.6875
H8: 45974 | L8: 8748 | M8: 0.74 | N8: =SUM('BM Stock Halba'!$I8:$L8)*'BM Stock Halba'!$M8 -> 6473.52
H9: 45974 | I9: 7010 | J9: 9897 | M9: 0.7275 | N9: =SUM('BM Stock Halba'!$I9:$L9)*'BM Stock Halba'!$M9 -> 12299.843
H10: 45981 | L10: 8098 | M10: 0.7125 | N10: =SUM('BM Stock Halba'!$I10:$L10)*'BM Stock Halba'!$M10 -> 5769.825
H11: 45981 | I11: 8859 | J11: 3085 | M11: 0.746 | N11: =SUM('BM Stock Halba'!$I11:$L11)*'BM Stock Halba'!$M11 -> 8910.224
H12: 45987 | I12: 9903 | J12: 6059 | M12: 0.7495 | N12: =SUM('BM Stock Halba'!$I12:$L12)*'BM Stock Halba'!$M12 -> 11963.519
H13: 45994 | I13: 4166 | J13: 4088 | M13: 0.75 | N13: =SUM('BM Stock Halba'!$I13:$L13)*'BM Stock Halba'!$M13 -> 6190.5
H14: 45996 | I14: 4096 | J14: 3071 | M14: 0.75 | N14: =SUM('BM Stock Halba'!$I14:$L14)*'BM Stock Halba'!$M14 -> 5375.25
H15: 45996 | L15: 2962 | M15: 0.7495 | N15: =SUM('BM Stock Halba'!$I15:$L15)*'BM Stock Halba'!$M15 -> 2220.019
H16: 45998 | L16: 3085 | M16: 0.743 | N16: =SUM('BM Stock Halba'!$I16:$L16)*'BM Stock Halba'!$M16 -> 2292.155
H17: 46000 | I17: =3068+4092 -> 7160 | J17: =2998+2944 -> 5942 | M17: =14.95/20 -> 0.7475 | N17: =SUM('BM Stock Halba'!$I17:$L17)*'BM Stock Halba'!$M17 -> 9793.745
H18: 46003 | L18: 6082 | M18: =14.3/20 -> 0.715 | N18: =SUM('BM Stock Halba'!$I18:$L18)*'BM Stock Halba'!$M18 -> 4348.63
H19: 46003 | I19: 4099 | J19: 2948 | M19: =14.86/20 -> 0.743 | N19: =SUM('BM Stock Halba'!$I19:$L19)*'BM Stock Halba'!$M19 -> 5235.921
H20: 46007 | I20: 5960 | J20: 3070 | M20: =14.66/20 -> 0.733 | N20: =SUM('BM Stock Halba'!$I20:$L20)*'BM Stock Halba'!$M20 -> 6618.99
H21: 46007 | L21: 4021 | M21: =13.98/20 -> 0.699 | N21: =SUM('BM Stock Halba'!$I21:$L21)*'BM Stock Halba'!$M21 -> 2810.679
H22: 46010 | I22: 4896 | J22: 4662 | M22: =14.37/20 -> 0.7185 | N22: =SUM('BM Stock Halba'!$I22:$L22)*'BM Stock Halba'!$M22 -> 6867.423
H23: 46010 | L23: 3079 | M23: =13.68/20 -> 0.684 | N23: =SUM('BM Stock Halba'!$I23:$L23)*'BM Stock Halba'!$M23 -> 2106.036
H24: 46013 | L24: 226 | M24: Return to tank
H25: 46013 | I25: 2985 | M25: =14.32/20 -> 0.716 | N25: =SUM('BM Stock Halba'!$I25:$L25)*'BM Stock Halba'!$M25 -> 2137.26
H26: 46013 | L26: 600 | M26: =13.64/20 -> 0.682 | N26: =SUM('BM Stock Halba'!$I26:$L26)*'BM Stock Halba'!$M26 -> 409.2
H27: 46014 | J27: 4116 | M27: =14.1/20 -> 0.705 | N27: =SUM('BM Stock Halba'!$I27:$L27)*'BM Stock Halba'!$M27 -> 2901.78
H28: 46014 | L28: 4186 | M28: =13.44/20 -> 0.672 | N28: =SUM('BM Stock Halba'!$I28:$L28)*'BM Stock Halba'!$M28 -> 2812.992
H29: 46015 | I29: 6090 | M29: =14.1/20 -> 0.705 | N29: =SUM('BM Stock Halba'!$I29:$L29)*'BM Stock Halba'!$M29 -> 4293.45
H30: 46017 | L30: 3012 | M30: =13.23/20 -> 0.6615 | N30: =SUM('BM Stock Halba'!$I30:$L30)*'BM Stock Halba'!$M30 -> 1992.438
H31: 46017 | I31: 4671 | J31: 4121 | M31: =13.8/20 -> 0.69 | N31: =SUM('BM Stock Halba'!$I31:$L31)*'BM Stock Halba'!$M31 -> 6066.48
H32: 46021 | I32: 4114 | J32: 3084 | M32: =13.7/20 -> 0.685 | N32: =SUM('BM Stock Halba'!$I32:$L32)*'BM Stock Halba'!$M32 -> 4930.63
H33: 46021 | L33: 4109 | M33: =13.11/20 -> 0.6555 | N33: =SUM('BM Stock Halba'!$I33:$L33)*'BM Stock Halba'!$M33 -> 2693.4495
H34: 46022 | I34: 4895 | M34: =13.62/20 -> 0.681 | N34: =SUM('BM Stock Halba'!$I34:$L34)*'BM Stock Halba'!$M34 -> 3333.495
H35: 46022 | L35: 4033 | M35: =13.11/20 -> 0.6555 | N35: =SUM('BM Stock Halba'!$I35:$L35)*'BM Stock Halba'!$M35 -> 2643.6315
H36: 46024 | I36: 2500 | J36: 4114 | M36: =13.35/20 -> 0.6675 | N36: =SUM('BM Stock Halba'!$I36:$L36)*'BM Stock Halba'!$M36 -> 4414.845
H37: 46024 | L37: 4111 | M37: =12.97/20 -> 0.6485 | N37: =SUM('BM Stock Halba'!$I37:$L37)*'BM Stock Halba'!$M37 -> 2665.9835
H38: 46027 | I38: 4027 | J38: 2969 | M38: =13.45/20 -> 0.6725 | N38: =SUM('BM Stock Halba'!$I38:$L38)*'BM Stock Halba'!$M38 -> 4704.81
H39: 46027 | L39: 3080 | M39: =13.07/20 -> 0.6535 | N39: =SUM('BM Stock Halba'!$I39:$L39)*'BM Stock Halba'!$M39 -> 2012.78
H40: 46029 | I40: 4184 | J40: 4119 | M40: =13.3/20 -> 0.665 | N40: =SUM('BM Stock Halba'!$I40:$L40)*'BM Stock Halba'!$M40 -> 5521.495
H41: 46029 | L41: 4670 | M41: =13.05/20 -> 0.6525 | N41: =SUM('BM Stock Halba'!$I41:$L41)*'BM Stock Halba'!$M41 -> 3047.175
H42: 46031 | L42: 9573 | M42: =13/20 -> 0.65 | N42: =SUM('BM Stock Halba'!$I42:$L42)*'BM Stock Halba'!$M42 -> 6222.45
H43: 46031 | I43: 4120 | M43: =13.3/20 -> 0.665 | N43: =SUM('BM Stock Halba'!$I43:$L43)*'BM Stock Halba'!$M43 -> 2739.8
H44: 46034 | I44: =4669+4185 -> 8854 | J44: =4105+4120 -> 8225 | M44: =13.3/20 -> 0.665 | N44: =SUM('BM Stock Halba'!$I44:$L44)*'BM Stock Halba'!$M44 -> 11357.535
H45: 46034 | L45: 4909 | M45: =13/20 -> 0.65 | N45: =SUM('BM Stock Halba'!$I45:$L45)*'BM Stock Halba'!$M45 -> 3190.85
H46: 46036 | L46: =4168+4884+4088 -> 13140 | M46: =13.05/20 -> 0.6525 | N46: =SUM('BM Stock Halba'!$I46:$L46)*'BM Stock Halba'!$M46 -> 8573.85
H47: 46037 | I47: 4040 | J47: 2975 | M47: =13.4/20 -> 0.67 | N47: =SUM('BM Stock Halba'!$I47:$L47)*'BM Stock Halba'!$M47 -> 4700.05
H48: 46038 | J48: 4113 | M48: =13.4/20 -> 0.67 | N48: 4113
H49: 46038 | I49: 3085 | M49: =13.09/20 -> 0.6545 | N49: ='BM Stock Halba'!$M49*'BM Stock Halba'!$I49 -> 2019.1325
H50: 46039 | I50: 14276 | M50: =13.4/20 -> 0.67 | N50: ='BM Stock Halba'!$I50*'BM Stock Halba'!$M50 -> 9564.92
H51: 46039 | I51: 44 | M51: 0 | N51: Return to tank
H52: 46041 | I52: 3021 | J52: 2981 | M52: =13.4/20 -> 0.67 | N52: =SUM('BM Stock Halba'!$I52:$L52)*'BM Stock Halba'!$M52 -> 4021.34
H53: 46044 | L53: 4907 | M53: =13.2/20 -> 0.66 | N53: =SUM('BM Stock Halba'!$I53:$L53)*'BM Stock Halba'!$M53 -> 3238.62
H54: 46045 | J54: 4121 | M54: =13.55/20 -> 0.6775 | N54: =SUM('BM Stock Halba'!$I54:$L54)*'BM Stock Halba'!$M54 -> 2791.9775
H55: 46048 | I55: =3026+3096+4130 -> 10252 | J55: 2986 | M55: =13.6/20 -> 0.68 | N55: ='BM Stock Halba'!$M55*SUM('BM Stock Halba'!$I55:$J55) -> 9001.84
H56: 46048 | L56: =4040+2964+4893+4175 -> 16072 | M56: =13.3/20 -> 0.665 | N56: ='BM Stock Halba'!$M56*'BM Stock Halba'!$L56 -> 10687.88
H57: 46050 | I57: 4676 | J57: =4126+4111 -> 8237 | M57: =13.7/20 -> 0.685 | N57: =SUM('BM Stock Halba'!$I57:$J57)*'BM Stock Halba'!$M57 -> 8845.405
H58: 46051 | I58: 4112 | J58: 4037 | M58: =13.7/20 -> 0.685 | N58: ='BM Stock Halba'!$M58*('BM Stock Halba'!$I58+'BM Stock Halba'!$J58) -> 5582.065
H59: 46055 | I59: 8142 | J59: 9066 | M59: =13.88/20 -> 0.694 | N59: =SUM(Table_6[[#This Row],[Benzine 1]:[Mezout]])*Table_6[[#This Row],[Price]] -> 11942.352
H60: 46055 | L60: 8759 | M60: =13.7/20 -> 0.685 | N60: =Table_6[[#This Row],[Mezout]]*Table_6[[#This Row],[Price]] -> 5999.915
H61: 46064 | I61: 80 | M61: 0 | N61: Return to tank
H62: 46064 | I62: =4121+4186+4106 -> 12413 | J62: =4906+4671 -> 9577 | M62: =13.97/20 -> 0.6985 | N62: =SUM(Table_6[[#This Row],[Benzine 1]:[Benzine 2]])*Table_6[[#This Row],[Price]] -> 15360.015
H63: 46065 | L63: 6078 | M63: =13.99/20 -> 0.6995 | N63: =Table_6[[#This Row],[Price]]*Table_6[[#This Row],[Mezout]] -> 4251.561
H64: 46069 | I64: =4105+4025 -> 8130 | J64: =3008+3078+2968 -> 9054 | M64: =14.12/20 -> 0.706 | N64: =SUM(Table_6[[#This Row],[Benzine 1]:[Mezout]])*M64 -> 12131.904
H65: 46069 | L65: 4892 | M65: =14.09/20 -> 0.7045 | N65: =Table_6[[#This Row],[Price]]*Table_6[[#This Row],[Mezout]] -> 3446.414
H66: 46075 | L66: 220 | M66: 0 | N66: Return to tank
H67: 46076 | I67: 8133 | J67: 4897 | M67: =17.99/20 -> 0.8995 | N67: =(Table_6[[#This Row],[Benzine 1]]+Table_6[[#This Row],[Benzine 2]])*Table_6[[#This Row],[Price]] -> 11720.485
H68: 46076 | L68: 12006 | M68: =14.19/20 -> 0.7095 | N68: =Table_6[[#This Row],[Mezout]]*Table_6[[#This Row],[Price]] -> 8518.257
H69: 46079 | L69: 4883 | M69: =14.21/20 -> 0.7105 | N69: =Table_6[[#This Row],[Price]]*Table_6[[#This Row],[Mezout]] -> 3469.3715
H70: 46080 | I70: 4674 | J70: 4909 | M70: =18.23/20 -> 0.9115 | N70: =(Table_6[[#This Row],[Benzine 1]]+Table_6[[#This Row],[Benzine 2]])*Table_6[[#This Row],[Price]] -> 8734.9045
H71: 46082 | I71: 7104 | J71: =4000+4073+2964 -> 11037 | M71: =18.23/20 -> 0.9115 | N71: =SUM(Table_6[[#This Row],[Benzine 1]:[Benzine 2]])*0.9115 -> 16535.521
H72: 46083 | I72: 6102 | M72: =18.23/20 -> 0.9115 | N72: =Table_6[[#This Row],[Benzine 1]]*Table_6[[#This Row],[Price]] -> 5561.973
H73: 46083 | L73: 4905 | M73: =14.38/20 -> 0.719 | N73: =Table_6[[#This Row],[Mezout]]*Table_6[[#This Row],[Price]] -> 3526.695
H74: 46084 | I74: 4169 | J74: =4885+4652 -> 9537 | M74: Coupons
H75: 46085 | J75: 4117 | M75: =18.35/20 -> 0.9175 | N75: =Table_6[[#This Row],[Benzine 2]]*Table_6[[#This Row],[Price]] -> 3777.3475
H76: 46086 | L76: 9583 | M76: =18.23/20 -> 0.9115 | N76: =Table_6[[#This Row],[Mezout]]*Table_6[[#This Row],[Price]] -> 8734.9045
H77: 46090 | I77: 4683 | J77: 4132 | M77: =19.36/20 -> 0.968 | N77: =SUM(Table_6[[#This Row],[Benzine 1]:[Benzine 2]])*Table_6[[#This Row],[Price]] -> 8532.92
H78: 46090 | L78: 4909 | M78: =17.22/20 -> 0.861 | N78: =Table_6[[#This Row],[Price]]*Table_6[[#This Row],[Mezout]] -> 4226.649
H79: 46092 | I79: 2980 | J79: 4042 | M79: =20.35/20 -> 1.0175 | N79: =SUM(Table_6[[#This Row],[Benzine 1]:[Benzine 2]])*Table_6[[#This Row],[Price]] -> 7144.885
H80: 46092 | L80: 4136 | M80: =19.63/20 -> 0.9815 | N80: =Table_6[[#This Row],[Mezout]]*Table_6[[#This Row],[Price]] -> 4059.484
H81: 46093 | I81: 4120 | J81: =3019+3089 -> 6108 | M81: =20.35/20 -> 1.0175 | N81: =SUM(Table_6[[#This Row],[Benzine 1]:[Benzine 2]])*Table_6[[#This Row],[Price]] -> 10406.99
H82: 46093 | L82: =4033+2974+2959 -> 9966 | M82: =(19.28+0.35)/20 -> 0.9815 | N82: =Table_6[[#This Row],[Mezout]]*Table_6[[#This Row],[Price]] -> 9781.629
H83: 46094 | I83: 4117 | M83: =21.75/20 -> 1.0875 | N83: =Table_6[[#This Row],[Benzine 1]]*Table_6[[#This Row],[Price]] -> 4477.2375
H84: 46099 | I84: =3014+4114 -> 7128 | M84: =22.7/20 -> 1.135 | N84: =Table_6[[#This Row],[Benzine 1]]*Table_6[[#This Row],[Price]] -> 8090.28
H85: 46100 | I85: 4124 | J85: 12897 | M85: =23.56/20 -> 1.178 | N85: =(Table_6[[#This Row],[Benzine 1]]+Table_6[[#This Row],[Benzine 2]])*Table_6[[#This Row],[Price]] -> 20050.738
H86: 46100 | L86: 3084 | M86: =22.45/20 -> 1.1225 | N86: =Table_6[[#This Row],[Price]]*Table_6[[#This Row],[Mezout]] -> 3461.79
H87: 46102 | I87: 5929 | M87: =23.56/20 -> 1.178 | N87: =Table_6[[#This Row],[Benzine 1]]*Table_6[[#This Row],[Price]] -> 6984.362
H88: 46104 | I88: 8193 | M88: =23.6/20 -> 1.18 | N88: =Table_6[[#This Row],[Benzine 1]]*Table_6[[#This Row],[Price]] -> 9667.74
H89: 46108 | L89: 12959 | M89: =24.39/20 -> 1.2195 | N89: =Table_6[[#This Row],[Mezout]]*Table_6[[#This Row],[Price]] -> 15803.501
H90: 46108 | L90: 300 | M90: Return to tank | N90: Return to tank
H91: 46112 | J91: 11179 | M91: Coupons | N91: 8939
H92: 46114 | J92: 7200 | M92: =24.73/20 -> 1.2365 | N92: =Table_6[[#This Row],[Benzine 2]]*Table_6[[#This Row],[Price]] -> 8902.8
H93: 46119 | I93: 4174 | J93: 4657 | M93: =24.5/20 -> 1.225 | N93: =(Table_6[[#This Row],[Benzine 1]]+Table_6[[#This Row],[Benzine 2]])*Table_6[[#This Row],[Price]] -> 10817.975
H94: 46119 | L94: 40 | M94: Return to tank
H95: 46088 | I95: 500 | J95: -500 | M95: internal transfer | N95: within halba 500, to tekrit 3000
H96: 46121 | L96: -3380 | M96: direct sale to Saleh
H97: 46122
H98: 46122 | I98: =4898+4100+3007 -> 12005 | J98: 4663 | M98: =24.5/20 -> 1.225 | N98: =(Table_6[[#This Row],[Benzine 1]]+Table_6[[#This Row],[Benzine 2]])*Table_6[[#This Row],[Price]] -> 20418.3
H99: 46127 | L99: 3078 | M99: =26.61/20 -> 1.3305 | N99: =Table_6[[#This Row],[Price]]*Table_6[[#This Row],[Mezout]] -> 4095.279
H100: 46128 | J100: =2000+17763 -> 19763 | M100: =24.6/20 -> 1.23 | N100: =17763*Table_6[[#This Row],[Price]] -> 21848.49
...

Sheet ODOMETERS Halba
A1: Initial Odo | C1: Sales In Liters | H1: 6416973 | J1: =SUM(Table_1[Benzine 1]) -> 494093 | K1: =SUM(Table_1[Benzine 2]) -> 396810 | L1: =SUM(Table_1[Mezout]) -> 315152
A2: Date | B2: At new Pricing | C2: Benzine 1 A | D2: Benzine 1 B | E2: Benzine 2 A | F2: Benzine B | G2: Mezout A | H2: Mezout B | I2: NOTHING HERE | J2: Benzine 1 | K2: Benzine 2 | L2: Mezout | M2: total
A3: Initial Odo | C3: 36249 | D3: 12951 | E3: 27540 | F3: 7191 | G3: 6614230 | H3: 6416973
A4: 45965 | C4: 37203 | D4: 13431 | E4: 28569 | F4: 7466 | G4: 6614729 | H4: 6417061 | J4: ='ODOMETERS Halba'!$C4+'ODOMETERS Halba'!$D4-D3-C3 -> 1434 | K4: ='ODOMETERS Halba'!$E4+'ODOMETERS Halba'!$F4-F3-E3 -> 1304 | L4: ='ODOMETERS Halba'!$G4+'ODOMETERS Halba'!$H4-H3-G3 -> 587 | M4: ='ODOMETERS Halba'!$J4+'ODOMETERS Halba'!$K4+'ODOMETERS Halba'!$L4 -> 3325
A5: 45966 | C5: 37855 | D5: 13814 | E5: 29326 | F5: 7605 | G5: 6615020 | H5: 6417187 | J5: ='ODOMETERS Halba'!$C5+'ODOMETERS Halba'!$D5-D4-C4 -> 1035 | K5: ='ODOMETERS Halba'!$E5+'ODOMETERS Halba'!$F5-F4-E4 -> 896 | L5: ='ODOMETERS Halba'!$G5+'ODOMETERS Halba'!$H5-H4-G4 -> 417 | M5: ='ODOMETERS Halba'!$J5+'ODOMETERS Halba'!$K5+'ODOMETERS Halba'!$L5 -> 2348
A6: 45967 | C6: 38625 | D6: 14258 | E6: 30174 | F6: 7731 | G6: 6615340 | H6: 6417308 | J6: ='ODOMETERS Halba'!$C6+'ODOMETERS Halba'!$D6-D5-C5 -> 1214 | K6: ='ODOMETERS Halba'!$E6+'ODOMETERS Halba'!$F6-F5-E5 -> 974 | L6: ='ODOMETERS Halba'!$G6+'ODOMETERS Halba'!$H6-H5-G5 -> 441 | M6: ='ODOMETERS Halba'!$J6+'ODOMETERS Halba'!$K6+'ODOMETERS Halba'!$L6 -> 2629
A7: 45968 | B7: Pre Price | C7: 39057 | D7: 14436 | E7: 30546 | F7: 7817 | G7: 6615535 | H7: 6417425 | J7: ='ODOMETERS Halba'!$C7+'ODOMETERS Halba'!$D7-D6-C6 -> 610 | K7: ='ODOMETERS Halba'!$E7+'ODOMETERS Halba'!$F7-F6-E6 -> 458 | L7: ='ODOMETERS Halba'!$G7+'ODOMETERS Halba'!$H7-H6-G6 -> 312 | M7: ='ODOMETERS Halba'!$J7+'ODOMETERS Halba'!$K7+'ODOMETERS Halba'!$L7 -> 1380
A8: 45968 | B8: Post Price | C8: 39403 | D8: 14617 | E8: 30987 | F8: 7957 | G8: 6615646 | H8: 6417483 | J8: ='ODOMETERS Halba'!$C8+'ODOMETERS Halba'!$D8-D7-C7 -> 527 | K8: ='ODOMETERS Halba'!$E8+'ODOMETERS Halba'!$F8-F7-E7 -> 581 | L8: ='ODOMETERS Halba'!$G8+'ODOMETERS Halba'!$H8-H7-G7 -> 169 | M8: ='ODOMETERS Halba'!$J8+'ODOMETERS Halba'!$K8+'ODOMETERS Halba'!$L8 -> 1277
A9: 45969 | C9: 40689 | D9: 15226 | E9: 31886 | F9: 8117 | G9: 6615904 | H9: 6417659 | J9: ='ODOMETERS Halba'!$C9+'ODOMETERS Halba'!$D9-D8-C8 -> 1895 | K9: ='ODOMETERS Halba'!$E9+'ODOMETERS Halba'!$F9-F8-E8 -> 1059 | L9: ='ODOMETERS Halba'!$G9+'ODOMETERS Halba'!$H9-H8-G8 -> 434 | M9: ='ODOMETERS Halba'!$J9+'ODOMETERS Halba'!$K9+'ODOMETERS Halba'!$L9 -> 3388
A10: 45970 | C10: 42154 | D10: 15849 | E10: 32384 | F10: 8204 | G10: 6616216 | H10: 6419864 | J10: ='ODOMETERS Halba'!$C10+'ODOMETERS Halba'!$D10-D9-C9 -> 2088 | K10: ='ODOMETERS Halba'!$E10+'ODOMETERS Halba'!$F10-F9-E9 -> 585 | L10: ='ODOMETERS Halba'!$G10+'ODOMETERS Halba'!$H10-H9-G9 -> 2517 | M10: ='ODOMETERS Halba'!$J10+'ODOMETERS Halba'!$K10+'ODOMETERS Halba'!$L10 -> 5190
A11: 45971 | C11: 43690 | D11: 16344 | E11: 32643 | F11: 8373 | G11: 6616645 | H11: 6420075 | J11: ='ODOMETERS Halba'!$C11+'ODOMETERS Halba'!$D11-D10-C10 -> 2031 | K11: ='ODOMETERS Halba'!$E11+'ODOMETERS Halba'!$F11-F10-E10 -> 428 | L11: ='ODOMETERS Halba'!$G11+'ODOMETERS Halba'!$H11-H10-G10 -> 640 | M11: ='ODOMETERS Halba'!$J11+'ODOMETERS Halba'!$K11+'ODOMETERS Halba'!$L11 -> 3099
A12: 45972 | B12: Pre Price | C12: 44370 | D12: 16598 | E12: 33056 | F12: 8425 | G12: 6616910 | H12: 6421136 | J12: ='ODOMETERS Halba'!$C12+'ODOMETERS Halba'!$D12-D11-C11 -> 934 | K12: ='ODOMETERS Halba'!$E12+'ODOMETERS Halba'!$F12-F11-E11 -> 465 | L12: ='ODOMETERS Halba'!$G12+'ODOMETERS Halba'!$H12-H11-G11 -> 1326 | M12: ='ODOMETERS Halba'!$J12+'ODOMETERS Halba'!$K12+'ODOMETERS Halba'!$L12 -> 2725
A13: 45972 | B13: Post Price | C13: 44905 | D13: 16973 | E13: 33549 | F13: 8570 | G13: 6617074 | H13: 6421273 | J13: ='ODOMETERS Halba'!$C13+'ODOMETERS Halba'!$D13-D12-C12 -> 910 | K13: ='ODOMETERS Halba'!$E13+'ODOMETERS Halba'!$F13-F12-E12 -> 638 | L13: ='ODOMETERS Halba'!$G13+'ODOMETERS Halba'!$H13-H12-G12 -> 301 | M13: ='ODOMETERS Halba'!$J13+'ODOMETERS Halba'!$K13+'ODOMETERS Halba'!$L13 -> 1849
A14: 45973 | C14: 45759 | D14: 17378 | E14: 34319 | F14: 8762 | G14: 6617575 | H14: 6421888 | J14: ='ODOMETERS Halba'!$C14+'ODOMETERS Halba'!$D14-D13-C13 -> 1259 | K14: ='ODOMETERS Halba'!$E14+'ODOMETERS Halba'!$F14-F13-E13 -> 962 | L14: ='ODOMETERS Halba'!$G14+'ODOMETERS Halba'!$H14-H13-G13 -> 1116 | M14: ='ODOMETERS Halba'!$J14+'ODOMETERS Halba'!$K14+'ODOMETERS Halba'!$L14 -> 3337
A15: 45974 | C15: 46733 | D15: 17981 | E15: 35149 | F15: 8976 | G15: 6617620 | H15: 6422168 | J15: ='ODOMETERS Halba'!$C15+'ODOMETERS Halba'!$D15-D14-C14 -> 1577 | K15: ='ODOMETERS Halba'!$E15+'ODOMETERS Halba'!$F15-F14-E14 -> 1044 | L15: ='ODOMETERS Halba'!$G15+'ODOMETERS Halba'!$H15-H14-G14 -> 325 | M15: ='ODOMETERS Halba'!$J15+'ODOMETERS Halba'!$K15+'ODOMETERS Halba'!$L15 -> 2946
A16: 45975 | B16: Pre Price | C16: 47053 | D16: 18178 | E16: 35542 | F16: 9054 | G16: 6617763 | H16: 6422312 | J16: ='ODOMETERS Halba'!$C16+'ODOMETERS Halba'!$D16-D15-C15 -> 517 | K16: ='ODOMETERS Halba'!$E16+'ODOMETERS Halba'!$F16-F15-E15 -> 471 | L16: ='ODOMETERS Halba'!$G16+'ODOMETERS Halba'!$H16-H15-G15 -> 287 | M16: ='ODOMETERS Halba'!$J16+'ODOMETERS Halba'!$K16+'ODOMETERS Halba'!$L16 -> 1275
A17: 45975 | B17: Post Price | C17: 47416 | D17: 18466 | E17: 35886 | F17: 9144 | G17: 6618052 | H17: 6422675 | J17: ='ODOMETERS Halba'!$C17+'ODOMETERS Halba'!$D17-D16-C16 -> 651 | K17: ='ODOMETERS Halba'!$E17+'ODOMETERS Halba'!$F17-F16-E16 -> 434 | L17: ='ODOMETERS Halba'!$G17+'ODOMETERS Halba'!$H17-H16-G16 -> 652 | M17: ='ODOMETERS Halba'!$J17+'ODOMETERS Halba'!$K17+'ODOMETERS Halba'!$L17 -> 1737
A18: 45976 | C18: 48582 | D18: 18996 | E18: 36555 | F18: 9295 | G18: 6618245 | H18: 6423216 | J18: ='ODOMETERS Halba'!$C18+'ODOMETERS Halba'!$D18-D17-C17 -> 1696 | K18: ='ODOMETERS Halba'!$E18+'ODOMETERS Halba'!$F18-F17-E17 -> 820 | L18: ='ODOMETERS Halba'!$G18+'ODOMETERS Halba'!$H18-H17-G17 -> 734 | M18: ='ODOMETERS Halba'!$J18+'ODOMETERS Halba'!$K18+'ODOMETERS Halba'!$L18 -> 3250
A19: 45977 | C19: 49927 | D19: 19572 | E19: 37404 | F19: 9414 | G19: 6618393 | H19: 6423455 | J19: ='ODOMETERS Halba'!$C19+'ODOMETERS Halba'!$D19-D18-C18 -> 1921 | K19: ='ODOMETERS Halba'!$E19+'ODOMETERS Halba'!$F19-F18-E18 -> 968 | L19: ='ODOMETERS Halba'!$G19+'ODOMETERS Halba'!$H19-H18-G18 -> 387 | M19: ='ODOMETERS Halba'!$J19+'ODOMETERS Halba'!$K19+'ODOMETERS Halba'!$L19 -> 3276
A20: 45978 | C20: 51096 | D20: 20224 | E20: 38006 | F20: 9694 | G20: 6619323 | H20: 6426286 | J20: ='ODOMETERS Halba'!$C20+'ODOMETERS Halba'!$D20-D19-C19 -> 1821 | K20: ='ODOMETERS Halba'!$E20+'ODOMETERS Halba'!$F20-F19-E19 -> 882 | L20: ='ODOMETERS Halba'!$G20+'ODOMETERS Halba'!$H20-H19-G19 -> 3761 | M20: ='ODOMETERS Halba'!$J20+'ODOMETERS Halba'!$K20+'ODOMETERS Halba'!$L20 -> 6464
A21: 45979 | B21: Pre Price | C21: 51531 | D21: 20589 | E21: 38319 | F21: 9826 | G21: 6619353 | H21: 6426327 | J21: ='ODOMETERS Halba'!$C21+'ODOMETERS Halba'!$D21-D20-C20 -> 800 | K21: ='ODOMETERS Halba'!$E21+'ODOMETERS Halba'!$F21-F20-E20 -> 445 | L21: ='ODOMETERS Halba'!$G21+'ODOMETERS Halba'!$H21-H20-G20 -> 71 | M21: ='ODOMETERS Halba'!$J21+'ODOMETERS Halba'!$K21+'ODOMETERS Halba'!$L21 -> 1316
A22: 45979 | B22: Pro Price | C22: 52121 | D22: 20772 | E22: 38674 | F22: 9877 | G22: 6619706 | H22: 6426617 | J22: ='ODOMETERS Halba'!$C22+'ODOMETERS Halba'!$D22-D21-C21 -> 773 | K22: ='ODOMETERS Halba'!$E22+'ODOMETERS Halba'!$F22-F21-E21 -> 406 | L22: ='ODOMETERS Halba'!$G22+'ODOMETERS Halba'!$H22-H21-G21 -> 643 | M22: ='ODOMETERS Halba'!$J22+'ODOMETERS Halba'!$K22+'ODOMETERS Halba'!$L22 -> 1822
A23: 45980 | C23: 53066 | D23: 21263 | E23: 39753 | F23: 10143 | G23: 6620168 | H23: 6426817 | J23: ='ODOMETERS Halba'!$C23+'ODOMETERS Halba'!$D23-D22-C22 -> 1436 | K23: ='ODOMETERS Halba'!$E23+'ODOMETERS Halba'!$F23-F22-E22 -> 1345 | L23: ='ODOMETERS Halba'!$G23+'ODOMETERS Halba'!$H23-H22-G22 -> 662 | M23: ='ODOMETERS Halba'!$J23+'ODOMETERS Halba'!$K23+'ODOMETERS Halba'!$L23 -> 3443
A24: 45981 | C24: 53912 | D24: 21859 | E24: 40455 | F24: 10339 | G24: 6620870 | H24: 6427051 | J24: ='ODOMETERS Halba'!$C24+'ODOMETERS Halba'!$D24-D23-C23 -> 1442 | K24: ='ODOMETERS Halba'!$E24+'ODOMETERS Halba'!$F24-F23-E23 -> 898 | L24: ='ODOMETERS Halba'!$G24+'ODOMETERS Halba'!$H24-H23-G23 -> 936 | M24: ='ODOMETERS Halba'!$J24+'ODOMETERS Halba'!$K24+'ODOMETERS Halba'!$L24 -> 3276
A25: 45982 | B25: Pre Price | C25: 54369 | D25: 22034 | E25: 40840 | F25: 10451 | G25: 6620915 | H25: 6427194 | J25: ='ODOMETERS Halba'!$C25+'ODOMETERS Halba'!$D25-D24-C24 -> 632 | K25: ='ODOMETERS Halba'!$E25+'ODOMETERS Halba'!$F25-F24-E24 -> 497 | L25: ='ODOMETERS Halba'!$G25+'ODOMETERS Halba'!$H25-H24-G24 -> 188 | M25: ='ODOMETERS Halba'!$J25+'ODOMETERS Halba'!$K25+'ODOMETERS Halba'!$L25 -> 1317
A26: 45982 | B26: Post Price | C26: 55051 | D26: 22179 | E26: 41591 | F26: 10535 | G26: 6621753 | H26: 6427432 | J26: ='ODOMETERS Halba'!$C26+'ODOMETERS Halba'!$D26-D25-C25 -> 827 | K26: ='ODOMETERS Halba'!$E26+'ODOMETERS Halba'!$F26-F25-E25 -> 835 | L26: ='ODOMETERS Halba'!$G26+'ODOMETERS Halba'!$H26-H25-G25 -> 1076 | M26: ='ODOMETERS Halba'!$J26+'ODOMETERS Halba'!$K26+'ODOMETERS Halba'!$L26 -> 2738
A27: 45983 | C27: 56491 | D27: 22631 | E27: 42619 | F27: 10747 | G27: 6622029 | H27: 6428687 | J27: ='ODOMETERS Halba'!$C27+'ODOMETERS Halba'!$D27-D26-C26 -> 1892 | K27: ='ODOMETERS Halba'!$E27+'ODOMETERS Halba'!$F27-F26-E26 -> 1240 | L27: ='ODOMETERS Halba'!$G27+'ODOMETERS Halba'!$H27-H26-G26 -> 1531 | M27: ='ODOMETERS Halba'!$J27+'ODOMETERS Halba'!$K27+'ODOMETERS Halba'!$L27 -> 4663
A28: 45984 | C28: 57740 | D28: 23064 | E28: 43263 | F28: 10874 | G28: 6622142 | H28: 6428820 | J28: ='ODOMETERS Halba'!$C28+'ODOMETERS Halba'!$D28-D27-C27 -> 1682 | K28: ='ODOMETERS Halba'!$E28+'ODOMETERS Halba'!$F28-F27-E27 -> 771 | L28: ='ODOMETERS Halba'!$G28+'ODOMETERS Halba'!$H28-H27-G27 -> 246 | M28: ='ODOMETERS Halba'!$J28+'ODOMETERS Halba'!$K28+'ODOMETERS Halba'!$L28 -> 2699
A29: 45985 | C29: 58778 | D29: 23433 | E29: 43915 | F29: 11191 | G29: 6622458 | H29: 6429709 | J29: ='ODOMETERS Halba'!$C29+'ODOMETERS Halba'!$D29-D28-C28 -> 1407 | K29: ='ODOMETERS Halba'!$E29+'ODOMETERS Halba'!$F29-F28-E28 -> 969 | L29: ='ODOMETERS Halba'!$G29+'ODOMETERS Halba'!$H29-H28-G28 -> 1205 | M29: ='ODOMETERS Halba'!$J29+'ODOMETERS Halba'!$K29+'ODOMETERS Halba'!$L29 -> 3581
A30: 45986 | B30: Pre Price | C30: 59315 | D30: 23757 | E30: 44134 | F30: 11301 | G30: 6622534 | H30: 6429750 | J30: ='ODOMETERS Halba'!$C30+'ODOMETERS Halba'!$D30-D29-C29 -> 861 | K30: ='ODOMETERS Halba'!$E30+'ODOMETERS Halba'!$F30-F29-E29 -> 329 | L30: ='ODOMETERS Halba'!$G30+'ODOMETERS Halba'!$H30-H29-G29 -> 117 | M30: ='ODOMETERS Halba'!$J30+'ODOMETERS Halba'!$K30+'ODOMETERS Halba'!$L30 -> 1307
A31: 45986 | B31: Post Price | C31: 59821 | D31: 24025 | E31: 44548 | F31: 11470 | G31: 6622768 | H31: 6429865 | J31: ='ODOMETERS Halba'!$C31+'ODOMETERS Halba'!$D31-D30-C30 -> 774 | K31: ='ODOMETERS Halba'!$E31+'ODOMETERS Halba'!$F31-F30-E30 -> 583 | L31: ='ODOMETERS Halba'!$G31+'ODOMETERS Halba'!$H31-H30-G30 -> 349 | M31: ='ODOMETERS Halba'!$J31+'ODOMETERS Halba'!$K31+'ODOMETERS Halba'!$L31 -> 1706
A32: 45987 | C32: 60604 | D32: 24383 | E32: 45239 | F32: 11635 | G32: 6623036 | H32: 6430069 | J32: ='ODOMETERS Halba'!$C32+'ODOMETERS Halba'!$D32-D31-C31 -> 1141 | K32: ='ODOMETERS Halba'!$E32+'ODOMETERS Halba'!$F32-F31-E31 -> 856 | L32: ='ODOMETERS Halba'!$G32+'ODOMETERS Halba'!$H32-H31-G31 -> 472 | M32: ='ODOMETERS Halba'!$J32+'ODOMETERS Halba'!$K32+'ODOMETERS Halba'!$L32 -> 2469
A33: 45988 | C33: 61862 | D33: 24824 | E33: 46054 | F33: 11835 | G33: 6623086 | H33: 6430425 | J33: ='ODOMETERS Halba'!$C33+'ODOMETERS Halba'!$D33-D32-C32 -> 1699 | K33: ='ODOMETERS Halba'!$E33+'ODOMETERS Halba'!$F33-F32-E32 -> 1015 | L33: ='ODOMETERS Halba'!$G33+'ODOMETERS Halba'!$H33-H32-G32 -> 406 | M33: ='ODOMETERS Halba'!$J33+'ODOMETERS Halba'!$K33+'ODOMETERS Halba'!$L33 -> 3120
A34: 45989 | C34: 63112 | D34: 25248 | E34: 47214 | F34: 12094 | G34: 6623672 | H34: 6430560 | J34: ='ODOMETERS Halba'!$C34+'ODOMETERS Halba'!$D34-D33-C33 -> 1674 | K34: ='ODOMETERS Halba'!$E34+'ODOMETERS Halba'!$F34-F33-E33 -> 1419 | L34: ='ODOMETERS Halba'!$G34+'ODOMETERS Halba'!$H34-H33-G33 -> 721 | M34: ='ODOMETERS Halba'!$J34+'ODOMETERS Halba'!$K34+'ODOMETERS Halba'!$L34 -> 3814
A35: 45990 | C35: 64457 | D35: 25591 | E35: 48256 | F35: 12251 | G35: 6624057 | H35: 6430767 | J35: ='ODOMETERS Halba'!$C35+'ODOMETERS Halba'!$D35-D34-C34 -> 1688 | K35: ='ODOMETERS Halba'!$E35+'ODOMETERS Halba'!$F35-F34-E34 -> 1199 | L35: ='ODOMETERS Halba'!$G35+'ODOMETERS Halba'!$H35-H34-G34 -> 592 | M35: ='ODOMETERS Halba'!$J35+'ODOMETERS Halba'!$K35+'ODOMETERS Halba'!$L35 -> 3479
A36: 45991 | C36: 65519 | D36: 25969 | E36: 49099 | F36: 12329 | G36: 6624684 | H36: 6430902 | J36: ='ODOMETERS Halba'!$C36+'ODOMETERS Halba'!$D36-D35-C35 -> 1440 | K36: ='ODOMETERS Halba'!$E36+'ODOMETERS Halba'!$F36-F35-E35 -> 921 | L36: ='ODOMETERS Halba'!$G36+'ODOMETERS Halba'!$H36-H35-G35 -> 762 | M36: ='ODOMETERS Halba'!$J36+'ODOMETERS Halba'!$K36+'ODOMETERS Halba'!$L36 -> 3123
A37: 45992 | C37: 66817 | D37: 26228 | E37: 49792 | F37: 12565 | G37: 6624988 | H37: 6434444 | J37: ='ODOMETERS Halba'!$C37+'ODOMETERS Halba'!$D37-D36-C36 -> 1557 | K37: ='ODOMETERS Halba'!$E37+'ODOMETERS Halba'!$F37-F36-E36 -> 929 | L37: ='ODOMETERS Halba'!$G37+'ODOMETERS Halba'!$H37-H36-G36+2091 -> 5937 | M37: ='ODOMETERS Halba'!$J37+'ODOMETERS Halba'!$K37+'ODOMETERS Halba'!$L37 -> 8423
A38: 45993 | C38: 67917 | D38: 26621 | E38: 50680 | F38: 12805 | G38: 6625337 | H38: 6435377 | J38: ='ODOMETERS Halba'!$C38+'ODOMETERS Halba'!$D38-D37-C37 -> 1493 | K38: ='ODOMETERS Halba'!$E38+'ODOMETERS Halba'!$F38-F37-E37 -> 1128 | L38: ='ODOMETERS Halba'!$G38+'ODOMETERS Halba'!$H38-H37-G37 -> 1282 | M38: ='ODOMETERS Halba'!$J38+'ODOMETERS Halba'!$K38+'ODOMETERS Halba'!$L38 -> 3903
A39: 45994 | B39: Pre Price | C39: 68254 | D39: 26720 | E39: 51358 | F39: 13076 | G39: 6625374 | H39: 6436822 | J39: ='ODOMETERS Halba'!$C39+'ODOMETERS Halba'!$D39-D38-C38 -> 436 | K39: ='ODOMETERS Halba'!$E39+'ODOMETERS Halba'!$F39-F38-E38 -> 949 | L39: ='ODOMETERS Halba'!$G39+'ODOMETERS Halba'!$H39-H38-G38 -> 1482 | M39: ='ODOMETERS Halba'!$J39+'ODOMETERS Halba'!$K39+'ODOMETERS Halba'!$L39 -> 2867
A40: 45994 | B40: Post Price | C40: 68589 | D40: 26914 | E40: 51889 | F40: 13283 | G40: 6625820 | H40: 6437106 | J40: ='ODOMETERS Halba'!$C40+'ODOMETERS Halba'!$D40-D39-C39 -> 529 | K40: ='ODOMETERS Halba'!$E40+'ODOMETERS Halba'!$F40-F39-E39 -> 738 | L40: ='ODOMETERS Halba'!$G40+'ODOMETERS Halba'!$H40-H39-G39 -> 730 | M40: ='ODOMETERS Halba'!$J40+'ODOMETERS Halba'!$K40+'ODOMETERS Halba'!$L40 -> 1997
A41: 45995 | C41: 69658 | D41: 27293 | E41: 53072 | F41: 13587 | G41: 6626018 | H41: 6438272 | J41: ='ODOMETERS Halba'!$C41+'ODOMETERS Halba'!$D41-D40-C40 -> 1448 | K41: ='ODOMETERS Halba'!$E41+'ODOMETERS Halba'!$F41-F40-E40 -> 1487 | L41: ='ODOMETERS Halba'!$G41+'ODOMETERS Halba'!$H41-H40-G40 -> 1364 | M41: ='ODOMETERS Halba'!$J41+'ODOMETERS Halba'!$K41+'ODOMETERS Halba'!$L41 -> 4299
A42: 45996 | B42: Pre Price | C42: 70042 | D42: 27470 | E42: 53448 | F42: 13704 | G42: 6626238 | H42: 6438311 | J42: ='ODOMETERS Halba'!$C42+'ODOMETERS Halba'!$D42-D41-C41 -> 561 | K42: ='ODOMETERS Halba'!$E42+'ODOMETERS Halba'!$F42-F41-E41 -> 493 | L42: ='ODOMETERS Halba'!$G42+'ODOMETERS Halba'!$H42-H41-G41 -> 259 | M42: ='ODOMETERS Halba'!$J42+'ODOMETERS Halba'!$K42+'ODOMETERS Halba'!$L42 -> 1313
A43: 45996 | B43: Post Price | C43: 70791 | D43: 27800 | E43: 53797 | F43: 13791 | G43: 6626732 | H43: 6439425 | J43: ='ODOMETERS Halba'!$C43+'ODOMETERS Halba'!$D43-D42-C42 -> 1079 | K43: ='ODOMETERS Halba'!$E43+'ODOMETERS Halba'!$F43-F42-E42 -> 436 | L43: ='ODOMETERS Halba'!$G43+'ODOMETERS Halba'!$H43-H42-G42 -> 1608 | M43: ='ODOMETERS Halba'!$J43+'ODOMETERS Halba'!$K43+'ODOMETERS Halba'!$L43 -> 3123
A44: 45997 | C44: 71819 | D44: 28268 | E44: 54891 | F44: 13926 | G44: 6627094 | H44: 6439492 | J44: ='ODOMETERS Halba'!$C44+'ODOMETERS Halba'!$D44-D43-C43 -> 1496 | K44: ='ODOMETERS Halba'!$E44+'ODOMETERS Halba'!$F44-F43-E43 -> 1229 | L44: ='ODOMETERS Halba'!$G44+'ODOMETERS Halba'!$H44-H43-G43 -> 429 | M44: ='ODOMETERS Halba'!$J44+'ODOMETERS Halba'!$K44+'ODOMETERS Halba'!$L44 -> 3154
A45: 45998 | C45: 72847 | D45: 28783 | E45: 55877 | F45: 14096 | G45: 6627995 | H45: 6441435 | J45: ='ODOMETERS Halba'!$C45+'ODOMETERS Halba'!$D45-D44-C44 -> 1543 | K45: ='ODOMETERS Halba'!$E45+'ODOMETERS Halba'!$F45-F44-E44 -> 1156 | L45: ='ODOMETERS Halba'!$G45+'ODOMETERS Halba'!$H45-H44-G44 -> 2844 | M45: ='ODOMETERS Halba'!$J45+'ODOMETERS Halba'!$K45+'ODOMETERS Halba'!$L45 -> 5543
A46: 45999 | C46: 73721 | D46: 29151 | E46: 56445 | F46: 14282 | G46: 6628141 | H46: 6441532 | J46: ='ODOMETERS Halba'!$C46+'ODOMETERS Halba'!$D46-D45-C45 -> 1242 | K46: ='ODOMETERS Halba'!$E46+'ODOMETERS Halba'!$F46-F45-E45 -> 754 | L46: ='ODOMETERS Halba'!$G46+'ODOMETERS Halba'!$H46-H45-G45 -> 243 | M46: ='ODOMETERS Halba'!$J46+'ODOMETERS Halba'!$K46+'ODOMETERS Halba'!$L46 -> 2239
A47: 46000 | B47: Pre Price | C47: 74233 | D47: 29406 | E47: 56819 | F47: 14303 | G47: 6628141 | H47: 6441666 | J47: ='ODOMETERS Halba'!$C47+'ODOMETERS Halba'!$D47-D46-C46 -> 767 | K47: ='ODOMETERS Halba'!$E47+'ODOMETERS Halba'!$F47-F46-E46 -> 395 | L47: ='ODOMETERS Halba'!$G47+'ODOMETERS Halba'!$H47-H46-G46 -> 134 | M47: ='ODOMETERS Halba'!$J47+'ODOMETERS Halba'!$K47+'ODOMETERS Halba'!$L47 -> 1296
A48: 46000 | B48: Post Price | C48: 74941 | D48: 29565 | E48: 57253 | F48: 14454 | G48: 6628304 | H48: 6441752 | J48: ='ODOMETERS Halba'!$C48+'ODOMETERS Halba'!$D48-D47-C47 -> 867 | K48: ='ODOMETERS Halba'!$E48+'ODOMETERS Halba'!$F48-F47-E47 -> 585 | L48: ='ODOMETERS Halba'!$G48+'ODOMETERS Halba'!$H48-H47-G47 -> 249 | M48: ='ODOMETERS Halba'!$J48+'ODOMETERS Halba'!$K48+'ODOMETERS Halba'!$L48 -> 1701
A49: 46001 | C49: 76130 | D49: 29979 | E49: 58425 | F49: 15167 | G49: 6628874 | H49: 6443205 | J49: ='ODOMETERS Halba'!$C49+'ODOMETERS Halba'!$D49-D48-C48 -> 1603 | K49: ='ODOMETERS Halba'!$E49+'ODOMETERS Halba'!$F49-F48-E48 -> 1885 | L49: ='ODOMETERS Halba'!$G49+'ODOMETERS Halba'!$H49-H48-G48 -> 2023 | M49: ='ODOMETERS Halba'!$J49+'ODOMETERS Halba'!$K49+'ODOMETERS Halba'!$L49 -> 5511
A50: 46002 | C50: 77296 | D50: 30343 | E50: 59033 | F50: 15314 | G50: 6629149 | H50: 6443754 | J50: ='ODOMETERS Halba'!$C50+'ODOMETERS Halba'!$D50-D49-C49 -> 1530 | K50: ='ODOMETERS Halba'!$E50+'ODOMETERS Halba'!$F50-F49-E49 -> 755 | L50: ='ODOMETERS Halba'!$G50+'ODOMETERS Halba'!$H50-H49-G49 -> 824 | M50: ='ODOMETERS Halba'!$J50+'ODOMETERS Halba'!$K50+'ODOMETERS Halba'!$L50 -> 3109
A51: 46003 | B51: Pre Price | C51: 77751 | D51: 30567 | E51: 59315 | F51: 15388 | G51: 6629245 | H51: 6443857 | J51: ='ODOMETERS Halba'!$C51+'ODOMETERS Halba'!$D51-D50-C50 -> 679 | K51: ='ODOMETERS Halba'!$E51+'ODOMETERS Halba'!$F51-F50-E50 -> 356 | L51: ='ODOMETERS Halba'!$G51+'ODOMETERS Halba'!$H51-H50-G50 -> 199 | M51: ='ODOMETERS Halba'!$J51+'ODOMETERS Halba'!$K51+'ODOMETERS Halba'!$L51 -> 1234
A52: 46003 | B52: Post Price | C52: 79078 | D52: 31554 | E52: 59758 | F52: 15518 | G52: 6629372 | H52: 6443917 | J52: ='ODOMETERS Halba'!$C52+'ODOMETERS Halba'!$D52-D51-C51 -> 2314 | K52: ='ODOMETERS Halba'!$E52+'ODOMETERS Halba'!$F52-F51-E51 -> 573 | L52: ='ODOMETERS Halba'!$G52+'ODOMETERS Halba'!$H52-H51-G51 -> 187 | M52: ='ODOMETERS Halba'!$J52+'ODOMETERS Halba'!$K52+'ODOMETERS Halba'!$L52 -> 3074
A53: 46004 | C53: 80410 | D53: 31944 | E53: 60598 | F53: 15761 | G53: 6629675 | H53: 6445059 | J53: ='ODOMETERS Halba'!$C53+'ODOMETERS Halba'!$D53-D52-C52 -> 1722 | K53: ='ODOMETERS Halba'!$E53+'ODOMETERS Halba'!$F53-F52-E52 -> 1083 | L53: ='ODOMETERS Halba'!$G53+'ODOMETERS Halba'!$H53-H52-G52 -> 1445 | M53: ='ODOMETERS Halba'!$J53+'ODOMETERS Halba'!$K53+'ODOMETERS Halba'!$L53 -> 4250
A54: 46005 | C54: 81470 | D54: 32304 | E54: 61983 | F54: 15944 | G54: 6629899 | H54: 6445492 | J54: ='ODOMETERS Halba'!$C54+'ODOMETERS Halba'!$D54-D53-C53 -> 1420 | K54: ='ODOMETERS Halba'!$E54+'ODOMETERS Halba'!$F54-F53-E53 -> 1568 | L54: ='ODOMETERS Halba'!$G54+'ODOMETERS Halba'!$H54-H53-G53 -> 657 | M54: ='ODOMETERS Halba'!$J54+'ODOMETERS Halba'!$K54+'ODOMETERS Halba'!$L54 -> 3645
A55: 46006 | C55: 82050 | D55: 32593 | E55: 63585 | F55: 16343 | G55: 6630875 | H55: 6445678 | J55: ='ODOMETERS Halba'!$C55+'ODOMETERS Halba'!$D55-D54-C54 -> 869 | K55: ='ODOMETERS Halba'!$E55+'ODOMETERS Halba'!$F55-F54-E54 -> 2001 | L55: ='ODOMETERS Halba'!$G55+'ODOMETERS Halba'!$H55-H54-G54 -> 1162 | M55: ='ODOMETERS Halba'!$J55+'ODOMETERS Halba'!$K55+'ODOMETERS Halba'!$L55 -> 4032
A56: 46007 | B56: Pre Price | C56: 82289 | D56: 32758 | E56: 64040 | F56: 16436 | G56: 6633961 | H56: 6445775 | J56: ='ODOMETERS Halba'!$C56+'ODOMETERS Halba'!$D56-D55-C55 -> 404 | K56: ='ODOMETERS Halba'!$E56+'ODOMETERS Halba'!$F56-F55-E55 -> 548 | L56: ='ODOMETERS Halba'!$G56+'ODOMETERS Halba'!$H56-H55-G55 -> 3183 | M56: ='ODOMETERS Halba'!$J56+'ODOMETERS Halba'!$K56+'ODOMETERS Halba'!$L56 -> 4135
A57: 46007 | B57: Post Price | C57: 82683 | D57: 32915 | E57: 64722 | F57: 16508 | G57: 6634439 | H57: 6445955 | J57: ='ODOMETERS Halba'!$C57+'ODOMETERS Halba'!$D57-D56-C56 -> 551 | K57: ='ODOMETERS Halba'!$E57+'ODOMETERS Halba'!$F57-F56-E56 -> 754 | L57: ='ODOMETERS Halba'!$G57+'ODOMETERS Halba'!$H57-H56-G56 -> 658 | M57: ='ODOMETERS Halba'!$J57+'ODOMETERS Halba'!$K57+'ODOMETERS Halba'!$L57 -> 1963
A58: 46008 | C58: 83693 | D58: 33178 | E58: 66250 | F58: 17256 | G58: 6634792 | H58: 6446188 | J58: ='ODOMETERS Halba'!$C58+'ODOMETERS Halba'!$D58-D57-C57 -> 1273 | K58: ='ODOMETERS Halba'!$E58+'ODOMETERS Halba'!$F58-F57-E57 -> 2276 | L58: ='ODOMETERS Halba'!$G58+'ODOMETERS Halba'!$H58-H57-G57 -> 586 | M58: ='ODOMETERS Halba'!$J58+'ODOMETERS Halba'!$K58+'ODOMETERS Halba'!$L58 -> 4135
A59: 46009 | C59: 84643 | D59: 33636 | E59: 67027 | F59: 17538 | G59: 6634922 | H59: 6446385 | J59: ='ODOMETERS Halba'!$C59+'ODOMETERS Halba'!$D59-D58-C58 -> 1408 | K59: ='ODOMETERS Halba'!$E59+'ODOMETERS Halba'!$F59-F58-E58 -> 1059 | L59: ='ODOMETERS Halba'!$G59+'ODOMETERS Halba'!$H59-H58-G58 -> 327 | M59: ='ODOMETERS Halba'!$J59+'ODOMETERS Halba'!$K59+'ODOMETERS Halba'!$L59 -> 2794
A60: 46010 | B60: Pre Price | C60: 85584 | D60: 33877 | E60: 67167 | F60: 17609 | G60: 6634950 | H60: 6446509 | J60: ='ODOMETERS Halba'!$C60+'ODOMETERS Halba'!$D60-D59-C59 -> 1182 | K60: ='ODOMETERS Halba'!$E60+'ODOMETERS Halba'!$F60-F59-E59 -> 211 | L60: ='ODOMETERS Halba'!$G60+'ODOMETERS Halba'!$H60-H59-G59 -> 152 | M60: ='ODOMETERS Halba'!$J60+'ODOMETERS Halba'!$K60+'ODOMETERS Halba'!$L60 -> 1545
A61: 46010 | B61: Post Price | C61: 86479 | D61: 34050 | E61: 67339 | F61: 17665 | G61: 6635157 | H61: 6446937 | J61: ='ODOMETERS Halba'!$C61+'ODOMETERS Halba'!$D61-D60-C60 -> 1068 | K61: ='ODOMETERS Halba'!$E61+'ODOMETERS Halba'!$F61-F60-E60 -> 228 | L61: ='ODOMETERS Halba'!$G61+'ODOMETERS Halba'!$H61-H60-G60 -> 635 | M61: ='ODOMETERS Halba'!$J61+'ODOMETERS Halba'!$K61+'ODOMETERS Halba'!$L61 -> 1931
A62: 46011 | C62: 88151 | D62: 34536 | E62: 68211 | F62: 17838 | G62: 6637740 | H62: 6447310 | J62: ='ODOMETERS Halba'!$C62+'ODOMETERS Halba'!$D62-D61-C61 -> 2158 | K62: ='ODOMETERS Halba'!$E62+'ODOMETERS Halba'!$F62-F61-E61 -> 1045 | L62: ='ODOMETERS Halba'!$G62+'ODOMETERS Halba'!$H62-H61-G61 -> 2956 | M62: ='ODOMETERS Halba'!$J62+'ODOMETERS Halba'!$K62+'ODOMETERS Halba'!$L62 -> 6159
A63: 46012 | C63: 88778 | D63: 34784 | E63: 69995 | F63: 18220 | G63: 6637837 | H63: 6447511 | J63: ='ODOMETERS Halba'!$C63+'ODOMETERS Halba'!$D63-D62-C62 -> 875 | K63: ='ODOMETERS Halba'!$E63+'ODOMETERS Halba'!$F63-F62-E62 -> 2166 | L63: ='ODOMETERS Halba'!$G63+'ODOMETERS Halba'!$H63-H62-G62 -> 298 | M63: ='ODOMETERS Halba'!$J63+'ODOMETERS Halba'!$K63+'ODOMETERS Halba'!$L63 -> 3339
A64: 46013 | C64: 90722 | D64: 35211 | E64: 70756 | F64: 18360 | G64: 6639704 | H64: 6448748 | J64: ='ODOMETERS Halba'!$C64+'ODOMETERS Halba'!$D64-D63-C63 -> 2371 | K64: ='ODOMETERS Halba'!$E64+'ODOMETERS Halba'!$F64-F63-E63 -> 901 | L64: ='ODOMETERS Halba'!$G64+'ODOMETERS Halba'!$H64-H63-G63 -> 3104 | M64: ='ODOMETERS Halba'!$J64+'ODOMETERS Halba'!$K64+'ODOMETERS Halba'!$L64 -> 6376
A65: 46014 | B65: Pre Price | C65: 91797 | D65: 35581 | E65: 70792 | F65: 18385 | G65: 6639847 | H65: 6448920 | J65: ='ODOMETERS Halba'!$C65+'ODOMETERS Halba'!$D65-D64-C64 -> 1445 | K65: ='ODOMETERS Halba'!$E65+'ODOMETERS Halba'!$F65-F64-E64 -> 61 | L65: ='ODOMETERS Halba'!$G65+'ODOMETERS Halba'!$H65-H64-G64 -> 315 | M65: ='ODOMETERS Halba'!$J65+'ODOMETERS Halba'!$K65+'ODOMETERS Halba'!$L65 -> 1821
A66: 46014 | B66: Post Price | C66: 92224 | D66: 35711 | E66: 71632 | F66: 18510 | G66: 6640598 | H66: 6449172 | J66: ='ODOMETERS Halba'!$C66+'ODOMETERS Halba'!$D66-D65-C65 -> 557 | K66: ='ODOMETERS Halba'!$E66+'ODOMETERS Halba'!$F66-F65-E65 -> 965 | L66: ='ODOMETERS Halba'!$G66+'ODOMETERS Halba'!$H66-H65-G65 -> 1003 | M66: ='ODOMETERS Halba'!$J66+'ODOMETERS Halba'!$K66+'ODOMETERS Halba'!$L66 -> 2525
A67: 46015 | C67: 92880 | D67: 35923 | E67: 73856 | F67: 18833 | G67: 6640941 | H67: 6449956 | J67: ='ODOMETERS Halba'!$C67+'ODOMETERS Halba'!$D67-D66-C66 -> 868 | K67: ='ODOMETERS Halba'!$E67+'ODOMETERS Halba'!$F67-F66-E66 -> 2547 | L67: ='ODOMETERS Halba'!$G67+'ODOMETERS Halba'!$H67-H66-G66 -> 1127 | M67: ='ODOMETERS Halba'!$J67+'ODOMETERS Halba'!$K67+'ODOMETERS Halba'!$L67 -> 4542
A68: 46016 | C68: 95033 | D68: 36598 | E68: 74183 | F68: 18885 | G68: 6641080 | H68: 6450072 | J68: ='ODOMETERS Halba'!$C68+'ODOMETERS Halba'!$D68-D67-C67 -> 2828 | K68: ='ODOMETERS Halba'!$E68+'ODOMETERS Halba'!$F68-F67-E67 -> 379 | L68: ='ODOMETERS Halba'!$G68+'ODOMETERS Halba'!$H68-H67-G67 -> 255 | M68: ='ODOMETERS Halba'!$J68+'ODOMETERS Halba'!$K68+'ODOMETERS Halba'!$L68 -> 3462
A69: 46017 | B69: Pre Price | C69: 96317 | D69: 37079 | E69: 74183 | F69: 18911 | G69: 6641262 | H69: 6450415 | J69: ='ODOMETERS Halba'!$C69+'ODOMETERS Halba'!$D69-D68-C68 -> 1765 | K69: ='ODOMETERS Halba'!$E69+'ODOMETERS Halba'!$F69-F68-E68 -> 26 | L69: ='ODOMETERS Halba'!$G69+'ODOMETERS Halba'!$H69-H68-G68 -> 525 | M69: ='ODOMETERS Halba'!$J69+'ODOMETERS Halba'!$K69+'ODOMETERS Halba'!$L69 -> 2316
A70: 46017 | B70: Post Price | C70: 97084 | D70: 37265 | E70: 74468 | F70: 18941 | G70: 6642713 | H70: 6450721 | J70: ='ODOMETERS Halba'!$C70+'ODOMETERS Halba'!$D70-D69-C69 -> 953 | K70: ='ODOMETERS Halba'!$E70+'ODOMETERS Halba'!$F70-F69-E69 -> 315 | L70: ='ODOMETERS Halba'!$G70+'ODOMETERS Halba'!$H70-H69-G69 -> 1757 | M70: ='ODOMETERS Halba'!$J70+'ODOMETERS Halba'!$K70+'ODOMETERS Halba'!$L70 -> 3025
A71: 46018 | C71: 98266 | D71: 37623 | E71: 75058 | F71: 19123 | G71: 6643552 | H71: 6450976 | J71: ='ODOMETERS Halba'!$C71+'ODOMETERS Halba'!$D71-D70-C70 -> 1540 | K71: ='ODOMETERS Halba'!$E71+'ODOMETERS Halba'!$F71-F70-E70 -> 772 | L71: ='ODOMETERS Halba'!$G71+'ODOMETERS Halba'!$H71-H70-G70 -> 1094 | M71: ='ODOMETERS Halba'!$J71+'ODOMETERS Halba'!$K71+'ODOMETERS Halba'!$L71 -> 3406
A72: 46019 | C72: 100122 | D72: 38001 | E72: 75670 | F72: 19300 | G72: 6643770 | H72: 6451346 | J72: ='ODOMETERS Halba'!$C72+'ODOMETERS Halba'!$D72-D71-C71 -> 2234 | K72: ='ODOMETERS Halba'!$E72+'ODOMETERS Halba'!$F72-F71-E71 -> 789 | L72: ='ODOMETERS Halba'!$G72+'ODOMETERS Halba'!$H72-H71-G71 -> 588 | M72: ='ODOMETERS Halba'!$J72+'ODOMETERS Halba'!$K72+'ODOMETERS Halba'!$L72 -> 3611
A73: 46020 | C73: 101047 | D73: 38359 | E73: 77254 | F73: 19693 | G73: 6644123 | H73: 6451512 | J73: ='ODOMETERS Halba'!$C73+'ODOMETERS Halba'!$D73-D72-C72 -> 1283 | K73: ='ODOMETERS Halba'!$E73+'ODOMETERS Halba'!$F73-F72-E72 -> 1977 | L73: ='ODOMETERS Halba'!$G73+'ODOMETERS Halba'!$H73-H72-G72 -> 519 | M73: ='ODOMETERS Halba'!$J73+'ODOMETERS Halba'!$K73+'ODOMETERS Halba'!$L73 -> 3779
A74: 46021 | B74: Pre Price | C74: 101561 | D74: 38587 | E74: 77741 | F74: 19837 | G74: 6644163 | H74: 6451625 | J74: ='ODOMETERS Halba'!$C74+'ODOMETERS Halba'!$D74-D73-C73 -> 742 | K74: ='ODOMETERS Halba'!$E74+'ODOMETERS Halba'!$F74-F73-E73 -> 631 | L74: ='ODOMETERS Halba'!$G74+'ODOMETERS Halba'!$H74-H73-G73 -> 153 | M74: ='ODOMETERS Halba'!$J74+'ODOMETERS Halba'!$K74+'ODOMETERS Halba'!$L74 -> 1526
A75: 46021 | B75: Post Price | C75: 102206 | D75: 38692 | E75: 78564 | F75: 20028 | G75: 6645660 | H75: 6452677 | J75: ='ODOMETERS Halba'!$C75+'ODOMETERS Halba'!$D75-D74-C74 -> 750 | K75: ='ODOMETERS Halba'!$E75+'ODOMETERS Halba'!$F75-F74-E74 -> 1014 | L75: ='ODOMETERS Halba'!$G75+'ODOMETERS Halba'!$H75-H74-G74 -> 2549 | M75: ='ODOMETERS Halba'!$J75+'ODOMETERS Halba'!$K75+'ODOMETERS Halba'!$L75 -> 4313
A76: 46022 | C76: 103322 | D76: 39064 | E76: 79651 | F76: 20279 | G76: 6647349 | H76: 6452919 | J76: ='ODOMETERS Halba'!$C76+'ODOMETERS Halba'!$D76-D75-C75 -> 1488 | K76: ='ODOMETERS Halba'!$E76+'ODOMETERS Halba'!$F76-F75-E75 -> 1338 | L76: ='ODOMETERS Halba'!$G76+'ODOMETERS Halba'!$H76-H75-G75 -> 1931 | M76: ='ODOMETERS Halba'!$J76+'ODOMETERS Halba'!$K76+'ODOMETERS Halba'!$L76 -> 4757
A77: 46023 | C77: 104523 | D77: 39470 | E77: 80228 | F77: 20359 | G77: 6649802 | H77: 6453182 | J77: ='ODOMETERS Halba'!$C77+'ODOMETERS Halba'!$D77-D76-C76 -> 1607 | K77: ='ODOMETERS Halba'!$E77+'ODOMETERS Halba'!$F77-F76-E76 -> 657 | L77: ='ODOMETERS Halba'!$G77+'ODOMETERS Halba'!$H77-H76-G76 -> 2716 | M77: ='ODOMETERS Halba'!$J77+'ODOMETERS Halba'!$K77+'ODOMETERS Halba'!$L77 -> 4980
A78: 46024 | C78: 106293 | D78: 40117 | E78: 80321 | F78: 20409 | G78: 6651013 | H78: 6453402 | J78: ='ODOMETERS Halba'!$C78+'ODOMETERS Halba'!$D78-D77-C77 -> 2417 | K78: ='ODOMETERS Halba'!$E78+'ODOMETERS Halba'!$F78-F77-E77 -> 143 | L78: ='ODOMETERS Halba'!$G78+'ODOMETERS Halba'!$H78-H77-G77 -> 1431 | M78: ='ODOMETERS Halba'!$J78+'ODOMETERS Halba'!$K78+'ODOMETERS Halba'!$L78 -> 3991
A79: 46025 | B79: Pre Price | C79: 106983 | D79: 40316 | E79: 80620 | F79: 20419 | G79: 6651077 | H79: 6453489 | J79: ='ODOMETERS Halba'!$C79+'ODOMETERS Halba'!$D79-D78-C78 -> 889 | K79: ='ODOMETERS Halba'!$E79+'ODOMETERS Halba'!$F79-F78-E78 -> 309 | L79: ='ODOMETERS Halba'!$G79+'ODOMETERS Halba'!$H79-H78-G78 -> 151 | M79: ='ODOMETERS Halba'!$J79+'ODOMETERS Halba'!$K79+'ODOMETERS Halba'!$L79 -> 1349
A80: 46025 | B80: Post Price | C80: 107860 | D80: 40614 | E80: 81244 | F80: 20574 | G80: 6651611 | H80: 6453567 | J80: ='ODOMETERS Halba'!$C80+'ODOMETERS Halba'!$D80-D79-C79 -> 1175 | K80: ='ODOMETERS Halba'!$E80+'ODOMETERS Halba'!$F80-F79-E79 -> 779 | L80: ='ODOMETERS Halba'!$G80+'ODOMETERS Halba'!$H80-H79-G79 -> 612 | M80: ='ODOMETERS Halba'!$J80+'ODOMETERS Halba'!$K80+'ODOMETERS Halba'!$L80 -> 2566
A81: 46026 | C81: 109747 | D81: 41094 | E81: 82244 | F81: 20740 | G81: 6651760 | H81: 6453969 | J81: ='ODOMETERS Halba'!$C81+'ODOMETERS Halba'!$D81-D80-C80 -> 2367 | K81: ='ODOMETERS Halba'!$E81+'ODOMETERS Halba'!$F81-F80-E80 -> 1166 | L81: ='ODOMETERS Halba'!$G81+'ODOMETERS Halba'!$H81-H80-G80 -> 551 | M81: ='ODOMETERS Halba'!$J81+'ODOMETERS Halba'!$K81+'ODOMETERS Halba'!$L81 -> 4084
A82: 46027 | C82: 110481 | D82: 41404 | E82: 83893 | F82: 21159 | G82: 6652765 | H82: 6454640 | J82: ='ODOMETERS Halba'!$C82+'ODOMETERS Halba'!$D82-D81-C81 -> 1044 | K82: ='ODOMETERS Halba'!$E82+'ODOMETERS Halba'!$F82-F81-E81 -> 2068 | L82: ='ODOMETERS Halba'!$G82+'ODOMETERS Halba'!$H82-H81-G81 -> 1676 | M82: ='ODOMETERS Halba'!$J82+'ODOMETERS Halba'!$K82+'ODOMETERS Halba'!$L82 -> 4788
A83: 46028 | C83: 111713 | D83: 41865 | E83: 84563 | F83: 21420 | G83: 6654043 | H83: 6454989 | J83: ='ODOMETERS Halba'!$C83+'ODOMETERS Halba'!$D83-D82-C82 -> 1693 | K83: ='ODOMETERS Halba'!$E83+'ODOMETERS Halba'!$F83-F82-E82 -> 931 | L83: ='ODOMETERS Halba'!$G83+'ODOMETERS Halba'!$H83-H82-G82 -> 1627 | M83: ='ODOMETERS Halba'!$J83+'ODOMETERS Halba'!$K83+'ODOMETERS Halba'!$L83 -> 4251
A84: 46029 | B84: Pre Price | C84: 112345 | D84: 42262 | E84: 85067 | F84: 21686 | G84: 6655814 | H84: 6455231 | J84: ='ODOMETERS Halba'!$C84+'ODOMETERS Halba'!$D84-D83-C83 -> 1029 | K84: ='ODOMETERS Halba'!$E84+'ODOMETERS Halba'!$F84-F83-E83 -> 770 | L84: ='ODOMETERS Halba'!$G84+'ODOMETERS Halba'!$H84-H83-G83 -> 2013 | M84: ='ODOMETERS Halba'!$J84+'ODOMETERS Halba'!$K84+'ODOMETERS Halba'!$L84 -> 3812
A85: 46029 | B85: Post Price | C85: 112807 | D85: 42426 | E85: 85368 | F85: 21733 | G85: 6655880 | H85: 6455320 | J85: ='ODOMETERS Halba'!$C85+'ODOMETERS Halba'!$D85-D84-C84 -> 626 | K85: ='ODOMETERS Halba'!$E85+'ODOMETERS Halba'!$F85-F84-E84 -> 348 | L85: ='ODOMETERS Halba'!$G85+'ODOMETERS Halba'!$H85-H84-G84 -> 155 | M85: ='ODOMETERS Halba'!$J85+'ODOMETERS Halba'!$K85+'ODOMETERS Halba'!$L85 -> 1129
A86: 46030 | C86: 113939 | D86: 42936 | E86: 86253 | F86: 21943 | G86: 6658314 | H86: 6455646 | J86: ='ODOMETERS Halba'!$C86+'ODOMETERS Halba'!$D86-D85-C85 -> 1642 | K86: ='ODOMETERS Halba'!$E86+'ODOMETERS Halba'!$F86-F85-E85 -> 1095 | L86: ='ODOMETERS Halba'!$G86+'ODOMETERS Halba'!$H86-H85-G85 -> 2760 | M86: ='ODOMETERS Halba'!$J86+'ODOMETERS Halba'!$K86+'ODOMETERS Halba'!$L86 -> 5497
A87: 46031 | B87: Pre Price | C87: 114645 | D87: 43238 | E87: 86889 | F87: 22013 | G87: 6658578 | H87: 6455752 | J87: ='ODOMETERS Halba'!$C87+'ODOMETERS Halba'!$D87-D86-C86 -> 1008 | K87: ='ODOMETERS Halba'!$E87+'ODOMETERS Halba'!$F87-F86-E86 -> 706 | L87: ='ODOMETERS Halba'!$G87+'ODOMETERS Halba'!$H87-H86-G86 -> 370 | M87: ='ODOMETERS Halba'!$J87+'ODOMETERS Halba'!$K87+'ODOMETERS Halba'!$L87 -> 2084
A88: 46031 | B88: Post Price | C88: 115125 | D88: 43479 | E88: 87267 | F88: 22097 | G88: 6658858 | H88: 6455927 | J88: ='ODOMETERS Halba'!$C88+'ODOMETERS Halba'!$D88-D87-C87 -> 721 | K88: ='ODOMETERS Halba'!$E88+'ODOMETERS Halba'!$F88-F87-E87 -> 462 | L88: ='ODOMETERS Halba'!$G88+'ODOMETERS Halba'!$H88-H87-G87 -> 455 | M88: ='ODOMETERS Halba'!$J88+'ODOMETERS Halba'!$K88+'ODOMETERS Halba'!$L88 -> 1638
A89: 46032 | C89: 117065 | D89: 44216 | E89: 87708 | F89: 22180 | G89: 6660079 | H89: 6456164 | J89: ='ODOMETERS Halba'!$C89+'ODOMETERS Halba'!$D89-D88-C88 -> 2677 | K89: ='ODOMETERS Halba'!$E89+'ODOMETERS Halba'!$F89-F88-E88 -> 524 | L89: ='ODOMETERS Halba'!$G89+'ODOMETERS Halba'!$H89-H88-G88 -> 1458 | M89: ='ODOMETERS Halba'!$J89+'ODOMETERS Halba'!$K89+'ODOMETERS Halba'!$L89 -> 4659
A90: 46033 | C90: 118485 | D90: 44756 | E90: 88402 | F90: 22411 | G90: 6660518 | H90: 6457865 | J90: ='ODOMETERS Halba'!$C90+'ODOMETERS Halba'!$D90-D89-C89 -> 1960 | K90: ='ODOMETERS Halba'!$E90+'ODOMETERS Halba'!$F90-F89-E89 -> 925 | L90: ='ODOMETERS Halba'!$G90+'ODOMETERS Halba'!$H90-H89-G89 -> 2140 | M90: ='ODOMETERS Halba'!$J90+'ODOMETERS Halba'!$K90+'ODOMETERS Halba'!$L90 -> 5025
A91: 46034 | C91: 119289 | D91: 45199 | E91: 89960 | F91: 22645 | G91: 6660945 | H91: 6458134 | J91: ='ODOMETERS Halba'!$C91+'ODOMETERS Halba'!$D91-D90-C90 -> 1247 | K91: ='ODOMETERS Halba'!$E91+'ODOMETERS Halba'!$F91-F90-E90 -> 1792 | L91: ='ODOMETERS Halba'!$G91+'ODOMETERS Halba'!$H91-H90-G90 -> 696 | M91: ='ODOMETERS Halba'!$J91+'ODOMETERS Halba'!$K91+'ODOMETERS Halba'!$L91 -> 3735
A92: 46035 | B92: Pre Price | C92: 119879 | D92: 45370 | E92: 90290 | F92: 22765 | G92: 6662718 | H92: 6458285 | J92: ='ODOMETERS Halba'!$C92+'ODOMETERS Halba'!$D92-D91-C91 -> 761 | K92: ='ODOMETERS Halba'!$E92+'ODOMETERS Halba'!$F92-F91-E91 -> 450 | L92: ='ODOMETERS Halba'!$G92+'ODOMETERS Halba'!$H92-H91-G91 -> 1924 | M92: ='ODOMETERS Halba'!$J92+'ODOMETERS Halba'!$K92+'ODOMETERS Halba'!$L92 -> 3135
A93: 46035 | B93: Post Price | C93: 120246 | D93: 45502 | E93: 90860 | F93: 22809 | G93: 6662905 | H93: 6458606 | J93: ='ODOMETERS Halba'!$C93+'ODOMETERS Halba'!$D93-D92-C92 -> 499 | K93: ='ODOMETERS Halba'!$E93+'ODOMETERS Halba'!$F93-F92-E92 -> 614 | L93: ='ODOMETERS Halba'!$G93+'ODOMETERS Halba'!$H93-H92-G92 -> 508 | M93: ='ODOMETERS Halba'!$J93+'ODOMETERS Halba'!$K93+'ODOMETERS Halba'!$L93 -> 1621
A94: 46036 | C94: 121310 | D94: 46145 | E94: 91524 | F94: 22921 | G94: 6664756 | H94: 6461346 | J94: ='ODOMETERS Halba'!$C94+'ODOMETERS Halba'!$D94-D93-C93 -> 1707 | K94: ='ODOMETERS Halba'!$E94+'ODOMETERS Halba'!$F94-F93-E93 -> 776 | L94: ='ODOMETERS Halba'!$G94+'ODOMETERS Halba'!$H94-H93-G93 -> 4591 | M94: ='ODOMETERS Halba'!$J94+'ODOMETERS Halba'!$K94+'ODOMETERS Halba'!$L94 -> 7074
A95: 46037 | C95: 122347 | D95: 46797 | E95: 92456 | F95: 23142 | G95: 6666313 | H95: 6461821 | J95: ='ODOMETERS Halba'!$C95+'ODOMETERS Halba'!$D95-D94-C94 -> 1689 | K95: ='ODOMETERS Halba'!$E95+'ODOMETERS Halba'!$F95-F94-E94 -> 1153 | L95: ='ODOMETERS Halba'!$G95+'ODOMETERS Halba'!$H95-H94-G94 -> 2032 | M95: ='ODOMETERS Halba'!$J95+'ODOMETERS Halba'!$K95+'ODOMETERS Halba'!$L95 -> 4874
A96: 46038 | B96: Pre Price | C96: 123034 | D96: 47011 | E96: 92879 | F96: 23239 | G96: 6666571 | H96: 6461981 | J96: ='ODOMETERS Halba'!$C96+'ODOMETERS Halba'!$D96-D95-C95 -> 901 | K96: ='ODOMETERS Halba'!$E96+'ODOMETERS Halba'!$F96-F95-E95 -> 520 | L96: ='ODOMETERS Halba'!$G96+'ODOMETERS Halba'!$H96-H95-G95 -> 418 | M96: ='ODOMETERS Halba'!$J96+'ODOMETERS Halba'!$K96+'ODOMETERS Halba'!$L96 -> 1839
A97: 46038 | B97: Post Price | C97: 123575 | D97: 47209 | E97: 93498 | F97: 23302 | G97: 6667015 | H97: 6462078 | J97: ='ODOMETERS Halba'!$C97+'ODOMETERS Halba'!$D97-D96-C96 -> 739 | K97: ='ODOMETERS Halba'!$E97+'ODOMETERS Halba'!$F97-F96-E96 -> 682 | L97: ='ODOMETERS Halba'!$G97+'ODOMETERS Halba'!$H97-H96-G96 -> 541 | M97: ='ODOMETERS Halba'!$J97+'ODOMETERS Halba'!$K97+'ODOMETERS Halba'!$L97 -> 1962
A98: 46039 | C98: 123863 | D98: 47437 | E98: 95587 | F98: 24223 | G98: 6667512 | H98: 6462292 | J98: ='ODOMETERS Halba'!$C98+'ODOMETERS Halba'!$D98-D97-C97 -> 516 | K98: ='ODOMETERS Halba'!$E98+'ODOMETERS Halba'!$F98-F97-E97 -> 3010 | L98: ='ODOMETERS Halba'!$G98+'ODOMETERS Halba'!$H98-H97-G97 -> 711 | M98: ='ODOMETERS Halba'!$J98+'ODOMETERS Halba'!$K98+'ODOMETERS Halba'!$L98 -> 4237
A99: 46040 | C99: 125225 | D99: 48040 | E99: 96667 | F99: 24514 | G99: 6668817 | H99: 6462441 | J99: ='ODOMETERS Halba'!$C99+'ODOMETERS Halba'!$D99-D98-C98 -> 1965 | K99: ='ODOMETERS Halba'!$E99+'ODOMETERS Halba'!$F99-F98-E98 -> 1371 | L99: ='ODOMETERS Halba'!$G99+'ODOMETERS Halba'!$H99-H98-G98 -> 1454 | M99: ='ODOMETERS Halba'!$J99+'ODOMETERS Halba'!$K99+'ODOMETERS Halba'!$L99 -> 4790
A100: 46041 | C100: 126540 | D100: 48673 | E100: 97575 | F100: 24737 | G100: 6671378 | H100: 6462865 | J100: ='ODOMETERS Halba'!$C100+'ODOMETERS Halba'!$D100-D99-C99 -> 1948 | K100: ='ODOMETERS Halba'!$E100+'ODOMETERS Halba'!$F100-F99-E99 -> 1131 | L100: ='ODOMETERS Halba'!$G100+'ODOMETERS Halba'!$H100-H99-G99 -> 2985 | M100: ='ODOMETERS Halba'!$J100+'ODOMETERS Halba'!$K100+'ODOMETERS Halba'!$L100 -> 6064
...

Sheet Oil Stock Halba
A4: Item | B4: Price | C4: 9-Feb | D4: 11-Feb | E4: 17-Feb | F4: 20-Feb | G4: 25-Feb | H4: 7-Mar | I4: 23-Mar | J4: 6-Apr | K4: 14-Apr | L4: 28-Jun | M4: Restock | N4: Sold | O4: Value
A5: Shmol 10w-40 | B5: 6.5 | C5: 19 | D5: 18 | E5: 18 | F5: 17 | G5: 16 | H5: 13 | I5: 5 | J5: 3 | K5: 1 | L5: 1 | N5: =Table1[[#This Row],[14-Apr]]-Table1[[#This Row],[28-Jun]]+Table1[[#This Row],[Restock]] -> 0 | O5: =Table1[[#This Row],[Sold]]*Table1[[#This Row],[Price]] -> 0
A6: Shmol 5w-30 | B6: 9 | C6: 13 | D6: 13 | E6: 13 | F6: 13 | G6: 13 | H6: 13 | I6: 13 | J6: 12 | K6: 12 | L6: 12 | N6: =Table1[[#This Row],[14-Apr]]-Table1[[#This Row],[28-Jun]]+Table1[[#This Row],[Restock]] -> 0 | O6: =Table1[[#This Row],[Sold]]*Table1[[#This Row],[Price]] -> 0
A7: Shmol 20w-50 | B7: 8 | C7: 13 | D7: 13 | E7: 13 | F7: 13 | G7: 13 | H7: 12 | I7: 12 | J7: 12 | K7: 12 | L7: 12 | N7: =Table1[[#This Row],[14-Apr]]-Table1[[#This Row],[28-Jun]]+Table1[[#This Row],[Restock]] -> 0 | O7: =Table1[[#This Row],[Sold]]*Table1[[#This Row],[Price]] -> 0
A8: Shmol ATF | B8: 9 | C8: 37 | D8: 37 | E8: 37 | F8: 35 | G8: 35 | H8: =35-6 -> 29 | I8: 31 | J8: 31 | K8: 31 | L8: 31 | N8: =Table1[[#This Row],[14-Apr]]-Table1[[#This Row],[28-Jun]]+Table1[[#This Row],[Restock]] -> 0 | O8: =Table1[[#This Row],[Sold]]*Table1[[#This Row],[Price]] -> 0
N9: =Table1[[#This Row],[14-Apr]]-Table1[[#This Row],[28-Jun]]+Table1[[#This Row],[Restock]] -> 0 | O9: =Table1[[#This Row],[Sold]]*Table1[[#This Row],[Price]] -> 0
A10: Morse | B10: =250/89.7 -> 2.787068 | C10: 30 | D10: 58 | E10: 57 | F10: 57 | G10: 56 | H10: =50-12 -> 38 | I10: 32 | J10: 29 | K10: 26 | L10: 30 | M10: 30 | N10: =Table1[[#This Row],[14-Apr]]-Table1[[#This Row],[28-Jun]]+Table1[[#This Row],[Restock]] -> 26 | O10: =Table1[[#This Row],[Sold]]*Table1[[#This Row],[Price]] -> 72.463768
A11: dot 3 | B11: =150/89.7 -> 1.6722408 | C11: 55 | D11: 55 | E11: 55 | F11: 54 | G11: 54 | H11: =53-12 -> 41 | I11: 38 | J11: 35 | K11: 35 | L11: 20 | N11: =Table1[[#This Row],[14-Apr]]-Table1[[#This Row],[28-Jun]]+Table1[[#This Row],[Restock]] -> 15 | O11: =Table1[[#This Row],[Sold]]*Table1[[#This Row],[Price]] -> 25.083612
N12: =Table1[[#This Row],[14-Apr]]-Table1[[#This Row],[28-Jun]]+Table1[[#This Row],[Restock]] -> 0 | O12: =Table1[[#This Row],[Sold]]*Table1[[#This Row],[Price]] -> 0
N13: =Table1[[#This Row],[14-Apr]]-Table1[[#This Row],[28-Jun]]+Table1[[#This Row],[Restock]] -> 0 | O13: =Table1[[#This Row],[Sold]]*Table1[[#This Row],[Price]] -> 0
A14: Kraft max ATF synthetic white | B14: 8 | C14: 20 | D14: 20 | E14: 19 | F14: 19 | G14: 18 | H14: 18 | I14: 18 | J14: 16 | K14: 16 | L14: 12 | N14: =Table1[[#This Row],[14-Apr]]-Table1[[#This Row],[28-Jun]]+Table1[[#This Row],[Restock]] -> 4 | O14: =Table1[[#This Row],[Sold]]*Table1[[#This Row],[Price]] -> 32
A15: Kraft max ATF red | N15: =Table1[[#This Row],[14-Apr]]-Table1[[#This Row],[28-Jun]]+Table1[[#This Row],[Restock]] -> 0 | O15: =Table1[[#This Row],[Sold]]*Table1[[#This Row],[Price]] -> 0
A16: Kraft max injector cleaner | B16: 5 | C16: 26 | D16: 25 | E16: 25 | F16: 25 | G16: 25 | H16: 22 | I16: 21 | J16: 20 | K16: 19 | L16: 47 | M16: 48 | N16: =Table1[[#This Row],[14-Apr]]-Table1[[#This Row],[28-Jun]]+Table1[[#This Row],[Restock]] -> 20 | O16: =Table1[[#This Row],[Sold]]*Table1[[#This Row],[Price]] -> 100
A17: Kraft max Gasoline plus | N17: =Table1[[#This Row],[14-Apr]]-Table1[[#This Row],[28-Jun]]+Table1[[#This Row],[Restock]] -> 0 | O17: =Table1[[#This Row],[Sold]]*Table1[[#This Row],[Price]] -> 0
N18: =Table1[[#This Row],[14-Apr]]-Table1[[#This Row],[28-Jun]]+Table1[[#This Row],[Restock]] -> 0 | O18: =Table1[[#This Row],[Sold]]*Table1[[#This Row],[Price]] -> 0
A19: Castrol 20w-50 | B19: 6 | C19: 20 | D19: 20 | E19: 20 | F19: 163 | G19: 162 | H19: =162-12 -> 150 | I19: 140 | J19: 139 | K19: 139 | L19: 135 | N19: =Table1[[#This Row],[14-Apr]]-Table1[[#This Row],[28-Jun]]+Table1[[#This Row],[Restock]] -> 4 | O19: =Table1[[#This Row],[Sold]]*Table1[[#This Row],[Price]] -> 24
A20: Castrol 10w-40 | B20: 6 | C20: 27 | D20: 25 | E20: 22 | F20: 164 | G20: 163 | H20: =158-12 -> 146 | I20: 140 | J20: 125 | K20: 121 | L20: 35 | N20: =Table1[[#This Row],[14-Apr]]-Table1[[#This Row],[28-Jun]]+Table1[[#This Row],[Restock]] -> 86 | O20: =Table1[[#This Row],[Sold]]*Table1[[#This Row],[Price]] -> 516
A21: Castrol 5w-30 | B21: 10 | N21: =Table1[[#This Row],[14-Apr]]-Table1[[#This Row],[28-Jun]]+Table1[[#This Row],[Restock]] -> 0 | O21: =Table1[[#This Row],[Sold]]*Table1[[#This Row],[Price]] -> 0
A22: Castrol Mag 5w-30 | B22: 10 | C22: 6 | D22: 6 | E22: 6 | F22: 150 | G22: 150 | H22: =149-12 -> 137 | I22: 137 | J22: 137 | K22: 137 | L22: 122 | N22: =Table1[[#This Row],[14-Apr]]-Table1[[#This Row],[28-Jun]]+Table1[[#This Row],[Restock]] -> 15 | O22: =Table1[[#This Row],[Sold]]*Table1[[#This Row],[Price]] -> 150
A23: Castrol 10w-40 4L | B23: 24 | C23: 6 | D23: 6 | E23: 4 | F23: 4 | G23: 4 | H23: 4 | I23: 4 | J23: 4 | K23: 4 | L23: 4 | N23: =Table1[[#This Row],[14-Apr]]-Table1[[#This Row],[28-Jun]]+Table1[[#This Row],[Restock]] -> 0 | O23: =Table1[[#This Row],[Sold]]*Table1[[#This Row],[Price]] -> 0
A24: Castrol 20w-50 4L | B24: 24 | C24: 4 | D24: 4 | E24: 4 | F24: 4 | G24: 4 | H24: 4 | I24: 4 | J24: 4 | K24: 4 | L24: 4 | N24: =Table1[[#This Row],[14-Apr]]-Table1[[#This Row],[28-Jun]]+Table1[[#This Row],[Restock]] -> 0 | O24: =Table1[[#This Row],[Sold]]*Table1[[#This Row],[Price]] -> 0
A25: Castrol Mag 5w-30 4L | B25: 40 | C25: 2 | D25: 2 | E25: 2 | F25: 2 | G25: 2 | H25: 2 | I25: 2 | J25: 2 | K25: 2 | L25: 2 | N25: =Table1[[#This Row],[14-Apr]]-Table1[[#This Row],[28-Jun]]+Table1[[#This Row],[Restock]] -> 0 | O25: =Table1[[#This Row],[Sold]]*Table1[[#This Row],[Price]] -> 0
A26: Castrol Mag 10w-40 | C26: 0 | D26: 0 | E26: 0 | F26: 144 | G26: 140 | H26: =140-12 -> 128 | I26: 125 | J26: 125 | K26: 118 | L26: 64 | N26: =Table1[[#This Row],[14-Apr]]-Table1[[#This Row],[28-Jun]]+Table1[[#This Row],[Restock]] -> 54 | O26: =Table1[[#This Row],[Sold]]*Table1[[#This Row],[Price]] -> 0
A27: hitek 10w-40 | B27: =300/89.7 -> 3.3444816 | C27: 2 | D27: 37 | E27: 34 | F27: 32 | G27: 31 | H27: 25 | I27: =14+12 -> 26 | J27: 16 | K27: 9 | L27: 24 | M27: 48 | N27: =Table1[[#This Row],[14-Apr]]-Table1[[#This Row],[28-Jun]]+Table1[[#This Row],[Restock]] -> 33 | O27: =Table1[[#This Row],[Sold]]*Table1[[#This Row],[Price]] -> 110.36789
A28: hitek 20w-50 | B28: =300/89.7 -> 3.3444816 | C28: 14 | D28: 14 | E28: 14 | F28: 13 | G28: 11 | H28: 11 | I28: =7+12 -> 19 | J28: 15 | K28: 13 | L28: 21 | M28: 48 | N28: =Table1[[#This Row],[14-Apr]]-Table1[[#This Row],[28-Jun]]+Table1[[#This Row],[Restock]] -> 40 | O28: =Table1[[#This Row],[Sold]]*Table1[[#This Row],[Price]] -> 133.77926
A29: hitek ATF | B29: =300/89.7 -> 3.3444816 | C29: 13 | D29: 12 | E29: 9 | F29: 7 | G29: 5 | H29: 3 | I29: =12 -> 12 | J29: 0 | K29: 0 | L29: 24 | M29: 24 | N29: =Table1[[#This Row],[14-Apr]]-Table1[[#This Row],[28-Jun]]+Table1[[#This Row],[Restock]] -> 0 | O29: =Table1[[#This Row],[Sold]]*Table1[[#This Row],[Price]] -> 0
N30: =Table1[[#This Row],[14-Apr]]-Table1[[#This Row],[28-Jun]]+Table1[[#This Row],[Restock]] -> 0 | O30: =Table1[[#This Row],[Sold]]*Table1[[#This Row],[Price]] -> 0
N31: =Table1[[#This Row],[14-Apr]]-Table1[[#This Row],[28-Jun]]+Table1[[#This Row],[Restock]] -> 0 | O31: =Table1[[#This Row],[Sold]]*Table1[[#This Row],[Price]] -> 0
A32: Max-x 10w-40 | B32: 4 | C32: 0 | D32: 0 | E32: 0 | N32: =Table1[[#This Row],[14-Apr]]-Table1[[#This Row],[28-Jun]]+Table1[[#This Row],[Restock]] -> 0 | O32: =Table1[[#This Row],[Sold]]*Table1[[#This Row],[Price]] -> 0
A33: Max-x 15w-40 | B33: 4 | C33: 9 | D33: 9 | E33: 7 | F33: 7 | G33: 7 | H33: 7 | I33: 4 | J33: 4 | K33: 4 | L33: 0 | N33: =Table1[[#This Row],[14-Apr]]-Table1[[#This Row],[28-Jun]]+Table1[[#This Row],[Restock]] -> 4 | O33: =Table1[[#This Row],[Sold]]*Table1[[#This Row],[Price]] -> 16
A34: Max-x 20w-50 | B34: 4 | C34: 2 | D34: 1 | E34: 0 | N34: =Table1[[#This Row],[14-Apr]]-Table1[[#This Row],[28-Jun]]+Table1[[#This Row],[Restock]] -> 0 | O34: =Table1[[#This Row],[Sold]]*Table1[[#This Row],[Price]] -> 0
A35: Sure guard anitfreeze | B35: 4 | C35: 10 | D35: 10 | E35: 10 | F35: 10 | G35: 10 | H35: 10 | I35: 10 | J35: 10 | K35: 10 | L35: 8 | N35: =Table1[[#This Row],[14-Apr]]-Table1[[#This Row],[28-Jun]]+Table1[[#This Row],[Restock]] -> 2 | O35: =Table1[[#This Row],[Sold]]*Table1[[#This Row],[Price]] -> 8
N36: =Table1[[#This Row],[14-Apr]]-Table1[[#This Row],[28-Jun]]+Table1[[#This Row],[Restock]] -> 0 | O36: =Table1[[#This Row],[Sold]]*Table1[[#This Row],[Price]] -> 0
A37: Magic plus 15-40 | B37: 4 | L37: 24 | M37: 24 | N37: =Table1[[#This Row],[14-Apr]]-Table1[[#This Row],[28-Jun]]+Table1[[#This Row],[Restock]] -> 0 | O37: =Table1[[#This Row],[Sold]]*Table1[[#This Row],[Price]] -> 0
N38: =Table1[[#This Row],[14-Apr]]-Table1[[#This Row],[28-Jun]]+Table1[[#This Row],[Restock]] -> 0 | O38: =Table1[[#This Row],[Sold]]*Table1[[#This Row],[Price]] -> 0
C39: 1 | N39: =Table1[[#This Row],[14-Apr]]-Table1[[#This Row],[28-Jun]]+Table1[[#This Row],[Restock]] -> 0 | O39: =Table1[[#This Row],[Sold]]*Table1[[#This Row],[Price]] -> 0
C40: 1 | D40: 1 | E40: 1 | F40: 1 | G40: 1 | H40: 1 | I40: 1 | J40: 0 | N40: =Table1[[#This Row],[14-Apr]]-Table1[[#This Row],[28-Jun]]+Table1[[#This Row],[Restock]] -> 0 | O40: =Table1[[#This Row],[Sold]]*Table1[[#This Row],[Price]] -> 0
C41: 1 | D41: 1 | E41: 1 | F41: 1 | G41: 1 | H41: 1 | I41: 1 | J41: 0 | N41: =Table1[[#This Row],[14-Apr]]-Table1[[#This Row],[28-Jun]]+Table1[[#This Row],[Restock]] -> 0 | O41: =Table1[[#This Row],[Sold]]*Table1[[#This Row],[Price]] -> 0
C42: 1 | D42: 1 | E42: 1 | F42: 1 | G42: 1 | H42: 0 | N42: =Table1[[#This Row],[14-Apr]]-Table1[[#This Row],[28-Jun]]+Table1[[#This Row],[Restock]] -> 0 | O42: =Table1[[#This Row],[Sold]]*Table1[[#This Row],[Price]] -> 0
N43: =Table1[[#This Row],[14-Apr]]-Table1[[#This Row],[28-Jun]]+Table1[[#This Row],[Restock]] -> 0 | O43: =Table1[[#This Row],[Sold]]*Table1[[#This Row],[Price]] -> 0
N44: =Table1[[#This Row],[14-Apr]]-Table1[[#This Row],[28-Jun]]+Table1[[#This Row],[Restock]] -> 0 | O44: =Table1[[#This Row],[Sold]]*Table1[[#This Row],[Price]] -> 0
N45: =Table1[[#This Row],[14-Apr]]-Table1[[#This Row],[28-Jun]]+Table1[[#This Row],[Restock]] -> 0 | O45: =Table1[[#This Row],[Sold]]*Table1[[#This Row],[Price]] -> 0
A46: Shampion 10w-40 | B46: =350/89.7 -> 3.9018952 | C46: 0 | D46: 24 | E46: 57 | F46: 55 | G46: 54 | H46: =50-12 -> 38 | I46: 27 | J46: 146 | K46: 141 | L46: 45 | N46: =Table1[[#This Row],[14-Apr]]-Table1[[#This Row],[28-Jun]]+Table1[[#This Row],[Restock]] -> 96 | O46: =Table1[[#This Row],[Sold]]*Table1[[#This Row],[Price]] -> 374.58194
A47: Shampion 20w-50 | B47: =350/89.7 -> 3.9018952 | C47: 32 | D47: 31 | E47: 60 | F47: 59 | G47: 54 | H47: =53-12 -> 41 | I47: 29 | J47: 158 | K47: 155 | L47: 96 | N47: =Table1[[#This Row],[14-Apr]]-Table1[[#This Row],[28-Jun]]+Table1[[#This Row],[Restock]] -> 59 | O47: =Table1[[#This Row],[Sold]]*Table1[[#This Row],[Price]] -> 230.21182
A48: Shampion 50w-40 | B48: =350/89.7 -> 3.9018952 | C48: 23 | D48: 23 | E48: 21 | F48: 21 | G48: 21 | H48: 17 | I48: 12 | J48: 11 | K48: 5 | L48: 0 | N48: =Table1[[#This Row],[14-Apr]]-Table1[[#This Row],[28-Jun]]+Table1[[#This Row],[Restock]] -> 5 | O48: =Table1[[#This Row],[Sold]]*Table1[[#This Row],[Price]] -> 19.509476
A49: Shampion ATF | B49: =350/89.7 -> 3.9018952 | C49: 0 | D49: 36 | E49: 32 | F49: 31 | G49: 30 | H49: =29-12 -> 17 | I49: 2 | J49: 132 | K49: 125 | L49: 50 | N49: =Table1[[#This Row],[14-Apr]]-Table1[[#This Row],[28-Jun]]+Table1[[#This Row],[Restock]] -> 75 | O49: =Table1[[#This Row],[Sold]]*Table1[[#This Row],[Price]] -> 292.64214
A50: Shampion 15-40 | B50: =350/89.7 -> 3.9018952 | L50: 120 | M50: 144 | N50: =Table1[[#This Row],[14-Apr]]-Table1[[#This Row],[28-Jun]]+Table1[[#This Row],[Restock]] -> 24 | O50: =Table1[[#This Row],[Sold]]*Table1[[#This Row],[Price]] -> 93.645485
A51: Shampion Antifreeze | B51: 5 | C51: 6 | D51: 6 | E51: 4 | F51: 4 | G51: 4 | H51: 3 | I51: 2 | J51: 2 | K51: 2 | L51: 0 | N51: =Table1[[#This Row],[14-Apr]]-Table1[[#This Row],[28-Jun]]+Table1[[#This Row],[Restock]] -> 2 | O51: =Table1[[#This Row],[Sold]]*Table1[[#This Row],[Price]] -> 10
A52: Coolant pre mixed | B52: 5 | C52: 10 | D52: 10 | E52: 7 | F52: 7 | G52: 7 | H52: 7 | I52: 6 | J52: 5 | K52: 5 | L52: 2 | N52: =Table1[[#This Row],[14-Apr]]-Table1[[#This Row],[28-Jun]]+Table1[[#This Row],[Restock]] -> 3 | O52: =Table1[[#This Row],[Sold]]*Table1[[#This Row],[Price]] -> 15
N53: =Table1[[#This Row],[14-Apr]]-Table1[[#This Row],[28-Jun]]+Table1[[#This Row],[Restock]] -> 0 | O53: =Table1[[#This Row],[Sold]]*Table1[[#This Row],[Price]] -> 0
A54: Oil filter 1$ | B54: 5 | C54: 79 | D54: 79 | E54: 78 | F54: 78 | G54: 78 | H54: 78 | I54: 77 | J54: 77 | K54: 77 | L54: 75 | N54: =Table1[[#This Row],[14-Apr]]-Table1[[#This Row],[28-Jun]]+Table1[[#This Row],[Restock]] -> 2 | O54: =Table1[[#This Row],[Sold]]*Table1[[#This Row],[Price]] -> 10
A55: oil filter | N55: =Table1[[#This Row],[14-Apr]]-Table1[[#This Row],[28-Jun]]+Table1[[#This Row],[Restock]] -> 0 | O55: =Table1[[#This Row],[Sold]]*Table1[[#This Row],[Price]] -> 0
N56: =Table1[[#This Row],[14-Apr]]-Table1[[#This Row],[28-Jun]]+Table1[[#This Row],[Restock]] -> 0 | O56: =Table1[[#This Row],[Sold]]*Table1[[#This Row],[Price]] -> 0
N57: =Table1[[#This Row],[14-Apr]]-Table1[[#This Row],[28-Jun]]+Table1[[#This Row],[Restock]] -> 0 | O57: =Table1[[#This Row],[Sold]]*Table1[[#This Row],[Price]] -> 0
A58: Wipers | B58: 4 | C58: 27 | D58: 26 | E58: 26 | F58: 24 | G58: 24 | H58: 23 | I58: 21 | J58: 20 | K58: 19 | L58: 19 | N58: =Table1[[#This Row],[14-Apr]]-Table1[[#This Row],[28-Jun]]+Table1[[#This Row],[Restock]] -> 0 | O58: =Table1[[#This Row],[Sold]]*Table1[[#This Row],[Price]] -> 0
N59: =Table1[[#This Row],[14-Apr]]-Table1[[#This Row],[28-Jun]]+Table1[[#This Row],[Restock]] -> 0
A60: Balance | G60: {=SUM(G5:G58*B5:B58)} -> 6263.9688 | H60: {=SUM(H5:H58*B5:B58)} -> 5576.3194 | I60: {=SUM(I5:I58*B5:B58)} -> 5276.9994 | J60: {=SUM(J5:J58*B5:B58)} -> 6499.6795 | K60: {=SUM(K5:K58*B5:B58)} -> 6333.2781 | L60: {=SUM(L5:L58*B5:B58)} -> 5482.8155 | N60: =SUM(Table1[Sold]) -> 569 | O60: =SUM(Table1[Value]) -> 2233.2854

Sheet Kiosk And Gaz Halba
F1: Gaz
A2: Column1 | B2: Column2 | C2: Column3 | D2: Column4 | F2: Date | G2: Available | H2: Sold | I2: Restock
F3: 46043 | I3: 19 | K3: Current Gaz Stock | L3: Unit Price | M3: Stock Value
F4: 46044 | H4: 8 | I4: 7 | K4: =SUM($I$3:$I$115)-SUM($H$3:$H$115) -> 19 | L4: 21 | M4: =K4*L4 -> 399
F5: 46045 | H5: 6 | I5: 10
F6: 46046 | H6: 5 | I6: 7
F7: 46047 | H7: 3
F8: 46048 | H8: 9 | I8: 9
F9: 46049 | H9: 4 | I9: 5
F10: 46050 | H10: 4
F11: 46051 | H11: 7 | I11: 9
F12: 46052 | H12: 8
F13: 46053 | H13: 4 | I13: 14
F14: 46054 | H14: 11
F15: 46055 | H15: 3 | I15: 15
F16: 46056 | H16: 6
F17: 46057 | H17: 2
F18: 46058 | H18: 3 | I18: 11
F19: 46059 | H19: 2
F20: 46060 | H20: 6 | I20: 6
F21: 46061 | H21: 2
F22: 46062 | H22: 10
F23: 46063 | H23: 4 | I23: 17
F24: 46064 | H24: 4
F25: 46065 | H25: 8 | I25: 9
F26: 46066 | H26: 3
F27: 46067 | H27: 10 | I27: 15
F28: 46068 | H28: 13
F29: 46069 | H29: 2 | I29: 20
F30: 46070 | H30: 1
F31: 46071 | H31: 5
F32: 46072 | H32: 4 | I32: 10
F33: 46073 | H33: 5
F34: 46074 | H34: 1 | I34: 5
F35: 46075 | H35: 3
F36: 46076 | H36: 2
F37: 46077 | H37: 3 | I37: 8
F38: 46078 | H38: 2
F39: 46079 | H39: 8 | I39: 4
F40: 46080 | H40: 6
F41: 46081 | H41: 16 | I41: 23
F42: 46082 | H42: 7
F43: 46083 | H43: 9
F44: 46084 | H44: 12 | I44: 24
F45: 46085 | H45: 6
F46: 46086 | H46: 7 | I46: 17
F47: 46087 | H47: 7
F48: 46088 | H48: 4
F49: 46089 | H49: 8
F50: 46090 | H50: 1 | I50: 10
F51: 46091 | H51: 0
F52: 46092 | H52: 1
F53: 46093 | H53: =4+5 -> 9 | I53: 16
F54: 46094 | H54: 2
F55: 46095 | H55: 6
F56: 46096 | H56: 6
F57: 46097 | H57: 2 | I57: 18
F58: 46098 | H58: 2
F59: 46099 | H59: 1
F60: 46100 | H60: 3 | I60: 9
F61: 46101 | H61: 13
F62: 46102 | H62: 8
F63: 46103 | H63: 0 | I63: 0
F64: 46104 | H64: 1 | I64: 21
F65: 46105 | H65: 3
F66: 46106 | H66: 3
F67: 46107 | H67: 2
F68: 46108 | H68: 8 | I68: 11
F69: 46109 | H69: 6
F70: 46110 | H70: 1
F71: 46111 | H71: 5 | I71: 15
F72: 46112 | H72: 2 | I72: 4
F73: 46113 | H73: 13 | I73: 9
F74: 46114 | H74: 1
F75: 46115 | H75: 2
F76: 46116 | H76: 1 | I76: 7
F77: 46117 | H77: 1
F78: 46118 | H78: 1
F79: 46119 | H79: 2
F80: 46120 | H80: 1
F81: 46121 | H81: 1
F82: 46122 | H82: 1
F83: 46123 | H83: 2 | I83: 8
F84: 46124 | H84: 5
F85: 46125 | H85: 2
F86: 46126 | I86: 9
F87: 46128 | H87: 4
F88: 46129 | H88: 2
F89: 46131 | H89: 4
F90: 46134 | H90: 1
F91: 46135 | H91: 3
F92: 46136 | H92: 5
F93: 46137 | I93: 13
F94: 46138 | H94: 3
F95: 46141 | H95: 2
F96: 46143 | H96: 7
F97: 46146 | H97: 1
F98: 46147 | H98: 4 | I98: 12
F99: 46148 | H99: 5
F100: 46149
...

Sheet Daily Tekrit
C1: Opening Balance | D1: IN - Net | E1: Total Purchases | F1: Balance
C2: 0 | D2: =AR5 -> 169776.61 | E2: =SUM('BM Stock Tekrit'!N78) -> 157127.91 | F2: =0-(C2-D2+E2) -> 12648.7
C4: CASH IN | W4: CASH OUT | AR4: NET
A5: TOTAL | C5: =SUM(C8:C272) -> 64644 | D5: =SUM(D8:D272) -> 281.4225 | E5: =SUM(E8:E272) -> 73177.58 | F5: =SUM(F8:F272) -> 68768 | G5: =SUM(G8:G272) -> 281.4005 | H5: =SUM(H8:H272) -> 77260.843 | I5: =SUM(I8:I272) -> 133412 | J5: =SUM(J8:J272) -> 150438.42 | ... U5: =SUM(U8:U272) -> 216903.18 | W5: =SUM(W8:W272) -> 28986.47 | X5: =SUM(X8:X272) -> 4981.8138 | Y5: =SUM(Y8:Y272) -> 595.5 | Z5: =SUM(Z8:Z272) -> 0 | AA5: =SUM(AA8:AA272) -> 445 | AB5: =SUM(AB8:AB272) -> 0 | AC5: =SUM(AC8:AC272) -> 0 | AD5: =SUM(AD8:AD272) -> 445 | ... AO5: =SUM(AO8:AO272) -> 47126.57 | AP5: =SUM(AP8:AP107) -> 0 | AQ5: =SUM(AQ8:AQ107) -> 0 | AR5: =SUM(AR8:AR272) -> 169776.61
C6: BENZINE | K6: MEZOUT | N6: OTHER | Z6: PURCHASES | AE6: EXPENSES
A7: Date | B7: Price Change | C7: Benzine 1 L | D7: Benzine 1 P | E7: Total Benzine 1 | F7: Benzine 2 L | G7: Benzine 2 P | H7: Total Benzine 2 | I7: Total Benzine L (1+2) | J7: Total Benzine $ | K7: Mezout L | L7: Mezout P | M7: Total Mezout | N7: Oil | O7: Wash | P7: Gaz | Q7: Fragrence | R7: Kiosk | S7: Payments | T7: Coupon | U7: Total IN | W7: Debts | X7: Coupons | Y7: Difference | Z7: Purchase Oil | AA7: Purchase Kiosk | AB7: Purchase Gaz | AC7: Other Purchases | AD7: Total Purchases | AE7: PMNT - Rent | AF7: Salaries | AG7: R&M | AH7: Utilities | AI7: Client Satisfaction | AJ7: Tips | AK7: New Assets | AL7: Other | AM7: Total Expense | AN7: Profit Sharing | AO7: Total OUT | AP7: Notes | AR7: Daily Total
A8: 46009 | C8: ='ODOMETERS Tekrit'!J4 -> 253 | D8: 0.7988 | E8: ='Daily Tekrit'!$C8*'Daily Tekrit'!$D8 -> 202.0964 | F8: ='ODOMETERS Tekrit'!K4 -> 413 | G8: 0.7988 | H8: ='Daily Tekrit'!$F8*'Daily Tekrit'!$G8 -> 329.9044 | I8: ='Daily Tekrit'!$C8+'Daily Tekrit'!$F8 -> 666 | J8: ='Daily Tekrit'!$E8+'Daily Tekrit'!$H8 -> 532.0008 | K8: ='ODOMETERS Tekrit'!L4 -> 269.354 | L8: 0.738 | M8: ='Daily Tekrit'!$K8*'Daily Tekrit'!$L8 -> 198.78325 | T8: 1.67 | U8: ='Daily Tekrit'!$J8+'Daily Tekrit'!$M8+SUM($N8:$T8) -> 732.45405 | W8: 74 | X8: 16 | Y8: 44 | AD8: =SUM(Z8:AC8) -> 0 | AK8: 82 | AL8: =14.4+50 -> 64.4 | AM8: =SUM(AE8:AL8) -> 146.4 | AO8: =SUM(V8:Y8,AD8,AM8,AN8) -> 280.4 | AR8: ='Daily Tekrit'!$U8-'Daily Tekrit'!$AO8 -> 452.05405
A9: 46010 | C9: ='ODOMETERS Tekrit'!J5 -> 110 | D9: 0.7988 | E9: ='Daily Tekrit'!$C9*'Daily Tekrit'!$D9 -> 87.868 | F9: ='ODOMETERS Tekrit'!K5 -> 247 | G9: 0.7988 | H9: ='Daily Tekrit'!$F9*'Daily Tekrit'!$G9 -> 197.3036 | I9: ='Daily Tekrit'!$C9+'Daily Tekrit'!$F9 -> 357 | J9: ='Daily Tekrit'!$E9+'Daily Tekrit'!$H9 -> 285.1716 | K9: ='ODOMETERS Tekrit'!L5 -> 116.975 | L9: 0.738 | M9: ='Daily Tekrit'!$K9*'Daily Tekrit'!$L9 -> 86.32755 | S9: 74 | U9: ='Daily Tekrit'!$J9+'Daily Tekrit'!$M9+SUM($N9:$T9) -> 445.49915 | X9: =9*0.7988 -> 7.1892 | Y9: 10 | AD9: =SUM(Z9:AC9) -> 0 | AM9: =SUM(AE9:AL9) -> 0 | AO9: =SUM(W9:Y9,AD9,AM9,AN9) -> 17.1892 | AR9: =U9-AO9 -> 428.30995
A10: 46011 | C10: ='ODOMETERS Tekrit'!J6 -> 254 | D10: 0.7848 | E10: ='Daily Tekrit'!$C10*'Daily Tekrit'!$D10 -> 199.3392 | F10: ='ODOMETERS Tekrit'!K6 -> 523 | G10: 0.7848 | H10: ='Daily Tekrit'!$F10*'Daily Tekrit'!$G10 -> 410.4504 | I10: ='Daily Tekrit'!$C10+'Daily Tekrit'!$F10 -> 777 | J10: ='Daily Tekrit'!$E10+'Daily Tekrit'!$H10 -> 609.7896 | K10: ='ODOMETERS Tekrit'!L6 -> 257.235 | L10: 0.723 | M10: ='Daily Tekrit'!$K10*'Daily Tekrit'!$L10 -> 185.9809 | U10: ='Daily Tekrit'!$J10+'Daily Tekrit'!$M10+SUM($N10:$T10) -> 795.7705 | AD10: =SUM(Z10:AC10) -> 0 | AH10: =400/89.7 -> 4.4593088 | AJ10: =300/89.7 -> 3.3444816 | AL10: =26+61 -> 87 | AM10: =SUM(AE10:AL10) -> 94.80379 | AO10: =SUM(W10:Y10,AD10,AM10,AN10) -> 94.80379 | AP10: Jarret Gaz, return to the tank due to pump repair (26) | AR10: =U10-AO10 -> 700.96671
A11: 46012 | C11: ='ODOMETERS Tekrit'!J7 -> 116 | D11: 0.7848 | E11: ='Daily Tekrit'!$C11*'Daily Tekrit'!$D11 -> 91.0368 | F11: ='ODOMETERS Tekrit'!K7 -> 814 | G11: 0.7848 | H11: ='Daily Tekrit'!$F11*'Daily Tekrit'!$G11 -> 638.8272 | I11: ='Daily Tekrit'!$C11+'Daily Tekrit'!$F11 -> 930 | J11: ='Daily Tekrit'!$E11+'Daily Tekrit'!$H11 -> 729.864 | K11: ='ODOMETERS Tekrit'!L7 -> 457.86 | L11: 0.723 | M11: ='Daily Tekrit'!$K11*'Daily Tekrit'!$L11 -> 331.03278 | U11: ='Daily Tekrit'!$J11+'Daily Tekrit'!$M11+SUM($N11:$T11) -> 1060.8968 | W11: =200*0.723+200/89.7 -> 146.82965 | AD11: =SUM(Z11:AC11) -> 0 | AF11: 20 | AM11: =SUM(AE11:AL11) -> 20 | AO11: =SUM(W11:Y11,AD11,AM11,AN11) -> 166.82965 | AR11: =U11-AO11 -> 894.06713
A12: 46013 | C12: ='ODOMETERS Tekrit'!J8 -> 0 | D12: 0.7848 | E12: ='Daily Tekrit'!$C12*'Daily Tekrit'!$D12 -> 0 | F12: ='ODOMETERS Tekrit'!K8 -> 413 | G12: 0.7848 | H12: ='Daily Tekrit'!$F12*'Daily Tekrit'!$G12 -> 324.1224 | I12: ='Daily Tekrit'!$C12+'Daily Tekrit'!$F12 -> 413 | J12: ='Daily Tekrit'!$E12+'Daily Tekrit'!$H12 -> 324.1224 | K12: ='ODOMETERS Tekrit'!L8 -> 139.91 | L12: 0.723 | M12: ='Daily Tekrit'!$K12*'Daily Tekrit'!$L12 -> 101.15493 | S12: =150000/89700 -> 1.6722408 | U12: ='Daily Tekrit'!$J12+'Daily Tekrit'!$M12+SUM($N12:$T12) -> 426.94957 | X12: =20*0.7848 -> 15.696 | AD12: =SUM(Z12:AC12) -> 0 | AL12: 60 | AM12: =SUM(AE12:AL12) -> 60 | AO12: =SUM(W12:Y12,AD12,AM12,AN12) -> 75.696 | AP12: دفتر فواتير | AR12: =U12-AO12 -> 351.25357
A13: 46014 | B13: Pre Price | C13: ='ODOMETERS Tekrit'!J9 -> 0 | D13: 0.7848 | E13: ='Daily Tekrit'!$C13*'Daily Tekrit'!$D13 -> 0 | F13: ='ODOMETERS Tekrit'!K9 -> 272 | G13: 0.7848 | H13: ='Daily Tekrit'!$F13*'Daily Tekrit'!$G13 -> 213.4656 | I13: ='Daily Tekrit'!$C13+'Daily Tekrit'!$F13 -> 272 | J13: ='Daily Tekrit'!$E13+'Daily Tekrit'!$H13 -> 213.4656 | K13: ='ODOMETERS Tekrit'!L9 -> 70.2 | L13: 0.723 | M13: ='Daily Tekrit'!$K13*'Daily Tekrit'!$L13 -> 50.7546 | U13: ='Daily Tekrit'!$J13+'Daily Tekrit'!$M13+SUM($N13:$T13) -> 264.2202 | AD13: =SUM(Z13:AC13) -> 0 | AF13: 20 | AH13: 11 | AM13: =SUM(AE13:AL13) -> 31 | AO13: =SUM(W13:Y13,AD13,AM13,AN13) -> 31 | AP13: Municipality | AR13: =U13-AO13 -> 233.2202
A14: 46014 | B14: Post Price | C14: ='ODOMETERS Tekrit'!J10 -> 0 | D14: 0.7715 | E14: ='Daily Tekrit'!$C14*'Daily Tekrit'!$D14 -> 0 | F14: ='ODOMETERS Tekrit'!K10 -> 345 | G14: 0.7715 | H14: ='Daily Tekrit'!$F14*'Daily Tekrit'!$G14 -> 266.1675 | I14: ='Daily Tekrit'!$C14+'Daily Tekrit'!$F14 -> 345 | J14: ='Daily Tekrit'!$E14+'Daily Tekrit'!$H14 -> 266.1675 | K14: ='ODOMETERS Tekrit'!L10 -> 127 | L14: 0.7135 | M14: ='Daily Tekrit'!$K14*'Daily Tekrit'!$L14 -> 90.6145 | U14: ='Daily Tekrit'!$J14+'Daily Tekrit'!$M14+SUM($N14:$T14) -> 356.782 | AD14: =SUM(Z14:AC14) -> 0 | AM14: =SUM(AE14:AL14) -> 0 | AO14: =SUM(W14:Y14,AD14,AM14,AN14) -> 0 | AR14: =U14-AO14 -> 356.782
A15: 46015 | C15: ='ODOMETERS Tekrit'!J11 -> 0 | D15: 0.7715 | E15: ='Daily Tekrit'!$C15*'Daily Tekrit'!$D15 -> 0 | F15: ='ODOMETERS Tekrit'!K11 -> 549 | G15: 0.7715 | H15: ='Daily Tekrit'!$F15*'Daily Tekrit'!$G15 -> 423.5535 | I15: ='Daily Tekrit'!$C15+'Daily Tekrit'!$F15 -> 549 | J15: ='Daily Tekrit'!$E15+'Daily Tekrit'!$H15 -> 423.5535 | K15: ='ODOMETERS Tekrit'!L11 -> 227 | L15: 0.7135 | M15: ='Daily Tekrit'!$K15*'Daily Tekrit'!$L15 -> 161.9645 | U15: ='Daily Tekrit'!$J15+'Daily Tekrit'!$M15+SUM($N15:$T15) -> 585.518 | AD15: =SUM(Z15:AC15) -> 0 | AF15: 10 | AM15: =SUM(AE15:AL15) -> 10 | AO15: =SUM(W15:Y15,AD15,AM15,AN15) -> 10 | AR15: =U15-AO15 -> 575.518
A16: 46016 | C16: ='ODOMETERS Tekrit'!J12 -> 0 | D16: 0.7715 | E16: ='Daily Tekrit'!$C16*'Daily Tekrit'!$D16 -> 0 | F16: ='ODOMETERS Tekrit'!K12 -> 620 | G16: 0.7715 | H16: ='Daily Tekrit'!$F16*'Daily Tekrit'!$G16 -> 478.33 | I16: ='Daily Tekrit'!$C16+'Daily Tekrit'!$F16 -> 620 | J16: ='Daily Tekrit'!$E16+'Daily Tekrit'!$H16 -> 478.33 | K16: ='ODOMETERS Tekrit'!L12 -> 344 | L16: 0.7135 | M16: ='Daily Tekrit'!$K16*'Daily Tekrit'!$L16 -> 245.444 | T16: 8.36 | U16: ='Daily Tekrit'!$J16+'Daily Tekrit'!$M16+SUM($N16:$T16) -> 732.134 | X16: 71.35 | AD16: =SUM(Z16:AC16) -> 0 | AH16: 14.49 | AM16: =SUM(AE16:AL16) -> 14.49 | AO16: =SUM(W16:Y16,AD16,AM16,AN16) -> 85.84 | AR16: =U16-AO16 -> 646.294
A17: 46017 | C17: ='ODOMETERS Tekrit'!J13 -> 0 | D17: 0.7715 | E17: ='Daily Tekrit'!$C17*'Daily Tekrit'!$D17 -> 0 | F17: ='ODOMETERS Tekrit'!K13 -> 522 | G17: 0.7715 | H17: ='Daily Tekrit'!$F17*'Daily Tekrit'!$G17 -> 402.723 | I17: ='Daily Tekrit'!$C17+'Daily Tekrit'!$F17 -> 522 | J17: ='Daily Tekrit'!$E17+'Daily Tekrit'!$H17 -> 402.723 | K17: ='ODOMETERS Tekrit'!L13 -> 97 | L17: 0.7135 | M17: ='Daily Tekrit'!$K17*'Daily Tekrit'!$L17 -> 69.2095 | U17: ='Daily Tekrit'!$J17+'Daily Tekrit'!$M17+SUM($N17:$T17) -> 471.9325 | AD17: =SUM(Z17:AC17) -> 0 | AH17: =5+400/89.7 -> 9.4593088 | AM17: =SUM(AE17:AL17) -> 9.4593088 | AO17: =SUM(W17:Y17,AD17,AM17,AN17) -> 9.4593088 | AR17: =U17-AO17 -> 462.47319
A18: 46018 | C18: ='ODOMETERS Tekrit'!J14 -> 170 | D18: 0.7559 | E18: ='Daily Tekrit'!$C18*'Daily Tekrit'!$D18 -> 128.503 | F18: ='ODOMETERS Tekrit'!K14 -> 679 | G18: 0.7559 | H18: ='Daily Tekrit'!$F18*'Daily Tekrit'!$G18 -> 513.2561 | I18: ='Daily Tekrit'!$C18+'Daily Tekrit'!$F18 -> 849 | J18: ='Daily Tekrit'!$E18+'Daily Tekrit'!$H18 -> 641.7591 | K18: ='ODOMETERS Tekrit'!L14 -> 380 | L18: 0.7028 | M18: ='Daily Tekrit'!$K18*'Daily Tekrit'!$L18 -> 267.064 | T18: =370/89.7 -> 4.1248606 | U18: ='Daily Tekrit'!$J18+'Daily Tekrit'!$M18+SUM($N18:$T18) -> 912.94796 | X18: =50*0.7028 -> 35.14 | Y18: 20 | AD18: =SUM(Z18:AC18) -> 0 | AJ18: =5+300/89.7 -> 8.3444816 | AL18: =1300/89.7 -> 14.492754 | AM18: =SUM(AE18:AL18) -> 22.837235 | AO18: =SUM(W18:Y18,AD18,AM18,AN18) -> 77.977235 | AP18: سحب من المحطة تجريب فرد | AR18: =U18-AO18 -> 834.97073
A19: 46019 | C19: ='ODOMETERS Tekrit'!J15 -> 865 | D19: 0.7559 | E19: ='Daily Tekrit'!$C19*'Daily Tekrit'!$D19 -> 653.8535 | F19: ='ODOMETERS Tekrit'!K15 -> 281 | G19: 0.7559 | H19: ='Daily Tekrit'!$F19*'Daily Tekrit'!$G19 -> 212.4079 | I19: ='Daily Tekrit'!$C19+'Daily Tekrit'!$F19 -> 1146 | J19: ='Daily Tekrit'!$E19+'Daily Tekrit'!$H19 -> 866.2614 | K19: ='ODOMETERS Tekrit'!L15 -> 365 | L19: 0.7028 | M19: ='Daily Tekrit'!$K19*'Daily Tekrit'!$L19 -> 256.522 | U19: ='Daily Tekrit'!$J19+'Daily Tekrit'!$M19+SUM($N19:$T19) -> 1122.7834 | X19: 128 | AD19: =SUM(Z19:AC19) -> 0 | AL19: =500*0.7559+11.5+500/89.7 -> 395.02414 | AM19: =SUM(AE19:AL19) -> 395.02414 | AO19: =SUM(W19:Y19,AD19,AM19,AN19) -> 523.02414 | AP19: سحب من المحطة تجريب فرد وتحويل من خزان لخزان | AR19: =U19-AO19 -> 599.75926
A20: 46020 | C20: ='ODOMETERS Tekrit'!J16 -> 441 | D20: 0.7559 | E20: ='Daily Tekrit'!$C20*'Daily Tekrit'!$D20 -> 333.3519 | F20: ='ODOMETERS Tekrit'!K16 -> 72 | G20: 0.7559 | H20: ='Daily Tekrit'!$F20*'Daily Tekrit'!$G20 -> 54.4248 | I20: ='Daily Tekrit'!$C20+'Daily Tekrit'!$F20 -> 513 | J20: ='Daily Tekrit'!$E20+'Daily Tekrit'!$H20 -> 387.7767 | K20: ='ODOMETERS Tekrit'!L16 -> 265 | L20: 0.7028 | M20: ='Daily Tekrit'!$K20*'Daily Tekrit'!$L20 -> 186.242 | U20: ='Daily Tekrit'!$J20+'Daily Tekrit'!$M20+SUM($N20:$T20) -> 574.0187 | W20: 14 | AD20: =SUM(Z20:AC20) -> 0 | AM20: =SUM(AE20:AL20) -> 0 | AO20: =SUM(W20:Y20,AD20,AM20,AN20) -> 14 | AR20: =U20-AO20 -> 560.0187
A21: 46021 | B21: Pre Price | C21: ='ODOMETERS Tekrit'!J17 -> 201 | D21: 0.7559 | E21: ='Daily Tekrit'!$C21*'Daily Tekrit'!$D21 -> 151.9359 | F21: ='ODOMETERS Tekrit'!K17 -> 26 | G21: 0.7559 | H21: ='Daily Tekrit'!$F21*'Daily Tekrit'!$G21 -> 19.6534 | I21: ='Daily Tekrit'!$C21+'Daily Tekrit'!$F21 -> 227 | J21: ='Daily Tekrit'!$E21+'Daily Tekrit'!$H21 -> 171.5893 | K21: ='ODOMETERS Tekrit'!L17 -> 197 | L21: 0.7028 | M21: ='Daily Tekrit'!$K21*'Daily Tekrit'!$L21 -> 138.4516 | U21: ='Daily Tekrit'!$J21+'Daily Tekrit'!$M21+SUM($N21:$T21) -> 310.0409 | W21: 112.5 | AD21: =SUM(Z21:AC21) -> 0 | AH21: 13.37 | AM21: =SUM(AE21:AL21) -> 13.37 | AO21: =SUM(W21:Y21,AD21,AM21,AN21) -> 125.87 | AR21: =U21-AO21 -> 184.1709
A22: 46021 | B22: Post Price | C22: ='ODOMETERS Tekrit'!J18 -> 145 | D22: 0.7486 | E22: ='Daily Tekrit'!$C22*'Daily Tekrit'!$D22 -> 108.547 | F22: ='ODOMETERS Tekrit'!K18 -> 91 | G22: 0.7486 | H22: ='Daily Tekrit'!$F22*'Daily Tekrit'!$G22 -> 68.1226 | I22: ='Daily Tekrit'!$C22+'Daily Tekrit'!$F22 -> 236 | J22: ='Daily Tekrit'!$E22+'Daily Tekrit'!$H22 -> 176.6696 | K22: ='ODOMETERS Tekrit'!L18 -> 113 | L22: 0.6973 | M22: ='Daily Tekrit'!$K22*'Daily Tekrit'!$L22 -> 78.7949 | O22: =400/89.7 -> 4.4593088 | U22: ='Daily Tekrit'!$J22+'Daily Tekrit'!$M22+SUM($N22:$T22) -> 259.92381 | AD22: =SUM(Z22:AC22) -> 0 | AH22: =800/89.7 -> 8.9186176 | AJ22: =300/89.7 -> 3.3444816 | AM22: =SUM(AE22:AL22) -> 12.263099 | AO22: =SUM(W22:Y22,AD22,AM22,AN22) -> 12.263099 | AR22: =U22-AO22 -> 247.66071
A23: 46022 | C23: ='ODOMETERS Tekrit'!J19 -> 568 | D23: 0.7486 | E23: ='Daily Tekrit'!$C23*'Daily Tekrit'!$D23 -> 425.2048 | F23: ='ODOMETERS Tekrit'!K19 -> 72 | G23: 0.7486 | H23: ='Daily Tekrit'!$F23*'Daily Tekrit'!$G23 -> 53.8992 | I23: ='Daily Tekrit'!$C23+'Daily Tekrit'!$F23 -> 640 | J23: ='Daily Tekrit'!$E23+'Daily Tekrit'!$H23 -> 479.104 | K23: ='ODOMETERS Tekrit'!L19 -> 237 | L23: 0.6973 | M23: ='Daily Tekrit'!$K23*'Daily Tekrit'!$L23 -> 165.2601 | U23: ='Daily Tekrit'!$J23+'Daily Tekrit'!$M23+SUM($N23:$T23) -> 644.3641 | X23: =9*0.7486 -> 6.7374 | AD23: =SUM(Z23:AC23) -> 0 | AH23: =5+700/89.7 -> 12.80379 | AJ23: =300/89.7 -> 3.3444816 | AM23: =SUM(AE23:AL23) -> 16.148272 | AO23: =SUM(W23:Y23,AD23,AM23,AN23) -> 22.885672 | AR23: =U23-AO23 -> 621.47843
A24: 46023 | C24: ='ODOMETERS Tekrit'!J20 -> 221 | D24: 0.7486 | E24: ='Daily Tekrit'!$C24*'Daily Tekrit'!$D24 -> 165.4406 | F24: ='ODOMETERS Tekrit'!K20 -> 243 | G24: 0.7486 | H24: ='Daily Tekrit'!$F24*'Daily Tekrit'!$G24 -> 181.9098 | I24: ='Daily Tekrit'!$C24+'Daily Tekrit'!$F24 -> 464 | J24: ='Daily Tekrit'!$E24+'Daily Tekrit'!$H24 -> 347.3504 | K24: ='ODOMETERS Tekrit'!L20 -> 385 | L24: 0.6973 | M24: ='Daily Tekrit'!$K24*'Daily Tekrit'!$L24 -> 268.4605 | T24: =75/89.7 -> 0.8361204 | U24: ='Daily Tekrit'!$J24+'Daily Tekrit'!$M24+SUM($N24:$T24) -> 616.64702 | X24: =10*0.7486 -> 7.486 | AD24: =SUM(Z24:AC24) -> 0 | AH24: =900/89.7 -> 10.033445 | AL24: =200/89.7+4 -> 6.2296544 | AM24: =SUM(AE24:AL24) -> 16.263099 | AO24: =SUM(W24:Y24,AD24,AM24,AN24) -> 23.749099 | AR24: =U24-AO24 -> 592.89792
A25: 46024 | C25: ='ODOMETERS Tekrit'!J21 -> 15 | D25: 0.7486 | E25: ='Daily Tekrit'!$C25*'Daily Tekrit'!$D25 -> 11.229 | F25: ='ODOMETERS Tekrit'!K21 -> 928 | G25: 0.7486 | H25: ='Daily Tekrit'!$F25*'Daily Tekrit'!$G25 -> 694.7008 | I25: ='Daily Tekrit'!$C25+'Daily Tekrit'!$F25 -> 943 | J25: ='Daily Tekrit'!$E25+'Daily Tekrit'!$H25 -> 705.9298 | K25: ='ODOMETERS Tekrit'!L21 -> 623 | L25: 0.6973 | M25: ='Daily Tekrit'!$K25*'Daily Tekrit'!$L25 -> 434.4179 | U25: ='Daily Tekrit'!$J25+'Daily Tekrit'!$M25+SUM($N25:$T25) -> 1140.3477 | W25: 139 | AD25: =SUM(Z25:AC25) -> 0 | AH25: =200/89.7 -> 2.2296544 | AM25: =SUM(AE25:AL25) -> 2.2296544 | AO25: =SUM(W25:Y25,AD25,AM25,AN25) -> 141.22965 | AR25: =U25-AO25 -> 999.11805
A26: 3-Jan and 4-Jan | C26: ='ODOMETERS Tekrit'!J22 -> 26 | D26: 0.7358 | E26: ='Daily Tekrit'!$C26*'Daily Tekrit'!$D26 -> 19.1308 | F26: ='ODOMETERS Tekrit'!K22 -> 1047 | G26: 0.7358 | H26: ='Daily Tekrit'!$F26*'Daily Tekrit'!$G26 -> 770.3826 | I26: ='Daily Tekrit'!$C26+'Daily Tekrit'!$F26 -> 1073 | J26: ='Daily Tekrit'!$E26+'Daily Tekrit'!$H26 -> 789.5134 | K26: ='ODOMETERS Tekrit'!L22 -> 391 | L26: 0.6895 | M26: ='Daily Tekrit'!$K26*'Daily Tekrit'!$L26 -> 269.5945 | U26: ='Daily Tekrit'!$J26+'Daily Tekrit'!$M26+SUM($N26:$T26) -> 1059.1079 | W26: 5 | AD26: =SUM(Z26:AC26) -> 0 | AM26: =SUM(AE26:AL26) -> 0 | AO26: =SUM(W26:Y26,AD26,AM26,AN26) -> 5 | AR26: =U26-AO26 -> 1054.1079
A27: 46027 | C27: ='ODOMETERS Tekrit'!J23 -> 137 | D27: 0.7358 | E27: ='Daily Tekrit'!$C27*'Daily Tekrit'!$D27 -> 100.8046 | F27: ='ODOMETERS Tekrit'!K23 -> 918 | G27: 0.7358 | H27: ='Daily Tekrit'!$F27*'Daily Tekrit'!$G27 -> 675.4644 | I27: ='Daily Tekrit'!$C27+'Daily Tekrit'!$F27 -> 1055 | J27: ='Daily Tekrit'!$E27+'Daily Tekrit'!$H27 -> 776.269 | K27: ='ODOMETERS Tekrit'!L23 -> 321 | L27: 0.6895 | M27: ='Daily Tekrit'!$K27*'Daily Tekrit'!$L27 -> 221.3295 | U27: ='Daily Tekrit'!$J27+'Daily Tekrit'!$M27+SUM($N27:$T27) -> 997.5985 | AD27: =SUM(Z27:AC27) -> 0 | AG27: 18.87 | AJ27: 6 | AM27: =SUM(AE27:AL27) -> 24.87 | AO27: =SUM(W27:Y27,AD27,AM27,AN27) -> 24.87 | AP27: Maintenance | AR27: =U27-AO27 -> 972.7285
A28: 46028 | C28: ='ODOMETERS Tekrit'!J24 -> 269 | D28: 0.7358 | E28: ='Daily Tekrit'!$C28*'Daily Tekrit'!$D28 -> 197.9302 | F28: ='ODOMETERS Tekrit'!K24 -> 383 | G28: 0.7358 | H28: ='Daily Tekrit'!$F28*'Daily Tekrit'!$G28 -> 281.8114 | I28: ='Daily Tekrit'!$C28+'Daily Tekrit'!$F28 -> 652 | J28: ='Daily Tekrit'!$E28+'Daily Tekrit'!$H28 -> 479.7416 | K28: ='ODOMETERS Tekrit'!L24 -> 214 | L28: 0.6895 | M28: ='Daily Tekrit'!$K28*'Daily Tekrit'!$L28 -> 147.553 | U28: ='Daily Tekrit'!$J28+'Daily Tekrit'!$M28+SUM($N28:$T28) -> 627.2946 | Y28: 15 | AD28: =SUM(Z28:AC28) -> 0 | AH28: 9.5 | AJ28: 5 | AL28: 114 | AM28: =SUM(AE28:AL28) -> 128.5 | AO28: =SUM(W28:Y28,AD28,AM28,AN28) -> 143.5 | AP28: Other: Maintenance | AR28: =U28-AO28 -> 483.7946
A29: 46029 | B29: Pre Price | C29: ='ODOMETERS Tekrit'!J25 -> 218 | D29: 0.7358 | E29: ='Daily Tekrit'!$C29*'Daily Tekrit'!$D29 -> 160.4044 | F29: ='ODOMETERS Tekrit'!K25 -> 35 | G29: 0.7358 | H29: ='Daily Tekrit'!$F29*'Daily Tekrit'!$G29 -> 25.753 | I29: ='Daily Tekrit'!$C29+'Daily Tekrit'!$F29 -> 253 | J29: ='Daily Tekrit'!$E29+'Daily Tekrit'!$H29 -> 186.1574 | K29: ='ODOMETERS Tekrit'!L25 -> 115 | L29: 0.6895 | M29: ='Daily Tekrit'!$K29*'Daily Tekrit'!$L29 -> 79.2925 | U29: ='Daily Tekrit'!$J29+'Daily Tekrit'!$M29+SUM($N29:$T29) -> 265.4499 | AD29: =SUM(Z29:AC29) -> 0 | AM29: =SUM(AE29:AL29) -> 0 | AO29: =SUM(W29:Y29,AD29,AM29,AN29) -> 0 | AR29: =U29-AO29 -> 265.4499
A30: 46030 | C30: ='ODOMETERS Tekrit'!J26 -> 575 | D30: 0.7291 | E30: ='Daily Tekrit'!$C30*'Daily Tekrit'!$D30 -> 419.2325 | F30: ='ODOMETERS Tekrit'!K26 -> 228 | G30: 0.7291 | H30: ='Daily Tekrit'!$F30*'Daily Tekrit'!$G30 -> 166.2348 | I30: ='Daily Tekrit'!$C30+'Daily Tekrit'!$F30 -> 803 | J30: ='Daily Tekrit'!$E30+'Daily Tekrit'!$H30 -> 585.4673 | K30: ='ODOMETERS Tekrit'!L26 -> 370 | L30: 0.6867 | M30: ='Daily Tekrit'!$K30*'Daily Tekrit'!$L30 -> 254.079 | S30: 95 | U30: ='Daily Tekrit'!$J30+'Daily Tekrit'!$M30+SUM($N30:$T30) -> 934.5463 | W30: 20 | AD30: =SUM(Z30:AC30) -> 0 | AM30: =SUM(AE30:AL30) -> 0 | AO30: =SUM(W30:Y30,AD30,AM30,AN30) -> 20 | AR30: =U30-AO30 -> 914.5463
A31: 46031 | B31: Pre Price | C31: ='ODOMETERS Tekrit'!J27 -> 154 | D31: 0.7291 | E31: ='Daily Tekrit'!$C31*'Daily Tekrit'!$D31 -> 112.2814 | F31: ='ODOMETERS Tekrit'!K27 -> 256 | G31: 0.7291 | H31: ='Daily Tekrit'!$F31*'Daily Tekrit'!$G31 -> 186.6496 | I31: ='Daily Tekrit'!$C31+'Daily Tekrit'!$F31 -> 410 | J31: ='Daily Tekrit'!$E31+'Daily Tekrit'!$H31 -> 298.931 | K31: ='ODOMETERS Tekrit'!L27 -> 269 | L31: 0.6867 | M31: ='Daily Tekrit'!$K31*'Daily Tekrit'!$L31 -> 184.7223 | U31: ='Daily Tekrit'!$J31+'Daily Tekrit'!$M31+SUM($N31:$T31) -> 483.6533 | W31: =1400/89.7 -> 15.607581 | AD31: =SUM(Z31:AC31) -> 0 | AH31: =850/89.7 -> 9.4760312 | AM31: =SUM(AE31:AL31) -> 9.4760312 | AO31: =SUM(W31:Y31,AD31,AM31,AN31) -> 25.083612 | AR31: =U31-AO31 -> 458.56969
A32: 46032 | C32: ='ODOMETERS Tekrit'!J28 -> 234 | D32: 0.728 | E32: ='Daily Tekrit'!$C32*'Daily Tekrit'!$D32 -> 170.352 | F32: ='ODOMETERS Tekrit'!K28 -> 564 | G32: 0.728 | H32: ='Daily Tekrit'!$F32*'Daily Tekrit'!$G32 -> 410.592 | I32: ='Daily Tekrit'!$C32+'Daily Tekrit'!$F32 -> 798 | J32: ='Daily Tekrit'!$E32+'Daily Tekrit'!$H32 -> 580.944 | K32: ='ODOMETERS Tekrit'!L28 -> 1353 | L32: 0.6851 | M32: ='Daily Tekrit'!$K32*'Daily Tekrit'!$L32 -> 926.9403 | U32: ='Daily Tekrit'!$J32+'Daily Tekrit'!$M32+SUM($N32:$T32) -> 1507.8843 | W32: =5.57+500 -> 505.57 | Y32: 1 | AD32: =SUM(Z32:AC32) -> 0 | AF32: 20 | AG32: 31.3 | AM32: =SUM(AE32:AL32) -> 51.3 | AO32: =SUM(W32:Y32,AD32,AM32,AN32) -> 557.87 | AR32: =U32-AO32 -> 950.0143
A33: 46033 | C33: ='ODOMETERS Tekrit'!J29 -> 77 | D33: 0.728 | E33: ='Daily Tekrit'!$C33*'Daily Tekrit'!$D33 -> 56.056 | F33: ='ODOMETERS Tekrit'!K29 -> 320 | G33: 0.728 | H33: ='Daily Tekrit'!$F33*'Daily Tekrit'!$G33 -> 232.96 | I33: ='Daily Tekrit'!$C33+'Daily Tekrit'!$F33 -> 397 | J33: ='Daily Tekrit'!$E33+'Daily Tekrit'!$H33 -> 289.016 | K33: ='ODOMETERS Tekrit'!L29 -> 182 | L33: 0.6851 | M33: ='Daily Tekrit'!$K33*'Daily Tekrit'!$L33 -> 124.6882 | U33: ='Daily Tekrit'!$J33+'Daily Tekrit'!$M33+SUM($N33:$T33) -> 413.7042 | Y33: 2 | AD33: =SUM(Z33:AC33) -> 0 | AH33: =950/89.7 -> 10.590858 | AM33: =SUM(AE33:AL33) -> 10.590858 | AO33: =SUM(W33:Y33,AD33,AM33,AN33) -> 12.590858 | AR33: =U33-AO33 -> 401.11334
A34: 46034 | C34: ='ODOMETERS Tekrit'!J30 -> 73 | D34: 0.728 | E34: ='Daily Tekrit'!$C34*'Daily Tekrit'!$D34 -> 53.144 | F34: ='ODOMETERS Tekrit'!K30 -> 521 | G34: 0.728 | H34: ='Daily Tekrit'!$F34*'Daily Tekrit'!$G34 -> 379.288 | I34: ='Daily Tekrit'!$C34+'Daily Tekrit'!$F34 -> 594 | J34: ='Daily Tekrit'!$E34+'Daily Tekrit'!$H34 -> 432.432 | K34: ='ODOMETERS Tekrit'!L30 -> 517 | L34: 0.6851 | M34: ='Daily Tekrit'!$K34*'Daily Tekrit'!$L34 -> 354.1967 | U34: ='Daily Tekrit'!$J34+'Daily Tekrit'!$M34+SUM($N34:$T34) -> 786.6287 | W34: 102.87 | Y34: 1 | AD34: =SUM(Z34:AC34) -> 0 | AH34: 14 | AM34: =SUM(AE34:AL34) -> 14 | AO34: =SUM(W34:Y34,AD34,AM34,AN34) -> 117.87 | AR34: =U34-AO34 -> 668.7587
A35: 46035 | B35: Pre Price | C35: ='ODOMETERS Tekrit'!J31 -> 3 | D35: 0.728 | E35: ='Daily Tekrit'!$C35*'Daily Tekrit'!$D35 -> 2.184 | F35: ='ODOMETERS Tekrit'!K31 -> 301 | G35: 0.728 | H35: ='Daily Tekrit'!$F35*'Daily Tekrit'!$G35 -> 219.128 | I35: ='Daily Tekrit'!$C35+'Daily Tekrit'!$F35 -> 304 | J35: ='Daily Tekrit'!$E35+'Daily Tekrit'!$H35 -> 221.312 | K35: ='ODOMETERS Tekrit'!L31 -> 173 | L35: 0.6851 | M35: ='Daily Tekrit'!$K35*'Daily Tekrit'!$L35 -> 118.5223 | U35: ='Daily Tekrit'!$J35+'Daily Tekrit'!$M35+SUM($N35:$T35) -> 339.8343 | W35: 6 | AD35: =SUM(Z35:AC35) -> 0 | AH35: =400/89.7 -> 4.4593088 | AM35: =SUM(AE35:AL35) -> 4.4593088 | AO35: =SUM(W35:Y35,AD35,AM35,AN35) -> 10.459309 | AR35: =U35-AO35 -> 329.37499
A36: 46035 | B36: Post Price | C36: ='ODOMETERS Tekrit'!J32 -> 21 | D36: 0.7313 | E36: ='Daily Tekrit'!$C36*'Daily Tekrit'!$D36 -> 15.3573 | F36: ='ODOMETERS Tekrit'!K32 -> 296 | G36: 0.7313 | H36: ='Daily Tekrit'!$F36*'Daily Tekrit'!$G36 -> 216.4648 | I36: ='Daily Tekrit'!$C36+'Daily Tekrit'!$F36 -> 317 | J36: ='Daily Tekrit'!$E36+'Daily Tekrit'!$H36 -> 231.8221 | K36: ='ODOMETERS Tekrit'!L32 -> 225 | L36: 0.6867 | M36: ='Daily Tekrit'!$K36*'Daily Tekrit'!$L36 -> 154.5075 | U36: ='Daily Tekrit'!$J36+'Daily Tekrit'!$M36+SUM($N36:$T36) -> 386.3296 | W36: =1800/89.7 -> 20.06689 | AD36: =SUM(Z36:AC36) -> 0 | AH36: =500/89.7 -> 5.574136 | AJ36: =300/89.7 -> 3.3444816 | AM36: =SUM(AE36:AL36) -> 8.9186176 | AO36: =SUM(W36:Y36,AD36,AM36,AN36) -> 28.985507 | AR36: =U36-AO36 -> 357.34409
A37: 46036 | C37: ='ODOMETERS Tekrit'!J33 -> 574 | D37: 0.7313 | E37: ='Daily Tekrit'!$C37*'Daily Tekrit'!$D37 -> 419.7662 | F37: ='ODOMETERS Tekrit'!K33 -> 135 | G37: 0.7313 | H37: ='Daily Tekrit'!$F37*'Daily Tekrit'!$G37 -> 98.7255 | I37: ='Daily Tekrit'!$C37+'Daily Tekrit'!$F37 -> 709 | J37: ='Daily Tekrit'!$E37+'Daily Tekrit'!$H37 -> 518.4917 | K37: ='ODOMETERS Tekrit'!L33 -> 389 | L37: 0.6867 | M37: ='Daily Tekrit'!$K37*'Daily Tekrit'!$L37 -> 267.1263 | S37: 5 | U37: ='Daily Tekrit'!$J37+'Daily Tekrit'!$M37+SUM($N37:$T37) -> 790.618 | W37: 26 | AD37: =SUM(Z37:AC37) -> 0 | AM37: =SUM(AE37:AL37) -> 0 | AO37: =SUM(W37:Y37,AD37,AM37,AN37) -> 26 | AR37: =U37-AO37 -> 764.618
A38: 46037 | C38: ='ODOMETERS Tekrit'!J34 -> 352 | D38: 0.7313 | E38: ='Daily Tekrit'!$C38*'Daily Tekrit'!$D38 -> 257.4176 | F38: ='ODOMETERS Tekrit'!K34 -> 51 | G38: 0.7313 | H38: ='Daily Tekrit'!$F38*'Daily Tekrit'!$G38 -> 37.2963 | I38: ='Daily Tekrit'!$C38+'Daily Tekrit'!$F38 -> 403 | J38: ='Daily Tekrit'!$E38+'Daily Tekrit'!$H38 -> 294.7139 | K38: ='ODOMETERS Tekrit'!L34 -> 243 | L38: 0.6867 | M38: ='Daily Tekrit'!$K38*'Daily Tekrit'!$L38 -> 166.8681 | U38: ='Daily Tekrit'!$J38+'Daily Tekrit'!$M38+SUM($N38:$T38) -> 461.582 | W38: 33.37 | Y38: 5 | AD38: =SUM(Z38:AC38) -> 0 | AG38: 2 | AM38: =SUM(AE38:AL38) -> 2 | AO38: =SUM(W38:Y38,AD38,AM38,AN38) -> 40.37 | AR38: =U38-AO38 -> 421.212
A39: 46038 | B39: Pre Price | C39: ='ODOMETERS Tekrit'!J35 -> 84 | D39: 0.7313 | E39: ='Daily Tekrit'!$C39*'Daily Tekrit'!$D39 -> 61.4292 | F39: ='ODOMETERS Tekrit'!K35 -> 106 | G39: 0.7313 | H39: ='Daily Tekrit'!$F39*'Daily Tekrit'!$G39 -> 77.5178 | I39: ='Daily Tekrit'!$C39+'Daily Tekrit'!$F39 -> 190 | J39: ='Daily Tekrit'!$E39+'Daily Tekrit'!$H39 -> 138.947 | K39: ='ODOMETERS Tekrit'!L35 -> 92 | L39: 0.6867 | M39: ='Daily Tekrit'!$K39*'Daily Tekrit'!$L39 -> 63.1764 | U39: ='Daily Tekrit'!$J39+'Daily Tekrit'!$M39+SUM($N39:$T39) -> 202.1234 | W39: =500/89.7 -> 5.574136 | AD39: =SUM(Z39:AC39) -> 0 | AM39: =SUM(AE39:AL39) -> 0 | AO39: =SUM(W39:Y39,AD39,AM39,AN39) -> 5.574136 | AR39: =U39-AO39 -> 196.54926
A40: 46038 | B40: Post Price | C40: ='ODOMETERS Tekrit'!J36 -> 145 | D40: 0.738 | E40: ='Daily Tekrit'!$C40*'Daily Tekrit'!$D40 -> 107.01 | F40: ='ODOMETERS Tekrit'!K36 -> 92 | G40: 0.738 | H40: ='Daily Tekrit'!$F40*'Daily Tekrit'!$G40 -> 67.896 | I40: ='Daily Tekrit'!$C40+'Daily Tekrit'!$F40 -> 237 | J40: ='Daily Tekrit'!$E40+'Daily Tekrit'!$H40 -> 174.906 | K40: ='ODOMETERS Tekrit'!L36 -> 297 | L40: 0.6923 | M40: ='Daily Tekrit'!$K40*'Daily Tekrit'!$L40 -> 205.6131 | U40: ='Daily Tekrit'!$J40+'Daily Tekrit'!$M40+SUM($N40:$T40) -> 380.5191 | AD40: =SUM(Z40:AC40) -> 0 | AM40: =SUM(AE40:AL40) -> 0 | AO40: =SUM(W40:Y40,AD40,AM40,AN40) -> 0 | AR40: =U40-AO40 -> 380.5191
A41: 46039 | C41: ='ODOMETERS Tekrit'!J37 -> 292 | D41: 0.738 | E41: ='Daily Tekrit'!$C41*'Daily Tekrit'!$D41 -> 215.496 | F41: ='ODOMETERS Tekrit'!K37 -> 258 | G41: 0.738 | H41: ='Daily Tekrit'!$F41*'Daily Tekrit'!$G41 -> 190.404 | I41: ='Daily Tekrit'!$C41+'Daily Tekrit'!$F41 -> 550 | J41: ='Daily Tekrit'!$E41+'Daily Tekrit'!$H41 -> 405.9 | K41: ='ODOMETERS Tekrit'!L37 -> 408 | L41: 0.6923 | M41: ='Daily Tekrit'!$K41*'Daily Tekrit'!$L41 -> 282.4584 | U41: ='Daily Tekrit'!$J41+'Daily Tekrit'!$M41+SUM($N41:$T41) -> 688.3584 | W41: =1400/89.7 -> 15.607581 | AD41: =SUM(Z41:AC41) -> 0 | AH41: =500/89.7+15 -> 20.574136 | AM41: =SUM(AE41:AL41) -> 20.574136 | AO41: =SUM(W41:Y41,AD41,AM41,AN41) -> 36.181717 | AR41: =U41-AO41 -> 652.17668
A42: 46040 | C42: ='ODOMETERS Tekrit'!J38 -> 327 | D42: 0.738 | E42: ='Daily Tekrit'!$C42*'Daily Tekrit'!$D42 -> 241.326 | F42: ='ODOMETERS Tekrit'!K38 -> 289 | G42: 0.738 | H42: ='Daily Tekrit'!$F42*'Daily Tekrit'!$G42 -> 213.282 | I42: ='Daily Tekrit'!$C42+'Daily Tekrit'!$F42 -> 616 | J42: ='Daily Tekrit'!$E42+'Daily Tekrit'!$H42 -> 454.608 | K42: ='ODOMETERS Tekrit'!L38 -> 430 | L42: 0.6923 | M42: ='Daily Tekrit'!$K42*'Daily Tekrit'!$L42 -> 297.689 | U42: ='Daily Tekrit'!$J42+'Daily Tekrit'!$M42+SUM($N42:$T42) -> 752.297 | W42: 3 | AD42: =SUM(Z42:AC42) -> 0 | AF42: 5 | AM42: =SUM(AE42:AL42) -> 5 | AO42: =SUM(W42:Y42,AD42,AM42,AN42) -> 8 | AR42: =U42-AO42 -> 744.297
A43: 46041 | C43: ='ODOMETERS Tekrit'!J39 -> 270 | D43: 0.738 | E43: ='Daily Tekrit'!$C43*'Daily Tekrit'!$D43 -> 199.26 | F43: ='ODOMETERS Tekrit'!K39 -> 179 | G43: 0.738 | H43: ='Daily Tekrit'!$F43*'Daily Tekrit'!$G43 -> 132.102 | I43: ='Daily Tekrit'!$C43+'Daily Tekrit'!$F43 -> 449 | J43: ='Daily Tekrit'!$E43+'Daily Tekrit'!$H43 -> 331.362 | K43: ='ODOMETERS Tekrit'!L39 -> 258 | L43: 0.6923 | M43: ='Daily Tekrit'!$K43*'Daily Tekrit'!$L43 -> 178.6134 | U43: ='Daily Tekrit'!$J43+'Daily Tekrit'!$M43+SUM($N43:$T43) -> 509.9754 | W43: =20*0.6923 -> 13.846 | AD43: =SUM(Z43:AC43) -> 0 | AH43: =500/89.7 -> 5.574136 | AM43: =SUM(AE43:AL43) -> 5.574136 | AO43: =SUM(W43:Y43,AD43,AM43,AN43) -> 19.420136 | AR43: =U43-AO43 -> 490.55526
A44: 46042 | B44: Pre Price | C44: ='ODOMETERS Tekrit'!J40 -> 144 | D44: 0.738 | E44: ='Daily Tekrit'!$C44*'Daily Tekrit'!$D44 -> 106.272 | F44: ='ODOMETERS Tekrit'!K40 -> 140 | G44: 0.738 | H44: ='Daily Tekrit'!$F44*'Daily Tekrit'!$G44 -> 103.32 | I44: ='Daily Tekrit'!$C44+'Daily Tekrit'!$F44 -> 284 | J44: ='Daily Tekrit'!$E44+'Daily Tekrit'!$H44 -> 209.592 | K44: ='ODOMETERS Tekrit'!L40 -> 157 | L44: 0.6923 | M44: ='Daily Tekrit'!$K44*'Daily Tekrit'!$L44 -> 108.6911 | U44: ='Daily Tekrit'!$J44+'Daily Tekrit'!$M44+SUM($N44:$T44) -> 318.2831 | AD44: =SUM(Z44:AC44) -> 0 | AM44: =SUM(AE44:AL44) -> 0 | AO44: =SUM(W44:Y44,AD44,AM44,AN44) -> 0 | AR44: =U44-AO44 -> 318.2831
A45: 46042 | B45: Post Price | C45: ='ODOMETERS Tekrit'!J41 -> 243 | D45: 0.7391 | E45: ='Daily Tekrit'!$C45*'Daily Tekrit'!$D45 -> 179.6013 | F45: ='ODOMETERS Tekrit'!K41 -> 93 | G45: 0.7391 | H45: ='Daily Tekrit'!$F45*'Daily Tekrit'!$G45 -> 68.7363 | I45: ='Daily Tekrit'!$C45+'Daily Tekrit'!$F45 -> 336 | J45: ='Daily Tekrit'!$E45+'Daily Tekrit'!$H45 -> 248.3376 | K45: ='ODOMETERS Tekrit'!L41 -> 306 | L45: 0.6957 | M45: ='Daily Tekrit'!$K45*'Daily Tekrit'!$L45 -> 212.8842 | U45: ='Daily Tekrit'!$J45+'Daily Tekrit'!$M45+SUM($N45:$T45) -> 461.2218 | W45: =500/89.7 -> 5.574136 | AD45: =SUM(Z45:AC45) -> 0 | AJ45: =300/89.7 -> 3.3444816 | AM45: =SUM(AE45:AL45) -> 3.3444816 | AO45: =SUM(W45:Y45,AD45,AM45,AN45) -> 8.9186176 | AR45: =U45-AO45 -> 452.30318
A46: 46043 | C46: ='ODOMETERS Tekrit'!J42 -> 254 | D46: 0.7391 | E46: ='Daily Tekrit'!$C46*'Daily Tekrit'!$D46 -> 187.7314 | F46: ='ODOMETERS Tekrit'!K42 -> 234 | G46: 0.7391 | H46: ='Daily Tekrit'!$F46*'Daily Tekrit'!$G46 -> 172.9494 | I46: ='Daily Tekrit'!$C46+'Daily Tekrit'!$F46 -> 488 | J46: ='Daily Tekrit'!$E46+'Daily Tekrit'!$H46 -> 360.6808 | K46: ='ODOMETERS Tekrit'!L42 -> 660 | L46: 0.6957 | M46: ='Daily Tekrit'!$K46*'Daily Tekrit'!$L46 -> 459.162 | U46: ='Daily Tekrit'!$J46+'Daily Tekrit'!$M46+SUM($N46:$T46) -> 819.8428 | W46: =26 -> 26 | AD46: =SUM(Z46:AC46) -> 0 | AF46: 10 | AH46: =500/89.7+3 -> 8.574136 | AM46: =SUM(AE46:AL46) -> 18.574136 | AO46: =SUM(W46:Y46,AD46,AM46,AN46) -> 44.574136 | AR46: =U46-AO46 -> 775.26866
A47: 46044 | C47: ='ODOMETERS Tekrit'!J43 -> 400 | D47: 0.7391 | E47: ='Daily Tekrit'!$C47*'Daily Tekrit'!$D47 -> 295.64 | F47: ='ODOMETERS Tekrit'!K43 -> 185 | G47: 0.7391 | H47: ='Daily Tekrit'!$F47*'Daily Tekrit'!$G47 -> 136.7335 | I47: ='Daily Tekrit'!$C47+'Daily Tekrit'!$F47 -> 585 | J47: ='Daily Tekrit'!$E47+'Daily Tekrit'!$H47 -> 432.3735 | K47: ='ODOMETERS Tekrit'!L43 -> 367 | L47: 0.6957 | M47: ='Daily Tekrit'!$K47*'Daily Tekrit'!$L47 -> 255.3219 | S47: 10 | U47: ='Daily Tekrit'!$J47+'Daily Tekrit'!$M47+SUM($N47:$T47) -> 697.6954 | W47: =1000000/89700 -> 11.148272 | AD47: =SUM(Z47:AC47) -> 0 | AM47: =SUM(AE47:AL47) -> 0 | AO47: =SUM(W47:Y47,AD47,AM47,AN47) -> 11.148272 | AR47: =U47-AO47 -> 686.54713
A48: 46045 | B48: Pre Price | C48: ='ODOMETERS Tekrit'!J44 -> 141 | D48: 0.7391 | E48: ='Daily Tekrit'!$C48*'Daily Tekrit'!$D48 -> 104.2131 | F48: ='ODOMETERS Tekrit'!K44 -> 189 | G48: 0.7391 | H48: ='Daily Tekrit'!$F48*'Daily Tekrit'!$G48 -> 139.6899 | I48: ='Daily Tekrit'!$C48+'Daily Tekrit'!$F48 -> 330 | J48: ='Daily Tekrit'!$E48+'Daily Tekrit'!$H48 -> 243.903 | K48: ='ODOMETERS Tekrit'!L44 -> 136 | L48: 0.6957 | M48: ='Daily Tekrit'!$K48*'Daily Tekrit'!$L48 -> 94.6152 | U48: ='Daily Tekrit'!$J48+'Daily Tekrit'!$M48+SUM($N48:$T48) -> 338.5182 | AD48: =SUM(Z48:AC48) -> 0 | AH48: =500/89.7 -> 5.574136 | AM48: =SUM(AE48:AL48) -> 5.574136 | AO48: =SUM(W48:Y48,AD48,AM48,AN48) -> 5.574136 | AR48: =U48-AO48 -> 332.94406
A49: 46045 | B49: Post Price | C49: ='ODOMETERS Tekrit'!J45 -> 99 | D49: 0.7441 | E49: ='Daily Tekrit'!$C49*'Daily Tekrit'!$D49 -> 73.6659 | F49: ='ODOMETERS Tekrit'!K45 -> 137 | G49: 0.7441 | H49: ='Daily Tekrit'!$F49*'Daily Tekrit'!$G49 -> 101.9417 | I49: ='Daily Tekrit'!$C49+'Daily Tekrit'!$F49 -> 236 | J49: ='Daily Tekrit'!$E49+'Daily Tekrit'!$H49 -> 175.6076 | K49: ='ODOMETERS Tekrit'!L45 -> 215 | L49: 0.7035 | M49: ='Daily Tekrit'!$K49*'Daily Tekrit'!$L49 -> 151.2525 | U49: ='Daily Tekrit'!$J49+'Daily Tekrit'!$M49+SUM($N49:$T49) -> 326.8601 | AD49: =SUM(Z49:AC49) -> 0 | AJ49: 3 | AM49: =SUM(AE49:AL49) -> 3 | AO49: =SUM(W49:Y49,AD49,AM49,AN49) -> 3 | AR49: =U49-AO49 -> 323.8601
A50: 46046 | C50: ='ODOMETERS Tekrit'!J46 -> 254 | D50: 0.7441 | E50: ='Daily Tekrit'!$C50*'Daily Tekrit'!$D50 -> 189.0014 | F50: ='ODOMETERS Tekrit'!K46 -> 212 | G50: 0.7441 | H50: ='Daily Tekrit'!$F50*'Daily Tekrit'!$G50 -> 157.7492 | I50: ='Daily Tekrit'!$C50+'Daily Tekrit'!$F50 -> 466 | J50: ='Daily Tekrit'!$E50+'Daily Tekrit'!$H50 -> 346.7506 | K50: ='ODOMETERS Tekrit'!L46 -> 327 | L50: 0.7035 | M50: ='Daily Tekrit'!$K50*'Daily Tekrit'!$L50 -> 230.0445 | N50: =900/89.7 -> 10.033445 | S50: 14 | U50: ='Daily Tekrit'!$J50+'Daily Tekrit'!$M50+SUM($N50:$T50) -> 600.82854 | W50: =690/89.7 -> 7.6923077 | AD50: =SUM(Z50:AC50) -> 0 | AH50: 6 | AM50: =SUM(AE50:AL50) -> 6 | AO50: =SUM(W50:Y50,AD50,AM50,AN50) -> 13.692308 | AR50: =U50-AO50 -> 587.13624
A51: 46047 | C51: ='ODOMETERS Tekrit'!J47 -> 354 | D51: 0.7441 | E51: ='Daily Tekrit'!$C51*'Daily Tekrit'!$D51 -> 263.4114 | F51: ='ODOMETERS Tekrit'!K47 -> 152 | G51: 0.7441 | H51: ='Daily Tekrit'!$F51*'Daily Tekrit'!$G51 -> 113.1032 | I51: ='Daily Tekrit'!$C51+'Daily Tekrit'!$F51 -> 506 | J51: ='Daily Tekrit'!$E51+'Daily Tekrit'!$H51 -> 376.5146 | K51: ='ODOMETERS Tekrit'!L47 -> 458 | L51: 0.7035 | M51: ='Daily Tekrit'!$K51*'Daily Tekrit'!$L51 -> 322.203 | N51: =300/89.7 -> 3.3444816 | T51: =70/89.7 -> 0.78037904 | U51: ='Daily Tekrit'!$J51+'Daily Tekrit'!$M51+SUM($N51:$T51) -> 702.84246 | W51: =1000/89.7 -> 11.148272 | X51: =10*0.7441 -> 7.441 | Y51: -3 | AD51: =SUM(Z51:AC51) -> 0 | AM51: =SUM(AE51:AL51) -> 0 | AO51: =SUM(W51:Y51,AD51,AM51,AN51) -> 15.589272 | AR51: =U51-AO51 -> 687.25319
A52: 46048 | C52: ='ODOMETERS Tekrit'!J48 -> 417 | D52: 0.7441 | E52: ='Daily Tekrit'!$C52*'Daily Tekrit'!$D52 -> 310.2897 | F52: ='ODOMETERS Tekrit'!K48 -> 188 | G52: 0.7441 | H52: ='Daily Tekrit'!$F52*'Daily Tekrit'!$G52 -> 139.8908 | I52: ='Daily Tekrit'!$C52+'Daily Tekrit'!$F52 -> 605 | J52: ='Daily Tekrit'!$E52+'Daily Tekrit'!$H52 -> 450.1805 | K52: ='ODOMETERS Tekrit'!L48 -> 366 | L52: 0.7035 | M52: ='Daily Tekrit'!$K52*'Daily Tekrit'!$L52 -> 257.481 | S52: =500/89.7 -> 5.574136 | U52: ='Daily Tekrit'!$J52+'Daily Tekrit'!$M52+SUM($N52:$T52) -> 713.23564 | W52: =400/89.7 -> 4.4593088 | Y52: 8 | AD52: =SUM(Z52:AC52) -> 0 | AJ52: =300/89.7 -> 3.3444816 | AM52: =SUM(AE52:AL52) -> 3.3444816 | AO52: =SUM(W52:Y52,AD52,AM52,AN52) -> 15.80379 | AR52: =U52-AO52 -> 697.43185
A53: 46049 | B53: Pre Price | C53: ='ODOMETERS Tekrit'!J49 -> 318 | D53: 0.7441 | E53: ='Daily Tekrit'!$C53*'Daily Tekrit'!$D53 -> 236.6238 | F53: ='ODOMETERS Tekrit'!K49 -> 112 | G53: 0.7441 | H53: ='Daily Tekrit'!$F53*'Daily Tekrit'!$G53 -> 83.3392 | I53: ='Daily Tekrit'!$C53+'Daily Tekrit'!$F53 -> 430 | J53: ='Daily Tekrit'!$E53+'Daily Tekrit'!$H53 -> 319.963 | K53: ='ODOMETERS Tekrit'!L49 -> 115 | L53: 0.7035 | M53: ='Daily Tekrit'!$K53*'Daily Tekrit'!$L53 -> 80.9025 | S53: =1000/89.7 -> 11.148272 | U53: ='Daily Tekrit'!$J53+'Daily Tekrit'!$M53+SUM($N53:$T53) -> 412.01377 | AD53: =SUM(Z53:AC53) -> 0 | AH53: =560/89.7 -> 6.2430323 | AM53: =SUM(AE53:AL53) -> 6.2430323 | AO53: =SUM(W53:Y53,AD53,AM53,AN53) -> 6.2430323 | AR53: =U53-AO53 -> 405.77074
A54: 46049 | B54: Post Price | C54: ='ODOMETERS Tekrit'!J50 -> 173 | D54: 0.748 | E54: ='Daily Tekrit'!$C54*'Daily Tekrit'!$D54 -> 129.404 | F54: ='ODOMETERS Tekrit'!K50 -> 41 | G54: 0.748 | H54: ='Daily Tekrit'!$F54*'Daily Tekrit'!$G54 -> 30.668 | I54: ='Daily Tekrit'!$C54+'Daily Tekrit'!$F54 -> 214 | J54: ='Daily Tekrit'!$E54+'Daily Tekrit'!$H54 -> 160.072 | K54: ='ODOMETERS Tekrit'!L50 -> 271 | L54: 0.7085 | M54: ='Daily Tekrit'!$K54*'Daily Tekrit'!$L54 -> 192.0035 | U54: ='Daily Tekrit'!$J54+'Daily Tekrit'!$M54+SUM($N54:$T54) -> 352.0755 | AD54: =SUM(Z54:AC54) -> 0 | AM54: =SUM(AE54:AL54) -> 0 | AO54: =SUM(W54:Y54,AD54,AM54,AN54) -> 0 | AR54: =U54-AO54 -> 352.0755
A55: 46050 | C55: ='ODOMETERS Tekrit'!J51 -> 399 | D55: 0.748 | E55: ='Daily Tekrit'!$C55*'Daily Tekrit'!$D55 -> 298.452 | F55: ='ODOMETERS Tekrit'!K51 -> 107 | G55: 0.748 | H55: ='Daily Tekrit'!$F55*'Daily Tekrit'!$G55 -> 80.036 | I55: ='Daily Tekrit'!$C55+'Daily Tekrit'!$F55 -> 506 | J55: ='Daily Tekrit'!$E55+'Daily Tekrit'!$H55 -> 378.488 | K55: ='ODOMETERS Tekrit'!L51 -> 441 | L55: 0.7085 | M55: ='Daily Tekrit'!$K55*'Daily Tekrit'!$L55 -> 312.4485 | N55: =300/89.7 -> 3.3444816 | U55: ='Daily Tekrit'!$J55+'Daily Tekrit'!$M55+SUM($N55:$T55) -> 694.28098 | W55: =5+500/89.7 -> 10.574136 | X55: =180*0.7085 -> 127.53 | AD55: =SUM(Z55:AC55) -> 0 | AJ55: =2000/89.7 -> 22.296544 | AM55: =SUM(AE55:AL55) -> 22.296544 | AO55: =SUM(W55:Y55,AD55,AM55,AN55) -> 160.40068 | AR55: =U55-AO55 -> 533.8803
A56: 46051 | C56: ='ODOMETERS Tekrit'!J52 -> 388 | D56: 0.748 | E56: ='Daily Tekrit'!$C56*'Daily Tekrit'!$D56 -> 290.224 | F56: ='ODOMETERS Tekrit'!K52 -> 219 | G56: 0.748 | H56: ='Daily Tekrit'!$F56*'Daily Tekrit'!$G56 -> 163.812 | I56: ='Daily Tekrit'!$C56+'Daily Tekrit'!$F56 -> 607 | J56: ='Daily Tekrit'!$E56+'Daily Tekrit'!$H56 -> 454.036 | K56: ='ODOMETERS Tekrit'!L52 -> 327 | L56: 0.7085 | M56: ='Daily Tekrit'!$K56*'Daily Tekrit'!$L56 -> 231.6795 | U56: ='Daily Tekrit'!$J56+'Daily Tekrit'!$M56+SUM($N56:$T56) -> 685.7155 | W56: =11+10 -> 21 | Y56: 1 | AD56: =SUM(Z56:AC56) -> 0 | AL56: =200/89.7+3 -> 5.2296544 | AM56: =SUM(AE56:AL56) -> 5.2296544 | AO56: =SUM(W56:Y56,AD56,AM56,AN56) -> 27.229654 | AR56: =U56-AO56 -> 658.48585
A57: 46052 | B57: Pre Price | C57: ='ODOMETERS Tekrit'!J53 -> 213 | D57: 0.748 | E57: ='Daily Tekrit'!$C57*'Daily Tekrit'!$D57 -> 159.324 | F57: ='ODOMETERS Tekrit'!K53 -> 194 | G57: 0.748 | H57: ='Daily Tekrit'!$F57*'Daily Tekrit'!$G57 -> 145.112 | I57: ='Daily Tekrit'!$C57+'Daily Tekrit'!$F57 -> 407 | J57: ='Daily Tekrit'!$E57+'Daily Tekrit'!$H57 -> 304.436 | K57: ='ODOMETERS Tekrit'!L53 -> 538 | L57: 0.7085 | M57: ='Daily Tekrit'!$K57*'Daily Tekrit'!$L57 -> 381.173 | T57: =33+10 -> 43 | U57: ='Daily Tekrit'!$J57+'Daily Tekrit'!$M57+SUM($N57:$T57) -> 728.609 | W57: =1000/89.7 -> 11.148272 | X57: =400*0.7085+45*0.748 -> 317.06 | AD57: =SUM(Z57:AC57) -> 0 | AM57: =SUM(AE57:AL57) -> 0 | AO57: =SUM(W57:Y57,AD57,AM57,AN57) -> 328.20827 | AR57: =U57-AO57 -> 400.40073
A58: 46052 | B58: Post Price | C58: ='ODOMETERS Tekrit'!J54 -> 157 | D58: 0.7698 | E58: ='Daily Tekrit'!$C58*'Daily Tekrit'!$D58 -> 120.8586 | F58: ='ODOMETERS Tekrit'!K54 -> 150 | G58: 0.7698 | H58: ='Daily Tekrit'!$F58*'Daily Tekrit'!$G58 -> 115.47 | I58: ='Daily Tekrit'!$C58+'Daily Tekrit'!$F58 -> 307 | J58: ='Daily Tekrit'!$E58+'Daily Tekrit'!$H58 -> 236.3286 | K58: ='ODOMETERS Tekrit'!L54 -> 209 | L58: 0.7202 | M58: ='Daily Tekrit'!$K58*'Daily Tekrit'!$L58 -> 150.5218 | T58: 1 | U58: ='Daily Tekrit'!$J58+'Daily Tekrit'!$M58+SUM($N58:$T58) -> 387.8504 | W58: 20 | X58: 7.7 | Y58: -1 | AD58: =SUM(Z58:AC58) -> 0 | AH58: 1 | AJ58: 3 | AM58: =SUM(AE58:AL58) -> 4 | AO58: =SUM(W58:Y58,AD58,AM58,AN58) -> 30.7 | AR58: =U58-AO58 -> 357.1504
A59: 46053 | C59: ='ODOMETERS Tekrit'!J55 -> 386 | D59: 0.7698 | E59: ='Daily Tekrit'!$C59*'Daily Tekrit'!$D59 -> 297.1428 | F59: ='ODOMETERS Tekrit'!K55 -> 407 | G59: 0.7698 | H59: ='Daily Tekrit'!$F59*'Daily Tekrit'!$G59 -> 313.3086 | I59: ='Daily Tekrit'!$C59+'Daily Tekrit'!$F59 -> 793 | J59: ='Daily Tekrit'!$E59+'Daily Tekrit'!$H59 -> 610.4514 | K59: ='ODOMETERS Tekrit'!L55 -> 423 | L59: 0.7202 | M59: ='Daily Tekrit'!$K59*'Daily Tekrit'!$L59 -> 304.6446 | N59: =300/89.7 -> 3.3444816 | S59: 42 | T59: 20 | U59: ='Daily Tekrit'!$J59+'Daily Tekrit'!$M59+SUM($N59:$T59) -> 980.44048 | X59: =180*0.7202+20*0.7202 -> 144.04 | AD59: =SUM(Z59:AC59) -> 0 | AH59: =300/89.7 -> 3.3444816 | AM59: =SUM(AE59:AL59) -> 3.3444816 | AO59: =SUM(W59:Y59,AD59,AM59,AN59) -> 147.38448 | AR59: =U59-AO59 -> 833.056
A60: 46054 | C60: ='ODOMETERS Tekrit'!J56 -> 265 | D60: 0.7698 | E60: ='Daily Tekrit'!$C60*'Daily Tekrit'!$D60 -> 203.997 | F60: ='ODOMETERS Tekrit'!K56 -> 192 | G60: 0.7698 | H60: ='Daily Tekrit'!$F60*'Daily Tekrit'!$G60 -> 147.8016 | I60: ='Daily Tekrit'!$C60+'Daily Tekrit'!$F60 -> 457 | J60: ='Daily Tekrit'!$E60+'Daily Tekrit'!$H60 -> 351.7986 | K60: ='ODOMETERS Tekrit'!L56 -> 441 | L60: 0.7202 | M60: ='Daily Tekrit'!$K60*'Daily Tekrit'!$L60 -> 317.6082 | N60: =300/89.7 -> 3.3444816 | S60: 46 | T60: =650/89.7 -> 7.2463768 | U60: ='Daily Tekrit'!$J60+'Daily Tekrit'!$M60+SUM($N60:$T60) -> 725.99766 | W60: =500/89.7 -> 5.574136 | X60: =97.5*0.7202 -> 70.2195 | AD60: =SUM(Z60:AC60) -> 0 | AH60: =300/89.7 -> 3.3444816 | AM60: =SUM(AE60:AL60) -> 3.3444816 | AO60: =SUM(W60:Y60,AD60,AM60,AN60) -> 79.138118 | AR60: =U60-AO60 -> 646.85954
A61: 46055 | C61: ='ODOMETERS Tekrit'!J57 -> 643 | D61: 0.7698 | E61: ='Daily Tekrit'!$C61*'Daily Tekrit'!$D61 -> 494.9814 | F61: ='ODOMETERS Tekrit'!K57 -> 324 | G61: 0.7698 | H61: ='Daily Tekrit'!$F61*'Daily Tekrit'!$G61 -> 249.4152 | I61: ='Daily Tekrit'!$C61+'Daily Tekrit'!$F61 -> 967 | J61: ='Daily Tekrit'!$E61+'Daily Tekrit'!$H61 -> 744.3966 | K61: ='ODOMETERS Tekrit'!L57 -> 504 | L61: 0.7202 | M61: ='Daily Tekrit'!$K61*'Daily Tekrit'!$L61 -> 362.9808 | U61: ='Daily Tekrit'!$J61+'Daily Tekrit'!$M61+SUM($N61:$T61) -> 1107.3774 | W61: =20+145+7.7+1500/89.7+500/89.7 -> 194.99654 | AD61: =SUM(Z61:AC61) -> 0 | AH61: =5+150/89.7 -> 6.6722408 | AM61: =SUM(AE61:AL61) -> 6.6722408 | AO61: =SUM(W61:Y61,AD61,AM61,AN61) -> 201.66878 | AR61: =U61-AO61 -> 905.70862
A62: 46056 | B62: Pre Price | C62: ='ODOMETERS Tekrit'!J58 -> 292 | D62: 0.7698 | E62: ='Daily Tekrit'!$C62*'Daily Tekrit'!$D62 -> 224.7816 | F62: ='ODOMETERS Tekrit'!K58 -> 161 | G62: 0.7698 | H62: ='Daily Tekrit'!$F62*'Daily Tekrit'!$G62 -> 123.9378 | I62: ='Daily Tekrit'!$C62+'Daily Tekrit'!$F62 -> 453 | J62: ='Daily Tekrit'!$E62+'Daily Tekrit'!$H62 -> 348.7194 | K62: ='ODOMETERS Tekrit'!L58 -> 65 | L62: 0.7202 | M62: ='Daily Tekrit'!$K62*'Daily Tekrit'!$L62 -> 46.813 | S62: 5.5 | U62: ='Daily Tekrit'!$J62+'Daily Tekrit'!$M62+SUM($N62:$T62) -> 401.0324 | W62: =36.7 -> 36.7 | Y62: -1 | AD62: =SUM(Z62:AC62) -> 0 | AM62: =SUM(AE62:AL62) -> 0 | AO62: =SUM(W62:Y62,AD62,AM62,AN62) -> 35.7 | AR62: =U62-AO62 -> 365.3324
A63: 46056 | B63: Post Price | C63: ='ODOMETERS Tekrit'!J59 -> 191 | D63: 0.7754 | E63: ='Daily Tekrit'!$C63*'Daily Tekrit'!$D63 -> 148.1014 | F63: ='ODOMETERS Tekrit'!K59 -> 80 | G63: 0.7754 | H63: ='Daily Tekrit'!$F63*'Daily Tekrit'!$G63 -> 62.032 | I63: ='Daily Tekrit'!$C63+'Daily Tekrit'!$F63 -> 271 | J63: ='Daily Tekrit'!$E63+'Daily Tekrit'!$H63 -> 210.1334 | K63: ='ODOMETERS Tekrit'!L59 -> 579 | L63: 0.7324 | M63: ='Daily Tekrit'!$K63*'Daily Tekrit'!$L63 -> 424.0596 | S63: =16.7*2+5.5 -> 38.9 | U63: ='Daily Tekrit'!$J63+'Daily Tekrit'!$M63+SUM($N63:$T63) -> 673.093 | W63: 17.8 | X63: 400 | AA63: 149 | AD63: =SUM(Z63:AC63) -> 149 | AM63: =SUM(AE63:AL63) -> 0 | AO63: =SUM(W63:Y63,AD63,AM63,AN63) -> 566.8 | AR63: =U63-AO63 -> 106.293
A64: 46057 | C64: ='ODOMETERS Tekrit'!J60 -> 338 | D64: 0.7754 | E64: ='Daily Tekrit'!$C64*'Daily Tekrit'!$D64 -> 262.0852 | F64: ='ODOMETERS Tekrit'!K60 -> 216 | G64: 0.7754 | H64: ='Daily Tekrit'!$F64*'Daily Tekrit'!$G64 -> 167.4864 | I64: ='Daily Tekrit'!$C64+'Daily Tekrit'!$F64 -> 554 | J64: ='Daily Tekrit'!$E64+'Daily Tekrit'!$H64 -> 429.5716 | K64: ='ODOMETERS Tekrit'!L60 -> 332 | L64: 0.7324 | M64: ='Daily Tekrit'!$K64*'Daily Tekrit'!$L64 -> 243.1568 | U64: ='Daily Tekrit'!$J64+'Daily Tekrit'!$M64+SUM($N64:$T64) -> 672.7284 | W64: 25 | X64: 65.9 | Y64: 1 | AA64: 136 | AD64: =SUM(Z64:AC64) -> 136 | AH64: 20 | AM64: =SUM(AE64:AL64) -> 20 | AO64: =SUM(W64:Y64,AD64,AM64,AN64) -> 247.9 | AR64: =U64-AO64 -> 424.8284
A65: 46058 | C65: ='ODOMETERS Tekrit'!J61 -> 484 | D65: 0.7754 | E65: ='Daily Tekrit'!$C65*'Daily Tekrit'!$D65 -> 375.2936 | F65: ='ODOMETERS Tekrit'!K61 -> 188 | G65: 0.7754 | H65: ='Daily Tekrit'!$F65*'Daily Tekrit'!$G65 -> 145.7752 | I65: ='Daily Tekrit'!$C65+'Daily Tekrit'!$F65 -> 672 | J65: ='Daily Tekrit'!$E65+'Daily Tekrit'!$H65 -> 521.0688 | K65: ='ODOMETERS Tekrit'!L61 -> 272 | L65: 0.7324 | M65: ='Daily Tekrit'!$K65*'Daily Tekrit'!$L65 -> 199.2128 | U65: ='Daily Tekrit'!$J65+'Daily Tekrit'!$M65+SUM($N65:$T65) -> 720.2816 | W65: 11 | AA65: 110 | AD65: =SUM(Z65:AC65) -> 110 | AM65: =SUM(AE65:AL65) -> 0 | AO65: =SUM(W65:Y65,AD65,AM65,AN65) -> 121 | AR65: =U65-AO65 -> 599.2816
A66: 46059 | B66: Pre Price | C66: ='ODOMETERS Tekrit'!J62 -> 162 | D66: 0.7754 | E66: ='Daily Tekrit'!$C66*'Daily Tekrit'!$D66 -> 125.6148 | F66: ='ODOMETERS Tekrit'!K62 -> 106 | G66: 0.7754 | H66: ='Daily Tekrit'!$F66*'Daily Tekrit'!$G66 -> 82.1924 | I66: ='Daily Tekrit'!$C66+'Daily Tekrit'!$F66 -> 268 | J66: ='Daily Tekrit'!$E66+'Daily Tekrit'!$H66 -> 207.8072 | K66: ='ODOMETERS Tekrit'!L62 -> 255 | L66: 0.7324 | M66: ='Daily Tekrit'!$K66*'Daily Tekrit'!$L66 -> 186.762 | U66: ='Daily Tekrit'!$J66+'Daily Tekrit'!$M66+SUM($N66:$T66) -> 394.5692 | X66: =180*0.7324 -> 131.832 | AA66: 50 | AD66: =SUM(Z66:AC66) -> 50 | AM66: =SUM(AE66:AL66) -> 0 | AO66: =SUM(W66:Y66,AD66,AM66,AN66) -> 181.832 | AR66: =U66-AO66 -> 212.7372
A67: 46059 | B67: Post Price | C67: ='ODOMETERS Tekrit'!J63 -> 140 | D67: 0.7821 | E67: ='Daily Tekrit'!$C67*'Daily Tekrit'!$D67 -> 109.494 | F67: ='ODOMETERS Tekrit'!K63 -> 173 | G67: 0.7821 | H67: ='Daily Tekrit'!$F67*'Daily Tekrit'!$G67 -> 135.3033 | I67: ='Daily Tekrit'!$C67+'Daily Tekrit'!$F67 -> 313 | J67: ='Daily Tekrit'!$E67+'Daily Tekrit'!$H67 -> 244.7973 | K67: ='ODOMETERS Tekrit'!L63 -> 222 | L67: 0.7453 | M67: ='Daily Tekrit'!$K67*'Daily Tekrit'!$L67 -> 165.4566 | T67: =750/89.7 -> 8.361204 | U67: ='Daily Tekrit'!$J67+'Daily Tekrit'!$M67+SUM($N67:$T67) -> 418.6151 | W67: =17 -> 17 | X67: =60+100*0.7453 -> 134.53 | AD67: =SUM(Z67:AC67) -> 0 | AM67: =SUM(AE67:AL67) -> 0 | AO67: =SUM(W67:Y67,AD67,AM67,AN67) -> 151.53 | AR67: =U67-AO67 -> 267.0851
A68: 46060 | C68: ='ODOMETERS Tekrit'!J64 -> 344 | D68: 0.7821 | E68: ='Daily Tekrit'!$C68*'Daily Tekrit'!$D68 -> 269.0424 | F68: ='ODOMETERS Tekrit'!K64 -> 148 | G68: 0.7821 | H68: ='Daily Tekrit'!$F68*'Daily Tekrit'!$G68 -> 115.7508 | I68: ='Daily Tekrit'!$C68+'Daily Tekrit'!$F68 -> 492 | J68: ='Daily Tekrit'!$E68+'Daily Tekrit'!$H68 -> 384.7932 | K68: ='ODOMETERS Tekrit'!L64 -> 245 | L68: 0.7453 | M68: ='Daily Tekrit'!$K68*'Daily Tekrit'!$L68 -> 182.5985 | N68: 8 | S68: 17 | U68: ='Daily Tekrit'!$J68+'Daily Tekrit'!$M68+SUM($N68:$T68) -> 592.3917 | AD68: =SUM(Z68:AC68) -> 0 | AM68: =SUM(AE68:AL68) -> 0 | AO68: =SUM(W68:Y68,AD68,AM68,AN68) -> 0 | AR68: =U68-AO68 -> 592.3917
A69: 46061 | C69: ='ODOMETERS Tekrit'!J65 -> 447 | D69: 0.7821 | E69: ='Daily Tekrit'!$C69*'Daily Tekrit'!$D69 -> 349.5987 | F69: ='ODOMETERS Tekrit'!K65 -> 424 | G69: 0.7821 | H69: ='Daily Tekrit'!$F69*'Daily Tekrit'!$G69 -> 331.6104 | I69: ='Daily Tekrit'!$C69+'Daily Tekrit'!$F69 -> 871 | J69: ='Daily Tekrit'!$E69+'Daily Tekrit'!$H69 -> 681.2091 | K69: ='ODOMETERS Tekrit'!L65 -> 234 | L69: 0.7453 | M69: ='Daily Tekrit'!$K69*'Daily Tekrit'!$L69 -> 174.4002 | N69: =600/89.7 -> 6.6889632 | U69: ='Daily Tekrit'!$J69+'Daily Tekrit'!$M69+SUM($N69:$T69) -> 862.29826 | Y69: -3 | AD69: =SUM(Z69:AC69) -> 0 | AM69: =SUM(AE69:AL69) -> 0 | AO69: =SUM(W69:Y69,AD69,AM69,AN69) -> -3 | AR69: =U69-AO69 -> 865.29826
